Metadata-Version: 2.2
Name: acryl-datahub
Version: 15.0.4
Summary: A CLI to work with DataHub metadata
Home-page: https://datahubproject.io/
License: Apache License 2.0
Project-URL: Documentation, https://datahubproject.io/docs/
Project-URL: Source, https://github.com/datahub-project/datahub
Project-URL: Changelog, https://github.com/datahub-project/datahub/releases
Project-URL: Releases, https://github.com/acryldata/datahub/releases
Classifier: Development Status :: 5 - Production/Stable
Classifier: Programming Language :: Python
Classifier: Programming Language :: Python :: 3
Classifier: Programming Language :: Python :: 3 :: Only
Classifier: Intended Audience :: Developers
Classifier: Intended Audience :: Information Technology
Classifier: Intended Audience :: System Administrators
Classifier: License :: OSI Approved
Classifier: License :: OSI Approved :: Apache Software License
Classifier: Operating System :: Unix
Classifier: Operating System :: POSIX :: Linux
Classifier: Environment :: Console
Classifier: Environment :: MacOS X
Classifier: Topic :: Software Development
Requires-Python: >=3.8
Requires-Dist: sentry-sdk
Requires-Dist: click-default-group
Requires-Dist: Deprecated
Requires-Dist: pydantic!=1.10.3,>=1.10.0
Requires-Dist: toml>=0.10.0
Requires-Dist: mixpanel>=4.9.0
Requires-Dist: avro<1.12,>=1.11.3
Requires-Dist: cached_property
Requires-Dist: click>=7.1.2
Requires-Dist: python-dateutil>=2.8.0
Requires-Dist: typing_extensions>=4.2.0
Requires-Dist: aiohttp<4
Requires-Dist: jsonref
Requires-Dist: docker
Requires-Dist: packaging
Requires-Dist: progressbar2
Requires-Dist: ijson
Requires-Dist: expandvars>=0.6.5
Requires-Dist: psutil>=5.8.0
Requires-Dist: jsonschema
Requires-Dist: avro-gen3==0.7.16
Requires-Dist: click-spinner
Requires-Dist: PyYAML
Requires-Dist: requests_file
Requires-Dist: tabulate
Requires-Dist: importlib_metadata>=4.0.0; python_version < "3.10"
Requires-Dist: humanfriendly
Requires-Dist: typing-inspect
Requires-Dist: ruamel.yaml
Provides-Extra: base
Requires-Dist: click-default-group; extra == "base"
Requires-Dist: Deprecated; extra == "base"
Requires-Dist: toml>=0.10.0; extra == "base"
Requires-Dist: avro<1.12,>=1.11.3; extra == "base"
Requires-Dist: cached_property; extra == "base"
Requires-Dist: click>=7.1.2; extra == "base"
Requires-Dist: python-dateutil>=2.8.0; extra == "base"
Requires-Dist: aiohttp<4; extra == "base"
Requires-Dist: jsonref; extra == "base"
Requires-Dist: docker; extra == "base"
Requires-Dist: packaging; extra == "base"
Requires-Dist: progressbar2; extra == "base"
Requires-Dist: ijson; extra == "base"
Requires-Dist: expandvars>=0.6.5; extra == "base"
Requires-Dist: psutil>=5.8.0; extra == "base"
Requires-Dist: jsonschema; extra == "base"
Requires-Dist: avro-gen3==0.7.16; extra == "base"
Requires-Dist: click-spinner; extra == "base"
Requires-Dist: PyYAML; extra == "base"
Requires-Dist: requests_file; extra == "base"
Requires-Dist: tabulate; extra == "base"
Requires-Dist: importlib_metadata>=4.0.0; python_version < "3.10" and extra == "base"
Requires-Dist: humanfriendly; extra == "base"
Requires-Dist: ruamel.yaml; extra == "base"
Provides-Extra: datahub-kafka
Requires-Dist: click-default-group; extra == "datahub-kafka"
Requires-Dist: Deprecated; extra == "datahub-kafka"
Requires-Dist: toml>=0.10.0; extra == "datahub-kafka"
Requires-Dist: avro<1.12,>=1.11.3; extra == "datahub-kafka"
Requires-Dist: cached_property; extra == "datahub-kafka"
Requires-Dist: click>=7.1.2; extra == "datahub-kafka"
Requires-Dist: python-dateutil>=2.8.0; extra == "datahub-kafka"
Requires-Dist: aiohttp<4; extra == "datahub-kafka"
Requires-Dist: jsonref; extra == "datahub-kafka"
Requires-Dist: docker; extra == "datahub-kafka"
Requires-Dist: packaging; extra == "datahub-kafka"
Requires-Dist: progressbar2; extra == "datahub-kafka"
Requires-Dist: ijson; extra == "datahub-kafka"
Requires-Dist: expandvars>=0.6.5; extra == "datahub-kafka"
Requires-Dist: psutil>=5.8.0; extra == "datahub-kafka"
Requires-Dist: jsonschema; extra == "datahub-kafka"
Requires-Dist: fastavro>=1.2.0; extra == "datahub-kafka"
Requires-Dist: avro-gen3==0.7.16; extra == "datahub-kafka"
Requires-Dist: click-spinner; extra == "datahub-kafka"
Requires-Dist: PyYAML; extra == "datahub-kafka"
Requires-Dist: requests_file; extra == "datahub-kafka"
Requires-Dist: tabulate; extra == "datahub-kafka"
Requires-Dist: importlib_metadata>=4.0.0; python_version < "3.10" and extra == "datahub-kafka"
Requires-Dist: confluent_kafka[schemaregistry]>=1.9.0; extra == "datahub-kafka"
Requires-Dist: humanfriendly; extra == "datahub-kafka"
Requires-Dist: ruamel.yaml; extra == "datahub-kafka"
Provides-Extra: datahub-rest
Requires-Dist: requests; extra == "datahub-rest"
Requires-Dist: click-default-group; extra == "datahub-rest"
Requires-Dist: Deprecated; extra == "datahub-rest"
Requires-Dist: toml>=0.10.0; extra == "datahub-rest"
Requires-Dist: avro<1.12,>=1.11.3; extra == "datahub-rest"
Requires-Dist: cached_property; extra == "datahub-rest"
Requires-Dist: click>=7.1.2; extra == "datahub-rest"
Requires-Dist: python-dateutil>=2.8.0; extra == "datahub-rest"
Requires-Dist: aiohttp<4; extra == "datahub-rest"
Requires-Dist: jsonref; extra == "datahub-rest"
Requires-Dist: docker; extra == "datahub-rest"
Requires-Dist: packaging; extra == "datahub-rest"
Requires-Dist: progressbar2; extra == "datahub-rest"
Requires-Dist: ijson; extra == "datahub-rest"
Requires-Dist: expandvars>=0.6.5; extra == "datahub-rest"
Requires-Dist: psutil>=5.8.0; extra == "datahub-rest"
Requires-Dist: jsonschema; extra == "datahub-rest"
Requires-Dist: avro-gen3==0.7.16; extra == "datahub-rest"
Requires-Dist: click-spinner; extra == "datahub-rest"
Requires-Dist: PyYAML; extra == "datahub-rest"
Requires-Dist: requests_file; extra == "datahub-rest"
Requires-Dist: tabulate; extra == "datahub-rest"
Requires-Dist: importlib_metadata>=4.0.0; python_version < "3.10" and extra == "datahub-rest"
Requires-Dist: humanfriendly; extra == "datahub-rest"
Requires-Dist: ruamel.yaml; extra == "datahub-rest"
Provides-Extra: sync-file-emitter
Requires-Dist: click-default-group; extra == "sync-file-emitter"
Requires-Dist: Deprecated; extra == "sync-file-emitter"
Requires-Dist: filelock; extra == "sync-file-emitter"
Requires-Dist: toml>=0.10.0; extra == "sync-file-emitter"
Requires-Dist: avro<1.12,>=1.11.3; extra == "sync-file-emitter"
Requires-Dist: cached_property; extra == "sync-file-emitter"
Requires-Dist: click>=7.1.2; extra == "sync-file-emitter"
Requires-Dist: python-dateutil>=2.8.0; extra == "sync-file-emitter"
Requires-Dist: aiohttp<4; extra == "sync-file-emitter"
Requires-Dist: jsonref; extra == "sync-file-emitter"
Requires-Dist: docker; extra == "sync-file-emitter"
Requires-Dist: packaging; extra == "sync-file-emitter"
Requires-Dist: progressbar2; extra == "sync-file-emitter"
Requires-Dist: ijson; extra == "sync-file-emitter"
Requires-Dist: expandvars>=0.6.5; extra == "sync-file-emitter"
Requires-Dist: psutil>=5.8.0; extra == "sync-file-emitter"
Requires-Dist: jsonschema; extra == "sync-file-emitter"
Requires-Dist: avro-gen3==0.7.16; extra == "sync-file-emitter"
Requires-Dist: click-spinner; extra == "sync-file-emitter"
Requires-Dist: PyYAML; extra == "sync-file-emitter"
Requires-Dist: requests_file; extra == "sync-file-emitter"
Requires-Dist: tabulate; extra == "sync-file-emitter"
Requires-Dist: importlib_metadata>=4.0.0; python_version < "3.10" and extra == "sync-file-emitter"
Requires-Dist: humanfriendly; extra == "sync-file-emitter"
Requires-Dist: ruamel.yaml; extra == "sync-file-emitter"
Provides-Extra: datahub-lite
Requires-Dist: click-default-group; extra == "datahub-lite"
Requires-Dist: Deprecated; extra == "datahub-lite"
Requires-Dist: toml>=0.10.0; extra == "datahub-lite"
Requires-Dist: duckdb; extra == "datahub-lite"
Requires-Dist: pydantic<2; extra == "datahub-lite"
Requires-Dist: avro<1.12,>=1.11.3; extra == "datahub-lite"
Requires-Dist: cached_property; extra == "datahub-lite"
Requires-Dist: click>=7.1.2; extra == "datahub-lite"
Requires-Dist: python-dateutil>=2.8.0; extra == "datahub-lite"
Requires-Dist: aiohttp<4; extra == "datahub-lite"
Requires-Dist: jsonref; extra == "datahub-lite"
Requires-Dist: docker; extra == "datahub-lite"
Requires-Dist: packaging; extra == "datahub-lite"
Requires-Dist: progressbar2; extra == "datahub-lite"
Requires-Dist: ijson; extra == "datahub-lite"
Requires-Dist: expandvars>=0.6.5; extra == "datahub-lite"
Requires-Dist: psutil>=5.8.0; extra == "datahub-lite"
Requires-Dist: jsonschema; extra == "datahub-lite"
Requires-Dist: avro-gen3==0.7.16; extra == "datahub-lite"
Requires-Dist: click-spinner; extra == "datahub-lite"
Requires-Dist: PyYAML; extra == "datahub-lite"
Requires-Dist: requests_file; extra == "datahub-lite"
Requires-Dist: tabulate; extra == "datahub-lite"
Requires-Dist: importlib_metadata>=4.0.0; python_version < "3.10" and extra == "datahub-lite"
Requires-Dist: uvicorn; extra == "datahub-lite"
Requires-Dist: humanfriendly; extra == "datahub-lite"
Requires-Dist: fastapi; extra == "datahub-lite"
Requires-Dist: ruamel.yaml; extra == "datahub-lite"
Provides-Extra: airflow
Requires-Dist: click-default-group; extra == "airflow"
Requires-Dist: Deprecated; extra == "airflow"
Requires-Dist: acryl-datahub-airflow-plugin==15.0.4; extra == "airflow"
Requires-Dist: toml>=0.10.0; extra == "airflow"
Requires-Dist: avro<1.12,>=1.11.3; extra == "airflow"
Requires-Dist: cached_property; extra == "airflow"
Requires-Dist: click>=7.1.2; extra == "airflow"
Requires-Dist: python-dateutil>=2.8.0; extra == "airflow"
Requires-Dist: aiohttp<4; extra == "airflow"
Requires-Dist: jsonref; extra == "airflow"
Requires-Dist: docker; extra == "airflow"
Requires-Dist: packaging; extra == "airflow"
Requires-Dist: progressbar2; extra == "airflow"
Requires-Dist: ijson; extra == "airflow"
Requires-Dist: expandvars>=0.6.5; extra == "airflow"
Requires-Dist: psutil>=5.8.0; extra == "airflow"
Requires-Dist: jsonschema; extra == "airflow"
Requires-Dist: avro-gen3==0.7.16; extra == "airflow"
Requires-Dist: click-spinner; extra == "airflow"
Requires-Dist: PyYAML; extra == "airflow"
Requires-Dist: requests_file; extra == "airflow"
Requires-Dist: tabulate; extra == "airflow"
Requires-Dist: importlib_metadata>=4.0.0; python_version < "3.10" and extra == "airflow"
Requires-Dist: humanfriendly; extra == "airflow"
Requires-Dist: ruamel.yaml; extra == "airflow"
Provides-Extra: circuit-breaker
Requires-Dist: click-default-group; extra == "circuit-breaker"
Requires-Dist: Deprecated; extra == "circuit-breaker"
Requires-Dist: toml>=0.10.0; extra == "circuit-breaker"
Requires-Dist: pydantic<2; extra == "circuit-breaker"
Requires-Dist: avro<1.12,>=1.11.3; extra == "circuit-breaker"
Requires-Dist: cached_property; extra == "circuit-breaker"
Requires-Dist: click>=7.1.2; extra == "circuit-breaker"
Requires-Dist: python-dateutil>=2.8.0; extra == "circuit-breaker"
Requires-Dist: aiohttp<4; extra == "circuit-breaker"
Requires-Dist: jsonref; extra == "circuit-breaker"
Requires-Dist: docker; extra == "circuit-breaker"
Requires-Dist: packaging; extra == "circuit-breaker"
Requires-Dist: progressbar2; extra == "circuit-breaker"
Requires-Dist: ijson; extra == "circuit-breaker"
Requires-Dist: expandvars>=0.6.5; extra == "circuit-breaker"
Requires-Dist: psutil>=5.8.0; extra == "circuit-breaker"
Requires-Dist: jsonschema; extra == "circuit-breaker"
Requires-Dist: avro-gen3==0.7.16; extra == "circuit-breaker"
Requires-Dist: click-spinner; extra == "circuit-breaker"
Requires-Dist: PyYAML; extra == "circuit-breaker"
Requires-Dist: requests_file; extra == "circuit-breaker"
Requires-Dist: tabulate; extra == "circuit-breaker"
Requires-Dist: importlib_metadata>=4.0.0; python_version < "3.10" and extra == "circuit-breaker"
Requires-Dist: humanfriendly; extra == "circuit-breaker"
Requires-Dist: gql[requests]>=3.3.0; extra == "circuit-breaker"
Requires-Dist: gql>=3.3.0; extra == "circuit-breaker"
Requires-Dist: ruamel.yaml; extra == "circuit-breaker"
Provides-Extra: datahub
Requires-Dist: toml>=0.10.0; extra == "datahub"
Requires-Dist: pydantic<2; extra == "datahub"
Requires-Dist: sqlalchemy<2,>=1.4.39; extra == "datahub"
Requires-Dist: cached_property; extra == "datahub"
Requires-Dist: click>=7.1.2; extra == "datahub"
Requires-Dist: scipy>=1.7.2; extra == "datahub"
Requires-Dist: schwifty<2024.08.0; extra == "datahub"
Requires-Dist: docker; extra == "datahub"
Requires-Dist: progressbar2; extra == "datahub"
Requires-Dist: patchy==2.8.0; extra == "datahub"
Requires-Dist: expandvars>=0.6.5; extra == "datahub"
Requires-Dist: traitlets!=5.2.2; extra == "datahub"
Requires-Dist: psutil>=5.8.0; extra == "datahub"
Requires-Dist: avro-gen3==0.7.16; extra == "datahub"
Requires-Dist: cachetools; extra == "datahub"
Requires-Dist: PyYAML; extra == "datahub"
Requires-Dist: requests_file; extra == "datahub"
Requires-Dist: confluent_kafka[schemaregistry]>=1.9.0; extra == "datahub"
Requires-Dist: importlib_metadata>=4.0.0; python_version < "3.10" and extra == "datahub"
Requires-Dist: click-default-group; extra == "datahub"
Requires-Dist: Deprecated; extra == "datahub"
Requires-Dist: IPython!=8.22.0; extra == "datahub"
Requires-Dist: pip; extra == "datahub"
Requires-Dist: avro<1.12,>=1.11.3; extra == "datahub"
Requires-Dist: acryl-datahub-classify==0.0.11; extra == "datahub"
Requires-Dist: python-dateutil>=2.8.0; extra == "datahub"
Requires-Dist: aiohttp<4; extra == "datahub"
Requires-Dist: jsonref; extra == "datahub"
Requires-Dist: sqlglot[rs]==25.32.1; extra == "datahub"
Requires-Dist: packaging; extra == "datahub"
Requires-Dist: ijson; extra == "datahub"
Requires-Dist: jsonschema; extra == "datahub"
Requires-Dist: greenlet; extra == "datahub"
Requires-Dist: fastavro>=1.2.0; extra == "datahub"
Requires-Dist: click-spinner; extra == "datahub"
Requires-Dist: numpy<2; extra == "datahub"
Requires-Dist: pymysql>=1.0.2; extra == "datahub"
Requires-Dist: great-expectations<=0.15.50,>=0.15.12; extra == "datahub"
Requires-Dist: tabulate; extra == "datahub"
Requires-Dist: humanfriendly; extra == "datahub"
Requires-Dist: sqlparse; extra == "datahub"
Requires-Dist: ruamel.yaml; extra == "datahub"
Provides-Extra: great-expectations
Requires-Dist: click-default-group; extra == "great-expectations"
Requires-Dist: Deprecated; extra == "great-expectations"
Requires-Dist: toml>=0.10.0; extra == "great-expectations"
Requires-Dist: pydantic<2; extra == "great-expectations"
Requires-Dist: avro<1.12,>=1.11.3; extra == "great-expectations"
Requires-Dist: cached_property; extra == "great-expectations"
Requires-Dist: click>=7.1.2; extra == "great-expectations"
Requires-Dist: python-dateutil>=2.8.0; extra == "great-expectations"
Requires-Dist: aiohttp<4; extra == "great-expectations"
Requires-Dist: jsonref; extra == "great-expectations"
Requires-Dist: acryl-datahub-gx-plugin==15.0.4; extra == "great-expectations"
Requires-Dist: docker; extra == "great-expectations"
Requires-Dist: packaging; extra == "great-expectations"
Requires-Dist: progressbar2; extra == "great-expectations"
Requires-Dist: ijson; extra == "great-expectations"
Requires-Dist: expandvars>=0.6.5; extra == "great-expectations"
Requires-Dist: psutil>=5.8.0; extra == "great-expectations"
Requires-Dist: jsonschema; extra == "great-expectations"
Requires-Dist: avro-gen3==0.7.16; extra == "great-expectations"
Requires-Dist: click-spinner; extra == "great-expectations"
Requires-Dist: PyYAML; extra == "great-expectations"
Requires-Dist: requests_file; extra == "great-expectations"
Requires-Dist: tabulate; extra == "great-expectations"
Requires-Dist: importlib_metadata>=4.0.0; python_version < "3.10" and extra == "great-expectations"
Requires-Dist: humanfriendly; extra == "great-expectations"
Requires-Dist: ruamel.yaml; extra == "great-expectations"
Provides-Extra: sql-parser
Requires-Dist: click-default-group; extra == "sql-parser"
Requires-Dist: Deprecated; extra == "sql-parser"
Requires-Dist: toml>=0.10.0; extra == "sql-parser"
Requires-Dist: avro<1.12,>=1.11.3; extra == "sql-parser"
Requires-Dist: cached_property; extra == "sql-parser"
Requires-Dist: click>=7.1.2; extra == "sql-parser"
Requires-Dist: python-dateutil>=2.8.0; extra == "sql-parser"
Requires-Dist: aiohttp<4; extra == "sql-parser"
Requires-Dist: jsonref; extra == "sql-parser"
Requires-Dist: docker; extra == "sql-parser"
Requires-Dist: sqlglot[rs]==25.32.1; extra == "sql-parser"
Requires-Dist: packaging; extra == "sql-parser"
Requires-Dist: progressbar2; extra == "sql-parser"
Requires-Dist: ijson; extra == "sql-parser"
Requires-Dist: patchy==2.8.0; extra == "sql-parser"
Requires-Dist: expandvars>=0.6.5; extra == "sql-parser"
Requires-Dist: psutil>=5.8.0; extra == "sql-parser"
Requires-Dist: jsonschema; extra == "sql-parser"
Requires-Dist: avro-gen3==0.7.16; extra == "sql-parser"
Requires-Dist: click-spinner; extra == "sql-parser"
Requires-Dist: PyYAML; extra == "sql-parser"
Requires-Dist: requests_file; extra == "sql-parser"
Requires-Dist: tabulate; extra == "sql-parser"
Requires-Dist: importlib_metadata>=4.0.0; python_version < "3.10" and extra == "sql-parser"
Requires-Dist: humanfriendly; extra == "sql-parser"
Requires-Dist: ruamel.yaml; extra == "sql-parser"
Provides-Extra: athena
Requires-Dist: toml>=0.10.0; extra == "athena"
Requires-Dist: pydantic<2; extra == "athena"
Requires-Dist: sqlalchemy<2,>=1.4.39; extra == "athena"
Requires-Dist: cached_property; extra == "athena"
Requires-Dist: click>=7.1.2; extra == "athena"
Requires-Dist: scipy>=1.7.2; extra == "athena"
Requires-Dist: schwifty<2024.08.0; extra == "athena"
Requires-Dist: docker; extra == "athena"
Requires-Dist: progressbar2; extra == "athena"
Requires-Dist: patchy==2.8.0; extra == "athena"
Requires-Dist: expandvars>=0.6.5; extra == "athena"
Requires-Dist: traitlets!=5.2.2; extra == "athena"
Requires-Dist: psutil>=5.8.0; extra == "athena"
Requires-Dist: avro-gen3==0.7.16; extra == "athena"
Requires-Dist: cachetools; extra == "athena"
Requires-Dist: PyYAML; extra == "athena"
Requires-Dist: requests_file; extra == "athena"
Requires-Dist: importlib_metadata>=4.0.0; python_version < "3.10" and extra == "athena"
Requires-Dist: tenacity!=8.4.0; extra == "athena"
Requires-Dist: click-default-group; extra == "athena"
Requires-Dist: Deprecated; extra == "athena"
Requires-Dist: IPython!=8.22.0; extra == "athena"
Requires-Dist: pip; extra == "athena"
Requires-Dist: avro<1.12,>=1.11.3; extra == "athena"
Requires-Dist: acryl-datahub-classify==0.0.11; extra == "athena"
Requires-Dist: python-dateutil>=2.8.0; extra == "athena"
Requires-Dist: aiohttp<4; extra == "athena"
Requires-Dist: jsonref; extra == "athena"
Requires-Dist: sqlglot[rs]==25.32.1; extra == "athena"
Requires-Dist: packaging; extra == "athena"
Requires-Dist: ijson; extra == "athena"
Requires-Dist: sqlalchemy-bigquery>=1.4.1; extra == "athena"
Requires-Dist: jsonschema; extra == "athena"
Requires-Dist: greenlet; extra == "athena"
Requires-Dist: PyAthena[SQLAlchemy]<3.0.0,>=2.6.0; extra == "athena"
Requires-Dist: click-spinner; extra == "athena"
Requires-Dist: numpy<2; extra == "athena"
Requires-Dist: great-expectations<=0.15.50,>=0.15.12; extra == "athena"
Requires-Dist: tabulate; extra == "athena"
Requires-Dist: humanfriendly; extra == "athena"
Requires-Dist: sqlparse; extra == "athena"
Requires-Dist: ruamel.yaml; extra == "athena"
Provides-Extra: azure-ad
Requires-Dist: click-default-group; extra == "azure-ad"
Requires-Dist: Deprecated; extra == "azure-ad"
Requires-Dist: toml>=0.10.0; extra == "azure-ad"
Requires-Dist: pydantic<2; extra == "azure-ad"
Requires-Dist: avro<1.12,>=1.11.3; extra == "azure-ad"
Requires-Dist: cached_property; extra == "azure-ad"
Requires-Dist: click>=7.1.2; extra == "azure-ad"
Requires-Dist: python-dateutil>=2.8.0; extra == "azure-ad"
Requires-Dist: aiohttp<4; extra == "azure-ad"
Requires-Dist: jsonref; extra == "azure-ad"
Requires-Dist: docker; extra == "azure-ad"
Requires-Dist: packaging; extra == "azure-ad"
Requires-Dist: progressbar2; extra == "azure-ad"
Requires-Dist: ijson; extra == "azure-ad"
Requires-Dist: expandvars>=0.6.5; extra == "azure-ad"
Requires-Dist: psutil>=5.8.0; extra == "azure-ad"
Requires-Dist: jsonschema; extra == "azure-ad"
Requires-Dist: avro-gen3==0.7.16; extra == "azure-ad"
Requires-Dist: click-spinner; extra == "azure-ad"
Requires-Dist: PyYAML; extra == "azure-ad"
Requires-Dist: requests_file; extra == "azure-ad"
Requires-Dist: tabulate; extra == "azure-ad"
Requires-Dist: importlib_metadata>=4.0.0; python_version < "3.10" and extra == "azure-ad"
Requires-Dist: humanfriendly; extra == "azure-ad"
Requires-Dist: ruamel.yaml; extra == "azure-ad"
Provides-Extra: bigquery
Requires-Dist: toml>=0.10.0; extra == "bigquery"
Requires-Dist: pydantic<2; extra == "bigquery"
Requires-Dist: sqlalchemy<2,>=1.4.39; extra == "bigquery"
Requires-Dist: cached_property; extra == "bigquery"
Requires-Dist: click>=7.1.2; extra == "bigquery"
Requires-Dist: parse>=1.19.0; extra == "bigquery"
Requires-Dist: google-cloud-datacatalog-lineage==0.2.2; extra == "bigquery"
Requires-Dist: scipy>=1.7.2; extra == "bigquery"
Requires-Dist: schwifty<2024.08.0; extra == "bigquery"
Requires-Dist: docker; extra == "bigquery"
Requires-Dist: google-cloud-resource-manager; extra == "bigquery"
Requires-Dist: progressbar2; extra == "bigquery"
Requires-Dist: patchy==2.8.0; extra == "bigquery"
Requires-Dist: google-cloud-logging<=3.5.0; extra == "bigquery"
Requires-Dist: expandvars>=0.6.5; extra == "bigquery"
Requires-Dist: traitlets!=5.2.2; extra == "bigquery"
Requires-Dist: psutil>=5.8.0; extra == "bigquery"
Requires-Dist: google-cloud-datacatalog>=1.5.0; extra == "bigquery"
Requires-Dist: avro-gen3==0.7.16; extra == "bigquery"
Requires-Dist: cachetools; extra == "bigquery"
Requires-Dist: PyYAML; extra == "bigquery"
Requires-Dist: requests_file; extra == "bigquery"
Requires-Dist: importlib_metadata>=4.0.0; python_version < "3.10" and extra == "bigquery"
Requires-Dist: google-cloud-bigquery; extra == "bigquery"
Requires-Dist: wcmatch; extra == "bigquery"
Requires-Dist: click-default-group; extra == "bigquery"
Requires-Dist: Deprecated; extra == "bigquery"
Requires-Dist: IPython!=8.22.0; extra == "bigquery"
Requires-Dist: pip; extra == "bigquery"
Requires-Dist: avro<1.12,>=1.11.3; extra == "bigquery"
Requires-Dist: acryl-datahub-classify==0.0.11; extra == "bigquery"
Requires-Dist: python-dateutil>=2.8.0; extra == "bigquery"
Requires-Dist: aiohttp<4; extra == "bigquery"
Requires-Dist: jsonref; extra == "bigquery"
Requires-Dist: more-itertools>=8.12.0; extra == "bigquery"
Requires-Dist: sqlglot[rs]==25.32.1; extra == "bigquery"
Requires-Dist: packaging; extra == "bigquery"
Requires-Dist: ijson; extra == "bigquery"
Requires-Dist: sqlalchemy-bigquery>=1.4.1; extra == "bigquery"
Requires-Dist: jsonschema; extra == "bigquery"
Requires-Dist: greenlet; extra == "bigquery"
Requires-Dist: click-spinner; extra == "bigquery"
Requires-Dist: numpy<2; extra == "bigquery"
Requires-Dist: great-expectations<=0.15.50,>=0.15.12; extra == "bigquery"
Requires-Dist: tabulate; extra == "bigquery"
Requires-Dist: humanfriendly; extra == "bigquery"
Requires-Dist: sqlparse; extra == "bigquery"
Requires-Dist: ruamel.yaml; extra == "bigquery"
Provides-Extra: bigquery-queries
Requires-Dist: toml>=0.10.0; extra == "bigquery-queries"
Requires-Dist: pydantic<2; extra == "bigquery-queries"
Requires-Dist: sqlalchemy<2,>=1.4.39; extra == "bigquery-queries"
Requires-Dist: cached_property; extra == "bigquery-queries"
Requires-Dist: click>=7.1.2; extra == "bigquery-queries"
Requires-Dist: parse>=1.19.0; extra == "bigquery-queries"
Requires-Dist: scipy>=1.7.2; extra == "bigquery-queries"
Requires-Dist: schwifty<2024.08.0; extra == "bigquery-queries"
Requires-Dist: docker; extra == "bigquery-queries"
Requires-Dist: google-cloud-resource-manager; extra == "bigquery-queries"
Requires-Dist: progressbar2; extra == "bigquery-queries"
Requires-Dist: patchy==2.8.0; extra == "bigquery-queries"
Requires-Dist: google-cloud-logging<=3.5.0; extra == "bigquery-queries"
Requires-Dist: expandvars>=0.6.5; extra == "bigquery-queries"
Requires-Dist: traitlets!=5.2.2; extra == "bigquery-queries"
Requires-Dist: psutil>=5.8.0; extra == "bigquery-queries"
Requires-Dist: google-cloud-datacatalog>=1.5.0; extra == "bigquery-queries"
Requires-Dist: avro-gen3==0.7.16; extra == "bigquery-queries"
Requires-Dist: cachetools; extra == "bigquery-queries"
Requires-Dist: PyYAML; extra == "bigquery-queries"
Requires-Dist: requests_file; extra == "bigquery-queries"
Requires-Dist: importlib_metadata>=4.0.0; python_version < "3.10" and extra == "bigquery-queries"
Requires-Dist: google-cloud-bigquery; extra == "bigquery-queries"
Requires-Dist: wcmatch; extra == "bigquery-queries"
Requires-Dist: click-default-group; extra == "bigquery-queries"
Requires-Dist: Deprecated; extra == "bigquery-queries"
Requires-Dist: IPython!=8.22.0; extra == "bigquery-queries"
Requires-Dist: pip; extra == "bigquery-queries"
Requires-Dist: avro<1.12,>=1.11.3; extra == "bigquery-queries"
Requires-Dist: acryl-datahub-classify==0.0.11; extra == "bigquery-queries"
Requires-Dist: python-dateutil>=2.8.0; extra == "bigquery-queries"
Requires-Dist: aiohttp<4; extra == "bigquery-queries"
Requires-Dist: jsonref; extra == "bigquery-queries"
Requires-Dist: more-itertools>=8.12.0; extra == "bigquery-queries"
Requires-Dist: sqlglot[rs]==25.32.1; extra == "bigquery-queries"
Requires-Dist: packaging; extra == "bigquery-queries"
Requires-Dist: ijson; extra == "bigquery-queries"
Requires-Dist: sqlalchemy-bigquery>=1.4.1; extra == "bigquery-queries"
Requires-Dist: jsonschema; extra == "bigquery-queries"
Requires-Dist: greenlet; extra == "bigquery-queries"
Requires-Dist: click-spinner; extra == "bigquery-queries"
Requires-Dist: numpy<2; extra == "bigquery-queries"
Requires-Dist: great-expectations<=0.15.50,>=0.15.12; extra == "bigquery-queries"
Requires-Dist: tabulate; extra == "bigquery-queries"
Requires-Dist: humanfriendly; extra == "bigquery-queries"
Requires-Dist: sqlparse; extra == "bigquery-queries"
Requires-Dist: ruamel.yaml; extra == "bigquery-queries"
Provides-Extra: clickhouse
Requires-Dist: toml>=0.10.0; extra == "clickhouse"
Requires-Dist: pydantic<2; extra == "clickhouse"
Requires-Dist: sqlalchemy<2,>=1.4.39; extra == "clickhouse"
Requires-Dist: cached_property; extra == "clickhouse"
Requires-Dist: click>=7.1.2; extra == "clickhouse"
Requires-Dist: scipy>=1.7.2; extra == "clickhouse"
Requires-Dist: schwifty<2024.08.0; extra == "clickhouse"
Requires-Dist: docker; extra == "clickhouse"
Requires-Dist: clickhouse-sqlalchemy<0.2.5,>=0.2.0; extra == "clickhouse"
Requires-Dist: progressbar2; extra == "clickhouse"
Requires-Dist: patchy==2.8.0; extra == "clickhouse"
Requires-Dist: expandvars>=0.6.5; extra == "clickhouse"
Requires-Dist: traitlets!=5.2.2; extra == "clickhouse"
Requires-Dist: psutil>=5.8.0; extra == "clickhouse"
Requires-Dist: avro-gen3==0.7.16; extra == "clickhouse"
Requires-Dist: cachetools; extra == "clickhouse"
Requires-Dist: PyYAML; extra == "clickhouse"
Requires-Dist: requests_file; extra == "clickhouse"
Requires-Dist: importlib_metadata>=4.0.0; python_version < "3.10" and extra == "clickhouse"
Requires-Dist: click-default-group; extra == "clickhouse"
Requires-Dist: Deprecated; extra == "clickhouse"
Requires-Dist: IPython!=8.22.0; extra == "clickhouse"
Requires-Dist: pip; extra == "clickhouse"
Requires-Dist: avro<1.12,>=1.11.3; extra == "clickhouse"
Requires-Dist: acryl-datahub-classify==0.0.11; extra == "clickhouse"
Requires-Dist: python-dateutil>=2.8.0; extra == "clickhouse"
Requires-Dist: aiohttp<4; extra == "clickhouse"
Requires-Dist: jsonref; extra == "clickhouse"
Requires-Dist: sqlglot[rs]==25.32.1; extra == "clickhouse"
Requires-Dist: packaging; extra == "clickhouse"
Requires-Dist: ijson; extra == "clickhouse"
Requires-Dist: jsonschema; extra == "clickhouse"
Requires-Dist: greenlet; extra == "clickhouse"
Requires-Dist: click-spinner; extra == "clickhouse"
Requires-Dist: numpy<2; extra == "clickhouse"
Requires-Dist: great-expectations<=0.15.50,>=0.15.12; extra == "clickhouse"
Requires-Dist: tabulate; extra == "clickhouse"
Requires-Dist: humanfriendly; extra == "clickhouse"
Requires-Dist: sqlparse; extra == "clickhouse"
Requires-Dist: ruamel.yaml; extra == "clickhouse"
Provides-Extra: clickhouse-usage
Requires-Dist: toml>=0.10.0; extra == "clickhouse-usage"
Requires-Dist: pydantic<2; extra == "clickhouse-usage"
Requires-Dist: sqlalchemy<2,>=1.4.39; extra == "clickhouse-usage"
Requires-Dist: cached_property; extra == "clickhouse-usage"
Requires-Dist: click>=7.1.2; extra == "clickhouse-usage"
Requires-Dist: scipy>=1.7.2; extra == "clickhouse-usage"
Requires-Dist: schwifty<2024.08.0; extra == "clickhouse-usage"
Requires-Dist: docker; extra == "clickhouse-usage"
Requires-Dist: clickhouse-sqlalchemy<0.2.5,>=0.2.0; extra == "clickhouse-usage"
Requires-Dist: progressbar2; extra == "clickhouse-usage"
Requires-Dist: patchy==2.8.0; extra == "clickhouse-usage"
Requires-Dist: expandvars>=0.6.5; extra == "clickhouse-usage"
Requires-Dist: traitlets!=5.2.2; extra == "clickhouse-usage"
Requires-Dist: psutil>=5.8.0; extra == "clickhouse-usage"
Requires-Dist: avro-gen3==0.7.16; extra == "clickhouse-usage"
Requires-Dist: cachetools; extra == "clickhouse-usage"
Requires-Dist: PyYAML; extra == "clickhouse-usage"
Requires-Dist: requests_file; extra == "clickhouse-usage"
Requires-Dist: importlib_metadata>=4.0.0; python_version < "3.10" and extra == "clickhouse-usage"
Requires-Dist: click-default-group; extra == "clickhouse-usage"
Requires-Dist: Deprecated; extra == "clickhouse-usage"
Requires-Dist: IPython!=8.22.0; extra == "clickhouse-usage"
Requires-Dist: pip; extra == "clickhouse-usage"
Requires-Dist: avro<1.12,>=1.11.3; extra == "clickhouse-usage"
Requires-Dist: acryl-datahub-classify==0.0.11; extra == "clickhouse-usage"
Requires-Dist: python-dateutil>=2.8.0; extra == "clickhouse-usage"
Requires-Dist: aiohttp<4; extra == "clickhouse-usage"
Requires-Dist: jsonref; extra == "clickhouse-usage"
Requires-Dist: sqlglot[rs]==25.32.1; extra == "clickhouse-usage"
Requires-Dist: packaging; extra == "clickhouse-usage"
Requires-Dist: ijson; extra == "clickhouse-usage"
Requires-Dist: jsonschema; extra == "clickhouse-usage"
Requires-Dist: greenlet; extra == "clickhouse-usage"
Requires-Dist: click-spinner; extra == "clickhouse-usage"
Requires-Dist: numpy<2; extra == "clickhouse-usage"
Requires-Dist: great-expectations<=0.15.50,>=0.15.12; extra == "clickhouse-usage"
Requires-Dist: tabulate; extra == "clickhouse-usage"
Requires-Dist: humanfriendly; extra == "clickhouse-usage"
Requires-Dist: sqlparse; extra == "clickhouse-usage"
Requires-Dist: ruamel.yaml; extra == "clickhouse-usage"
Provides-Extra: cockroachdb
Requires-Dist: toml>=0.10.0; extra == "cockroachdb"
Requires-Dist: pydantic<2; extra == "cockroachdb"
Requires-Dist: sqlalchemy<2,>=1.4.39; extra == "cockroachdb"
Requires-Dist: cached_property; extra == "cockroachdb"
Requires-Dist: click>=7.1.2; extra == "cockroachdb"
Requires-Dist: scipy>=1.7.2; extra == "cockroachdb"
Requires-Dist: schwifty<2024.08.0; extra == "cockroachdb"
Requires-Dist: docker; extra == "cockroachdb"
Requires-Dist: progressbar2; extra == "cockroachdb"
Requires-Dist: patchy==2.8.0; extra == "cockroachdb"
Requires-Dist: expandvars>=0.6.5; extra == "cockroachdb"
Requires-Dist: traitlets!=5.2.2; extra == "cockroachdb"
Requires-Dist: psutil>=5.8.0; extra == "cockroachdb"
Requires-Dist: avro-gen3==0.7.16; extra == "cockroachdb"
Requires-Dist: cachetools; extra == "cockroachdb"
Requires-Dist: PyYAML; extra == "cockroachdb"
Requires-Dist: requests_file; extra == "cockroachdb"
Requires-Dist: importlib_metadata>=4.0.0; python_version < "3.10" and extra == "cockroachdb"
Requires-Dist: GeoAlchemy2; extra == "cockroachdb"
Requires-Dist: click-default-group; extra == "cockroachdb"
Requires-Dist: Deprecated; extra == "cockroachdb"
Requires-Dist: IPython!=8.22.0; extra == "cockroachdb"
Requires-Dist: pip; extra == "cockroachdb"
Requires-Dist: avro<1.12,>=1.11.3; extra == "cockroachdb"
Requires-Dist: acryl-datahub-classify==0.0.11; extra == "cockroachdb"
Requires-Dist: python-dateutil>=2.8.0; extra == "cockroachdb"
Requires-Dist: aiohttp<4; extra == "cockroachdb"
Requires-Dist: jsonref; extra == "cockroachdb"
Requires-Dist: sqlglot[rs]==25.32.1; extra == "cockroachdb"
Requires-Dist: packaging; extra == "cockroachdb"
Requires-Dist: ijson; extra == "cockroachdb"
Requires-Dist: sqlalchemy-cockroachdb<2.0.0; extra == "cockroachdb"
Requires-Dist: psycopg2-binary; extra == "cockroachdb"
Requires-Dist: jsonschema; extra == "cockroachdb"
Requires-Dist: greenlet; extra == "cockroachdb"
Requires-Dist: click-spinner; extra == "cockroachdb"
Requires-Dist: numpy<2; extra == "cockroachdb"
Requires-Dist: great-expectations<=0.15.50,>=0.15.12; extra == "cockroachdb"
Requires-Dist: tabulate; extra == "cockroachdb"
Requires-Dist: humanfriendly; extra == "cockroachdb"
Requires-Dist: sqlparse; extra == "cockroachdb"
Requires-Dist: ruamel.yaml; extra == "cockroachdb"
Provides-Extra: datahub-lineage-file
Requires-Dist: click-default-group; extra == "datahub-lineage-file"
Requires-Dist: Deprecated; extra == "datahub-lineage-file"
Requires-Dist: toml>=0.10.0; extra == "datahub-lineage-file"
Requires-Dist: pydantic<2; extra == "datahub-lineage-file"
Requires-Dist: avro<1.12,>=1.11.3; extra == "datahub-lineage-file"
Requires-Dist: cached_property; extra == "datahub-lineage-file"
Requires-Dist: click>=7.1.2; extra == "datahub-lineage-file"
Requires-Dist: python-dateutil>=2.8.0; extra == "datahub-lineage-file"
Requires-Dist: aiohttp<4; extra == "datahub-lineage-file"
Requires-Dist: jsonref; extra == "datahub-lineage-file"
Requires-Dist: docker; extra == "datahub-lineage-file"
Requires-Dist: packaging; extra == "datahub-lineage-file"
Requires-Dist: progressbar2; extra == "datahub-lineage-file"
Requires-Dist: ijson; extra == "datahub-lineage-file"
Requires-Dist: expandvars>=0.6.5; extra == "datahub-lineage-file"
Requires-Dist: psutil>=5.8.0; extra == "datahub-lineage-file"
Requires-Dist: jsonschema; extra == "datahub-lineage-file"
Requires-Dist: avro-gen3==0.7.16; extra == "datahub-lineage-file"
Requires-Dist: click-spinner; extra == "datahub-lineage-file"
Requires-Dist: PyYAML; extra == "datahub-lineage-file"
Requires-Dist: requests_file; extra == "datahub-lineage-file"
Requires-Dist: tabulate; extra == "datahub-lineage-file"
Requires-Dist: importlib_metadata>=4.0.0; python_version < "3.10" and extra == "datahub-lineage-file"
Requires-Dist: humanfriendly; extra == "datahub-lineage-file"
Requires-Dist: ruamel.yaml; extra == "datahub-lineage-file"
Provides-Extra: datahub-business-glossary
Requires-Dist: click-default-group; extra == "datahub-business-glossary"
Requires-Dist: Deprecated; extra == "datahub-business-glossary"
Requires-Dist: toml>=0.10.0; extra == "datahub-business-glossary"
Requires-Dist: pydantic<2; extra == "datahub-business-glossary"
Requires-Dist: avro<1.12,>=1.11.3; extra == "datahub-business-glossary"
Requires-Dist: cached_property; extra == "datahub-business-glossary"
Requires-Dist: click>=7.1.2; extra == "datahub-business-glossary"
Requires-Dist: python-dateutil>=2.8.0; extra == "datahub-business-glossary"
Requires-Dist: aiohttp<4; extra == "datahub-business-glossary"
Requires-Dist: jsonref; extra == "datahub-business-glossary"
Requires-Dist: docker; extra == "datahub-business-glossary"
Requires-Dist: packaging; extra == "datahub-business-glossary"
Requires-Dist: progressbar2; extra == "datahub-business-glossary"
Requires-Dist: ijson; extra == "datahub-business-glossary"
Requires-Dist: expandvars>=0.6.5; extra == "datahub-business-glossary"
Requires-Dist: psutil>=5.8.0; extra == "datahub-business-glossary"
Requires-Dist: jsonschema; extra == "datahub-business-glossary"
Requires-Dist: avro-gen3==0.7.16; extra == "datahub-business-glossary"
Requires-Dist: click-spinner; extra == "datahub-business-glossary"
Requires-Dist: PyYAML; extra == "datahub-business-glossary"
Requires-Dist: requests_file; extra == "datahub-business-glossary"
Requires-Dist: tabulate; extra == "datahub-business-glossary"
Requires-Dist: importlib_metadata>=4.0.0; python_version < "3.10" and extra == "datahub-business-glossary"
Requires-Dist: humanfriendly; extra == "datahub-business-glossary"
Requires-Dist: ruamel.yaml; extra == "datahub-business-glossary"
Provides-Extra: delta-lake
Requires-Dist: pyarrow>=6.0.1; extra == "delta-lake"
Requires-Dist: deltalake!=0.6.4,<0.18.0,>=0.6.3; (platform_system == "Darwin" and platform_machine == "arm64") and extra == "delta-lake"
Requires-Dist: toml>=0.10.0; extra == "delta-lake"
Requires-Dist: deltalake!=0.6.4,>=0.6.3; (platform_system != "Darwin" or platform_machine != "arm64") and extra == "delta-lake"
Requires-Dist: tableschema>=1.20.2; extra == "delta-lake"
Requires-Dist: pydantic<2; extra == "delta-lake"
Requires-Dist: botocore!=1.23.0; extra == "delta-lake"
Requires-Dist: cached_property; extra == "delta-lake"
Requires-Dist: click>=7.1.2; extra == "delta-lake"
Requires-Dist: parse>=1.19.0; extra == "delta-lake"
Requires-Dist: smart-open[s3]>=5.2.1; extra == "delta-lake"
Requires-Dist: azure-storage-file-datalake>=12.14.0; extra == "delta-lake"
Requires-Dist: boto3; extra == "delta-lake"
Requires-Dist: moto[s3]<5.0.0; extra == "delta-lake"
Requires-Dist: docker; extra == "delta-lake"
Requires-Dist: progressbar2; extra == "delta-lake"
Requires-Dist: expandvars>=0.6.5; extra == "delta-lake"
Requires-Dist: psutil>=5.8.0; extra == "delta-lake"
Requires-Dist: azure-core==1.29.4; extra == "delta-lake"
Requires-Dist: avro-gen3==0.7.16; extra == "delta-lake"
Requires-Dist: azure-identity>=1.17.1; extra == "delta-lake"
Requires-Dist: PyYAML; extra == "delta-lake"
Requires-Dist: requests_file; extra == "delta-lake"
Requires-Dist: importlib_metadata>=4.0.0; python_version < "3.10" and extra == "delta-lake"
Requires-Dist: pydeequ>=1.1.0; extra == "delta-lake"
Requires-Dist: wcmatch; extra == "delta-lake"
Requires-Dist: click-default-group; extra == "delta-lake"
Requires-Dist: Deprecated; extra == "delta-lake"
Requires-Dist: ujson>=5.2.0; extra == "delta-lake"
Requires-Dist: avro<1.12,>=1.11.3; extra == "delta-lake"
Requires-Dist: python-dateutil>=2.8.0; extra == "delta-lake"
Requires-Dist: aiohttp<4; extra == "delta-lake"
Requires-Dist: jsonref; extra == "delta-lake"
Requires-Dist: more-itertools>=8.12.0; extra == "delta-lake"
Requires-Dist: packaging; extra == "delta-lake"
Requires-Dist: ijson; extra == "delta-lake"
Requires-Dist: azure-storage-blob>=12.19.0; extra == "delta-lake"
Requires-Dist: jsonschema; extra == "delta-lake"
Requires-Dist: click-spinner; extra == "delta-lake"
Requires-Dist: tabulate; extra == "delta-lake"
Requires-Dist: pyspark~=3.5.0; extra == "delta-lake"
Requires-Dist: humanfriendly; extra == "delta-lake"
Requires-Dist: smart-open[azure]>=5.2.1; extra == "delta-lake"
Requires-Dist: ruamel.yaml; extra == "delta-lake"
Provides-Extra: dbt
Requires-Dist: requests; extra == "dbt"
Requires-Dist: click-default-group; extra == "dbt"
Requires-Dist: Deprecated; extra == "dbt"
Requires-Dist: more_itertools; extra == "dbt"
Requires-Dist: toml>=0.10.0; extra == "dbt"
Requires-Dist: pydantic<2; extra == "dbt"
Requires-Dist: avro<1.12,>=1.11.3; extra == "dbt"
Requires-Dist: cached_property; extra == "dbt"
Requires-Dist: click>=7.1.2; extra == "dbt"
Requires-Dist: python-dateutil>=2.8.0; extra == "dbt"
Requires-Dist: botocore!=1.23.0; extra == "dbt"
Requires-Dist: aiohttp<4; extra == "dbt"
Requires-Dist: jsonref; extra == "dbt"
Requires-Dist: boto3; extra == "dbt"
Requires-Dist: docker; extra == "dbt"
Requires-Dist: sqlglot[rs]==25.32.1; extra == "dbt"
Requires-Dist: packaging; extra == "dbt"
Requires-Dist: progressbar2; extra == "dbt"
Requires-Dist: ijson; extra == "dbt"
Requires-Dist: patchy==2.8.0; extra == "dbt"
Requires-Dist: expandvars>=0.6.5; extra == "dbt"
Requires-Dist: psutil>=5.8.0; extra == "dbt"
Requires-Dist: jsonschema; extra == "dbt"
Requires-Dist: avro-gen3==0.7.16; extra == "dbt"
Requires-Dist: click-spinner; extra == "dbt"
Requires-Dist: PyYAML; extra == "dbt"
Requires-Dist: requests_file; extra == "dbt"
Requires-Dist: tabulate; extra == "dbt"
Requires-Dist: importlib_metadata>=4.0.0; python_version < "3.10" and extra == "dbt"
Requires-Dist: humanfriendly; extra == "dbt"
Requires-Dist: ruamel.yaml; extra == "dbt"
Provides-Extra: dbt-cloud
Requires-Dist: requests; extra == "dbt-cloud"
Requires-Dist: click-default-group; extra == "dbt-cloud"
Requires-Dist: Deprecated; extra == "dbt-cloud"
Requires-Dist: more_itertools; extra == "dbt-cloud"
Requires-Dist: toml>=0.10.0; extra == "dbt-cloud"
Requires-Dist: pydantic<2; extra == "dbt-cloud"
Requires-Dist: avro<1.12,>=1.11.3; extra == "dbt-cloud"
Requires-Dist: cached_property; extra == "dbt-cloud"
Requires-Dist: click>=7.1.2; extra == "dbt-cloud"
Requires-Dist: python-dateutil>=2.8.0; extra == "dbt-cloud"
Requires-Dist: aiohttp<4; extra == "dbt-cloud"
Requires-Dist: jsonref; extra == "dbt-cloud"
Requires-Dist: docker; extra == "dbt-cloud"
Requires-Dist: sqlglot[rs]==25.32.1; extra == "dbt-cloud"
Requires-Dist: packaging; extra == "dbt-cloud"
Requires-Dist: progressbar2; extra == "dbt-cloud"
Requires-Dist: ijson; extra == "dbt-cloud"
Requires-Dist: patchy==2.8.0; extra == "dbt-cloud"
Requires-Dist: expandvars>=0.6.5; extra == "dbt-cloud"
Requires-Dist: psutil>=5.8.0; extra == "dbt-cloud"
Requires-Dist: jsonschema; extra == "dbt-cloud"
Requires-Dist: avro-gen3==0.7.16; extra == "dbt-cloud"
Requires-Dist: click-spinner; extra == "dbt-cloud"
Requires-Dist: PyYAML; extra == "dbt-cloud"
Requires-Dist: requests_file; extra == "dbt-cloud"
Requires-Dist: tabulate; extra == "dbt-cloud"
Requires-Dist: importlib_metadata>=4.0.0; python_version < "3.10" and extra == "dbt-cloud"
Requires-Dist: humanfriendly; extra == "dbt-cloud"
Requires-Dist: ruamel.yaml; extra == "dbt-cloud"
Provides-Extra: dremio
Requires-Dist: requests; extra == "dremio"
Requires-Dist: toml>=0.10.0; extra == "dremio"
Requires-Dist: pydantic<2; extra == "dremio"
Requires-Dist: sqlalchemy<2,>=1.4.39; extra == "dremio"
Requires-Dist: cached_property; extra == "dremio"
Requires-Dist: click>=7.1.2; extra == "dremio"
Requires-Dist: scipy>=1.7.2; extra == "dremio"
Requires-Dist: schwifty<2024.08.0; extra == "dremio"
Requires-Dist: docker; extra == "dremio"
Requires-Dist: progressbar2; extra == "dremio"
Requires-Dist: patchy==2.8.0; extra == "dremio"
Requires-Dist: expandvars>=0.6.5; extra == "dremio"
Requires-Dist: traitlets!=5.2.2; extra == "dremio"
Requires-Dist: psutil>=5.8.0; extra == "dremio"
Requires-Dist: avro-gen3==0.7.16; extra == "dremio"
Requires-Dist: cachetools; extra == "dremio"
Requires-Dist: PyYAML; extra == "dremio"
Requires-Dist: requests_file; extra == "dremio"
Requires-Dist: importlib_metadata>=4.0.0; python_version < "3.10" and extra == "dremio"
Requires-Dist: click-default-group; extra == "dremio"
Requires-Dist: Deprecated; extra == "dremio"
Requires-Dist: IPython!=8.22.0; extra == "dremio"
Requires-Dist: pip; extra == "dremio"
Requires-Dist: avro<1.12,>=1.11.3; extra == "dremio"
Requires-Dist: acryl-datahub-classify==0.0.11; extra == "dremio"
Requires-Dist: python-dateutil>=2.8.0; extra == "dremio"
Requires-Dist: aiohttp<4; extra == "dremio"
Requires-Dist: jsonref; extra == "dremio"
Requires-Dist: sqlglot[rs]==25.32.1; extra == "dremio"
Requires-Dist: packaging; extra == "dremio"
Requires-Dist: ijson; extra == "dremio"
Requires-Dist: jsonschema; extra == "dremio"
Requires-Dist: greenlet; extra == "dremio"
Requires-Dist: click-spinner; extra == "dremio"
Requires-Dist: numpy<2; extra == "dremio"
Requires-Dist: great-expectations<=0.15.50,>=0.15.12; extra == "dremio"
Requires-Dist: tabulate; extra == "dremio"
Requires-Dist: humanfriendly; extra == "dremio"
Requires-Dist: sqlparse; extra == "dremio"
Requires-Dist: ruamel.yaml; extra == "dremio"
Provides-Extra: druid
Requires-Dist: toml>=0.10.0; extra == "druid"
Requires-Dist: pydantic<2; extra == "druid"
Requires-Dist: sqlalchemy<2,>=1.4.39; extra == "druid"
Requires-Dist: cached_property; extra == "druid"
Requires-Dist: click>=7.1.2; extra == "druid"
Requires-Dist: scipy>=1.7.2; extra == "druid"
Requires-Dist: schwifty<2024.08.0; extra == "druid"
Requires-Dist: docker; extra == "druid"
Requires-Dist: progressbar2; extra == "druid"
Requires-Dist: patchy==2.8.0; extra == "druid"
Requires-Dist: expandvars>=0.6.5; extra == "druid"
Requires-Dist: traitlets!=5.2.2; extra == "druid"
Requires-Dist: psutil>=5.8.0; extra == "druid"
Requires-Dist: avro-gen3==0.7.16; extra == "druid"
Requires-Dist: cachetools; extra == "druid"
Requires-Dist: PyYAML; extra == "druid"
Requires-Dist: requests_file; extra == "druid"
Requires-Dist: importlib_metadata>=4.0.0; python_version < "3.10" and extra == "druid"
Requires-Dist: click-default-group; extra == "druid"
Requires-Dist: Deprecated; extra == "druid"
Requires-Dist: IPython!=8.22.0; extra == "druid"
Requires-Dist: pip; extra == "druid"
Requires-Dist: avro<1.12,>=1.11.3; extra == "druid"
Requires-Dist: acryl-datahub-classify==0.0.11; extra == "druid"
Requires-Dist: pydruid>=0.6.2; extra == "druid"
Requires-Dist: python-dateutil>=2.8.0; extra == "druid"
Requires-Dist: aiohttp<4; extra == "druid"
Requires-Dist: jsonref; extra == "druid"
Requires-Dist: sqlglot[rs]==25.32.1; extra == "druid"
Requires-Dist: packaging; extra == "druid"
Requires-Dist: ijson; extra == "druid"
Requires-Dist: jsonschema; extra == "druid"
Requires-Dist: greenlet; extra == "druid"
Requires-Dist: click-spinner; extra == "druid"
Requires-Dist: numpy<2; extra == "druid"
Requires-Dist: great-expectations<=0.15.50,>=0.15.12; extra == "druid"
Requires-Dist: tabulate; extra == "druid"
Requires-Dist: humanfriendly; extra == "druid"
Requires-Dist: sqlparse; extra == "druid"
Requires-Dist: ruamel.yaml; extra == "druid"
Provides-Extra: dynamodb
Requires-Dist: click-default-group; extra == "dynamodb"
Requires-Dist: Deprecated; extra == "dynamodb"
Requires-Dist: toml>=0.10.0; extra == "dynamodb"
Requires-Dist: pip; extra == "dynamodb"
Requires-Dist: pydantic<2; extra == "dynamodb"
Requires-Dist: avro<1.12,>=1.11.3; extra == "dynamodb"
Requires-Dist: cached_property; extra == "dynamodb"
Requires-Dist: click>=7.1.2; extra == "dynamodb"
Requires-Dist: python-dateutil>=2.8.0; extra == "dynamodb"
Requires-Dist: acryl-datahub-classify==0.0.11; extra == "dynamodb"
Requires-Dist: aiohttp<4; extra == "dynamodb"
Requires-Dist: jsonref; extra == "dynamodb"
Requires-Dist: boto3; extra == "dynamodb"
Requires-Dist: botocore!=1.23.0; extra == "dynamodb"
Requires-Dist: schwifty<2024.08.0; extra == "dynamodb"
Requires-Dist: docker; extra == "dynamodb"
Requires-Dist: packaging; extra == "dynamodb"
Requires-Dist: progressbar2; extra == "dynamodb"
Requires-Dist: ijson; extra == "dynamodb"
Requires-Dist: expandvars>=0.6.5; extra == "dynamodb"
Requires-Dist: psutil>=5.8.0; extra == "dynamodb"
Requires-Dist: jsonschema; extra == "dynamodb"
Requires-Dist: avro-gen3==0.7.16; extra == "dynamodb"
Requires-Dist: click-spinner; extra == "dynamodb"
Requires-Dist: numpy<2; extra == "dynamodb"
Requires-Dist: PyYAML; extra == "dynamodb"
Requires-Dist: requests_file; extra == "dynamodb"
Requires-Dist: tabulate; extra == "dynamodb"
Requires-Dist: importlib_metadata>=4.0.0; python_version < "3.10" and extra == "dynamodb"
Requires-Dist: humanfriendly; extra == "dynamodb"
Requires-Dist: ruamel.yaml; extra == "dynamodb"
Provides-Extra: elasticsearch
Requires-Dist: click-default-group; extra == "elasticsearch"
Requires-Dist: Deprecated; extra == "elasticsearch"
Requires-Dist: toml>=0.10.0; extra == "elasticsearch"
Requires-Dist: pydantic<2; extra == "elasticsearch"
Requires-Dist: avro<1.12,>=1.11.3; extra == "elasticsearch"
Requires-Dist: cached_property; extra == "elasticsearch"
Requires-Dist: click>=7.1.2; extra == "elasticsearch"
Requires-Dist: python-dateutil>=2.8.0; extra == "elasticsearch"
Requires-Dist: aiohttp<4; extra == "elasticsearch"
Requires-Dist: jsonref; extra == "elasticsearch"
Requires-Dist: elasticsearch==7.13.4; extra == "elasticsearch"
Requires-Dist: docker; extra == "elasticsearch"
Requires-Dist: packaging; extra == "elasticsearch"
Requires-Dist: progressbar2; extra == "elasticsearch"
Requires-Dist: ijson; extra == "elasticsearch"
Requires-Dist: expandvars>=0.6.5; extra == "elasticsearch"
Requires-Dist: psutil>=5.8.0; extra == "elasticsearch"
Requires-Dist: jsonschema; extra == "elasticsearch"
Requires-Dist: avro-gen3==0.7.16; extra == "elasticsearch"
Requires-Dist: click-spinner; extra == "elasticsearch"
Requires-Dist: PyYAML; extra == "elasticsearch"
Requires-Dist: requests_file; extra == "elasticsearch"
Requires-Dist: tabulate; extra == "elasticsearch"
Requires-Dist: importlib_metadata>=4.0.0; python_version < "3.10" and extra == "elasticsearch"
Requires-Dist: humanfriendly; extra == "elasticsearch"
Requires-Dist: ruamel.yaml; extra == "elasticsearch"
Provides-Extra: cassandra
Requires-Dist: click-default-group; extra == "cassandra"
Requires-Dist: Deprecated; extra == "cassandra"
Requires-Dist: toml>=0.10.0; extra == "cassandra"
Requires-Dist: pydantic<2; extra == "cassandra"
Requires-Dist: avro<1.12,>=1.11.3; extra == "cassandra"
Requires-Dist: cached_property; extra == "cassandra"
Requires-Dist: click>=7.1.2; extra == "cassandra"
Requires-Dist: python-dateutil>=2.8.0; extra == "cassandra"
Requires-Dist: aiohttp<4; extra == "cassandra"
Requires-Dist: jsonref; extra == "cassandra"
Requires-Dist: docker; extra == "cassandra"
Requires-Dist: packaging; extra == "cassandra"
Requires-Dist: progressbar2; extra == "cassandra"
Requires-Dist: ijson; extra == "cassandra"
Requires-Dist: expandvars>=0.6.5; extra == "cassandra"
Requires-Dist: psutil>=5.8.0; extra == "cassandra"
Requires-Dist: jsonschema; extra == "cassandra"
Requires-Dist: avro-gen3==0.7.16; extra == "cassandra"
Requires-Dist: click-spinner; extra == "cassandra"
Requires-Dist: numpy<2; extra == "cassandra"
Requires-Dist: PyYAML; extra == "cassandra"
Requires-Dist: requests_file; extra == "cassandra"
Requires-Dist: tabulate; extra == "cassandra"
Requires-Dist: importlib_metadata>=4.0.0; python_version < "3.10" and extra == "cassandra"
Requires-Dist: cassandra-driver>=3.28.0; extra == "cassandra"
Requires-Dist: humanfriendly; extra == "cassandra"
Requires-Dist: ruamel.yaml; extra == "cassandra"
Provides-Extra: feast
Requires-Dist: click-default-group; extra == "feast"
Requires-Dist: Deprecated; extra == "feast"
Requires-Dist: toml>=0.10.0; extra == "feast"
Requires-Dist: dask[dataframe]<2024.7.0; extra == "feast"
Requires-Dist: avro<1.12,>=1.11.3; extra == "feast"
Requires-Dist: cached_property; extra == "feast"
Requires-Dist: click>=7.1.2; extra == "feast"
Requires-Dist: python-dateutil>=2.8.0; extra == "feast"
Requires-Dist: flask-openid>=1.3.0; extra == "feast"
Requires-Dist: aiohttp<4; extra == "feast"
Requires-Dist: jsonref; extra == "feast"
Requires-Dist: docker; extra == "feast"
Requires-Dist: packaging; extra == "feast"
Requires-Dist: progressbar2; extra == "feast"
Requires-Dist: ijson; extra == "feast"
Requires-Dist: expandvars>=0.6.5; extra == "feast"
Requires-Dist: psutil>=5.8.0; extra == "feast"
Requires-Dist: feast<1,>=0.34.0; extra == "feast"
Requires-Dist: jsonschema; extra == "feast"
Requires-Dist: avro-gen3==0.7.16; extra == "feast"
Requires-Dist: click-spinner; extra == "feast"
Requires-Dist: numpy<2; extra == "feast"
Requires-Dist: PyYAML; extra == "feast"
Requires-Dist: requests_file; extra == "feast"
Requires-Dist: tabulate; extra == "feast"
Requires-Dist: importlib_metadata>=4.0.0; python_version < "3.10" and extra == "feast"
Requires-Dist: humanfriendly; extra == "feast"
Requires-Dist: ruamel.yaml; extra == "feast"
Provides-Extra: grafana
Requires-Dist: requests; extra == "grafana"
Requires-Dist: click-default-group; extra == "grafana"
Requires-Dist: Deprecated; extra == "grafana"
Requires-Dist: toml>=0.10.0; extra == "grafana"
Requires-Dist: pydantic<2; extra == "grafana"
Requires-Dist: avro<1.12,>=1.11.3; extra == "grafana"
Requires-Dist: cached_property; extra == "grafana"
Requires-Dist: click>=7.1.2; extra == "grafana"
Requires-Dist: python-dateutil>=2.8.0; extra == "grafana"
Requires-Dist: aiohttp<4; extra == "grafana"
Requires-Dist: jsonref; extra == "grafana"
Requires-Dist: docker; extra == "grafana"
Requires-Dist: packaging; extra == "grafana"
Requires-Dist: progressbar2; extra == "grafana"
Requires-Dist: ijson; extra == "grafana"
Requires-Dist: expandvars>=0.6.5; extra == "grafana"
Requires-Dist: psutil>=5.8.0; extra == "grafana"
Requires-Dist: jsonschema; extra == "grafana"
Requires-Dist: avro-gen3==0.7.16; extra == "grafana"
Requires-Dist: click-spinner; extra == "grafana"
Requires-Dist: PyYAML; extra == "grafana"
Requires-Dist: requests_file; extra == "grafana"
Requires-Dist: tabulate; extra == "grafana"
Requires-Dist: importlib_metadata>=4.0.0; python_version < "3.10" and extra == "grafana"
Requires-Dist: humanfriendly; extra == "grafana"
Requires-Dist: ruamel.yaml; extra == "grafana"
Provides-Extra: glue
Requires-Dist: click-default-group; extra == "glue"
Requires-Dist: Deprecated; extra == "glue"
Requires-Dist: toml>=0.10.0; extra == "glue"
Requires-Dist: pydantic<2; extra == "glue"
Requires-Dist: avro<1.12,>=1.11.3; extra == "glue"
Requires-Dist: cached_property; extra == "glue"
Requires-Dist: click>=7.1.2; extra == "glue"
Requires-Dist: python-dateutil>=2.8.0; extra == "glue"
Requires-Dist: botocore!=1.23.0; extra == "glue"
Requires-Dist: aiohttp<4; extra == "glue"
Requires-Dist: jsonref; extra == "glue"
Requires-Dist: boto3; extra == "glue"
Requires-Dist: docker; extra == "glue"
Requires-Dist: packaging; extra == "glue"
Requires-Dist: progressbar2; extra == "glue"
Requires-Dist: ijson; extra == "glue"
Requires-Dist: expandvars>=0.6.5; extra == "glue"
Requires-Dist: psutil>=5.8.0; extra == "glue"
Requires-Dist: jsonschema; extra == "glue"
Requires-Dist: avro-gen3==0.7.16; extra == "glue"
Requires-Dist: click-spinner; extra == "glue"
Requires-Dist: PyYAML; extra == "glue"
Requires-Dist: requests_file; extra == "glue"
Requires-Dist: tabulate; extra == "glue"
Requires-Dist: importlib_metadata>=4.0.0; python_version < "3.10" and extra == "glue"
Requires-Dist: humanfriendly; extra == "glue"
Requires-Dist: ruamel.yaml; extra == "glue"
Provides-Extra: hana
Requires-Dist: toml>=0.10.0; extra == "hana"
Requires-Dist: hdbcli>=2.11.20; (platform_machine != "aarch64" and platform_machine != "arm64") and extra == "hana"
Requires-Dist: pydantic<2; extra == "hana"
Requires-Dist: sqlalchemy<2,>=1.4.39; extra == "hana"
Requires-Dist: cached_property; extra == "hana"
Requires-Dist: click>=7.1.2; extra == "hana"
Requires-Dist: scipy>=1.7.2; extra == "hana"
Requires-Dist: schwifty<2024.08.0; extra == "hana"
Requires-Dist: docker; extra == "hana"
Requires-Dist: progressbar2; extra == "hana"
Requires-Dist: patchy==2.8.0; extra == "hana"
Requires-Dist: expandvars>=0.6.5; extra == "hana"
Requires-Dist: traitlets!=5.2.2; extra == "hana"
Requires-Dist: sqlalchemy-hana>=0.5.0; (platform_machine != "aarch64" and platform_machine != "arm64") and extra == "hana"
Requires-Dist: psutil>=5.8.0; extra == "hana"
Requires-Dist: avro-gen3==0.7.16; extra == "hana"
Requires-Dist: cachetools; extra == "hana"
Requires-Dist: PyYAML; extra == "hana"
Requires-Dist: requests_file; extra == "hana"
Requires-Dist: importlib_metadata>=4.0.0; python_version < "3.10" and extra == "hana"
Requires-Dist: click-default-group; extra == "hana"
Requires-Dist: Deprecated; extra == "hana"
Requires-Dist: IPython!=8.22.0; extra == "hana"
Requires-Dist: pip; extra == "hana"
Requires-Dist: avro<1.12,>=1.11.3; extra == "hana"
Requires-Dist: acryl-datahub-classify==0.0.11; extra == "hana"
Requires-Dist: python-dateutil>=2.8.0; extra == "hana"
Requires-Dist: aiohttp<4; extra == "hana"
Requires-Dist: jsonref; extra == "hana"
Requires-Dist: sqlglot[rs]==25.32.1; extra == "hana"
Requires-Dist: packaging; extra == "hana"
Requires-Dist: ijson; extra == "hana"
Requires-Dist: jsonschema; extra == "hana"
Requires-Dist: greenlet; extra == "hana"
Requires-Dist: click-spinner; extra == "hana"
Requires-Dist: numpy<2; extra == "hana"
Requires-Dist: great-expectations<=0.15.50,>=0.15.12; extra == "hana"
Requires-Dist: tabulate; extra == "hana"
Requires-Dist: humanfriendly; extra == "hana"
Requires-Dist: sqlparse; extra == "hana"
Requires-Dist: ruamel.yaml; extra == "hana"
Provides-Extra: hive
Requires-Dist: toml>=0.10.0; extra == "hive"
Requires-Dist: pydantic<2; extra == "hive"
Requires-Dist: sqlalchemy<2,>=1.4.39; extra == "hive"
Requires-Dist: cached_property; extra == "hive"
Requires-Dist: click>=7.1.2; extra == "hive"
Requires-Dist: scipy>=1.7.2; extra == "hive"
Requires-Dist: schwifty<2024.08.0; extra == "hive"
Requires-Dist: docker; extra == "hive"
Requires-Dist: progressbar2; extra == "hive"
Requires-Dist: patchy==2.8.0; extra == "hive"
Requires-Dist: expandvars>=0.6.5; extra == "hive"
Requires-Dist: traitlets!=5.2.2; extra == "hive"
Requires-Dist: psutil>=5.8.0; extra == "hive"
Requires-Dist: avro-gen3==0.7.16; extra == "hive"
Requires-Dist: cachetools; extra == "hive"
Requires-Dist: PyYAML; extra == "hive"
Requires-Dist: requests_file; extra == "hive"
Requires-Dist: great-expectations!=0.15.23,!=0.15.24,!=0.15.25,!=0.15.26; extra == "hive"
Requires-Dist: importlib_metadata>=4.0.0; python_version < "3.10" and extra == "hive"
Requires-Dist: click-default-group; extra == "hive"
Requires-Dist: Deprecated; extra == "hive"
Requires-Dist: IPython!=8.22.0; extra == "hive"
Requires-Dist: pip; extra == "hive"
Requires-Dist: databricks-dbapi; extra == "hive"
Requires-Dist: avro<1.12,>=1.11.3; extra == "hive"
Requires-Dist: acryl-datahub-classify==0.0.11; extra == "hive"
Requires-Dist: python-dateutil>=2.8.0; extra == "hive"
Requires-Dist: aiohttp<4; extra == "hive"
Requires-Dist: jsonref; extra == "hive"
Requires-Dist: sqlglot[rs]==25.32.1; extra == "hive"
Requires-Dist: packaging; extra == "hive"
Requires-Dist: ijson; extra == "hive"
Requires-Dist: jsonschema; extra == "hive"
Requires-Dist: greenlet; extra == "hive"
Requires-Dist: click-spinner; extra == "hive"
Requires-Dist: numpy<2; extra == "hive"
Requires-Dist: acryl-pyhive[hive-pure-sasl]==0.6.16; extra == "hive"
Requires-Dist: great-expectations<=0.15.50,>=0.15.12; extra == "hive"
Requires-Dist: tabulate; extra == "hive"
Requires-Dist: humanfriendly; extra == "hive"
Requires-Dist: sqlparse; extra == "hive"
Requires-Dist: ruamel.yaml; extra == "hive"
Provides-Extra: hive-metastore
Requires-Dist: toml>=0.10.0; extra == "hive-metastore"
Requires-Dist: pydantic<2; extra == "hive-metastore"
Requires-Dist: sqlalchemy<2,>=1.4.39; extra == "hive-metastore"
Requires-Dist: cached_property; extra == "hive-metastore"
Requires-Dist: click>=7.1.2; extra == "hive-metastore"
Requires-Dist: scipy>=1.7.2; extra == "hive-metastore"
Requires-Dist: schwifty<2024.08.0; extra == "hive-metastore"
Requires-Dist: docker; extra == "hive-metastore"
Requires-Dist: progressbar2; extra == "hive-metastore"
Requires-Dist: patchy==2.8.0; extra == "hive-metastore"
Requires-Dist: expandvars>=0.6.5; extra == "hive-metastore"
Requires-Dist: traitlets!=5.2.2; extra == "hive-metastore"
Requires-Dist: psutil>=5.8.0; extra == "hive-metastore"
Requires-Dist: avro-gen3==0.7.16; extra == "hive-metastore"
Requires-Dist: cachetools; extra == "hive-metastore"
Requires-Dist: PyYAML; extra == "hive-metastore"
Requires-Dist: requests_file; extra == "hive-metastore"
Requires-Dist: importlib_metadata>=4.0.0; python_version < "3.10" and extra == "hive-metastore"
Requires-Dist: click-default-group; extra == "hive-metastore"
Requires-Dist: Deprecated; extra == "hive-metastore"
Requires-Dist: IPython!=8.22.0; extra == "hive-metastore"
Requires-Dist: pip; extra == "hive-metastore"
Requires-Dist: avro<1.12,>=1.11.3; extra == "hive-metastore"
Requires-Dist: acryl-datahub-classify==0.0.11; extra == "hive-metastore"
Requires-Dist: python-dateutil>=2.8.0; extra == "hive-metastore"
Requires-Dist: aiohttp<4; extra == "hive-metastore"
Requires-Dist: jsonref; extra == "hive-metastore"
Requires-Dist: sqlglot[rs]==25.32.1; extra == "hive-metastore"
Requires-Dist: packaging; extra == "hive-metastore"
Requires-Dist: ijson; extra == "hive-metastore"
Requires-Dist: psycopg2-binary; extra == "hive-metastore"
Requires-Dist: jsonschema; extra == "hive-metastore"
Requires-Dist: greenlet; extra == "hive-metastore"
Requires-Dist: click-spinner; extra == "hive-metastore"
Requires-Dist: numpy<2; extra == "hive-metastore"
Requires-Dist: acryl-pyhive[hive-pure-sasl]==0.6.16; extra == "hive-metastore"
Requires-Dist: great-expectations<=0.15.50,>=0.15.12; extra == "hive-metastore"
Requires-Dist: tabulate; extra == "hive-metastore"
Requires-Dist: pymysql>=1.0.2; extra == "hive-metastore"
Requires-Dist: humanfriendly; extra == "hive-metastore"
Requires-Dist: sqlparse; extra == "hive-metastore"
Requires-Dist: ruamel.yaml; extra == "hive-metastore"
Provides-Extra: iceberg
Requires-Dist: click-default-group; extra == "iceberg"
Requires-Dist: Deprecated; extra == "iceberg"
Requires-Dist: toml>=0.10.0; extra == "iceberg"
Requires-Dist: avro<1.12,>=1.11.3; extra == "iceberg"
Requires-Dist: cached_property; extra == "iceberg"
Requires-Dist: click>=7.1.2; extra == "iceberg"
Requires-Dist: python-dateutil>=2.8.0; extra == "iceberg"
Requires-Dist: aiohttp<4; extra == "iceberg"
Requires-Dist: jsonref; extra == "iceberg"
Requires-Dist: pyiceberg>=0.4.0; extra == "iceberg"
Requires-Dist: docker; extra == "iceberg"
Requires-Dist: packaging; extra == "iceberg"
Requires-Dist: progressbar2; extra == "iceberg"
Requires-Dist: ijson; extra == "iceberg"
Requires-Dist: expandvars>=0.6.5; extra == "iceberg"
Requires-Dist: psutil>=5.8.0; extra == "iceberg"
Requires-Dist: jsonschema; extra == "iceberg"
Requires-Dist: avro-gen3==0.7.16; extra == "iceberg"
Requires-Dist: click-spinner; extra == "iceberg"
Requires-Dist: PyYAML; extra == "iceberg"
Requires-Dist: requests_file; extra == "iceberg"
Requires-Dist: tabulate; extra == "iceberg"
Requires-Dist: importlib_metadata>=4.0.0; python_version < "3.10" and extra == "iceberg"
Requires-Dist: humanfriendly; extra == "iceberg"
Requires-Dist: ruamel.yaml; extra == "iceberg"
Provides-Extra: json-schema
Requires-Dist: click-default-group; extra == "json-schema"
Requires-Dist: Deprecated; extra == "json-schema"
Requires-Dist: toml>=0.10.0; extra == "json-schema"
Requires-Dist: pydantic<2; extra == "json-schema"
Requires-Dist: avro<1.12,>=1.11.3; extra == "json-schema"
Requires-Dist: cached_property; extra == "json-schema"
Requires-Dist: click>=7.1.2; extra == "json-schema"
Requires-Dist: python-dateutil>=2.8.0; extra == "json-schema"
Requires-Dist: aiohttp<4; extra == "json-schema"
Requires-Dist: jsonref; extra == "json-schema"
Requires-Dist: docker; extra == "json-schema"
Requires-Dist: packaging; extra == "json-schema"
Requires-Dist: progressbar2; extra == "json-schema"
Requires-Dist: ijson; extra == "json-schema"
Requires-Dist: expandvars>=0.6.5; extra == "json-schema"
Requires-Dist: psutil>=5.8.0; extra == "json-schema"
Requires-Dist: jsonschema; extra == "json-schema"
Requires-Dist: avro-gen3==0.7.16; extra == "json-schema"
Requires-Dist: click-spinner; extra == "json-schema"
Requires-Dist: PyYAML; extra == "json-schema"
Requires-Dist: requests_file; extra == "json-schema"
Requires-Dist: tabulate; extra == "json-schema"
Requires-Dist: importlib_metadata>=4.0.0; python_version < "3.10" and extra == "json-schema"
Requires-Dist: humanfriendly; extra == "json-schema"
Requires-Dist: ruamel.yaml; extra == "json-schema"
Provides-Extra: kafka
Requires-Dist: click-default-group; extra == "kafka"
Requires-Dist: Deprecated; extra == "kafka"
Requires-Dist: toml>=0.10.0; extra == "kafka"
Requires-Dist: pydantic<2; extra == "kafka"
Requires-Dist: avro<1.12,>=1.11.3; extra == "kafka"
Requires-Dist: cached_property; extra == "kafka"
Requires-Dist: click>=7.1.2; extra == "kafka"
Requires-Dist: python-dateutil>=2.8.0; extra == "kafka"
Requires-Dist: aiohttp<4; extra == "kafka"
Requires-Dist: jsonref; extra == "kafka"
Requires-Dist: grpcio-tools<2,>=1.44.0; extra == "kafka"
Requires-Dist: docker; extra == "kafka"
Requires-Dist: packaging; extra == "kafka"
Requires-Dist: grpcio<2,>=1.44.0; extra == "kafka"
Requires-Dist: progressbar2; extra == "kafka"
Requires-Dist: ijson; extra == "kafka"
Requires-Dist: expandvars>=0.6.5; extra == "kafka"
Requires-Dist: psutil>=5.8.0; extra == "kafka"
Requires-Dist: jsonschema; extra == "kafka"
Requires-Dist: fastavro>=1.2.0; extra == "kafka"
Requires-Dist: avro-gen3==0.7.16; extra == "kafka"
Requires-Dist: click-spinner; extra == "kafka"
Requires-Dist: networkx>=2.6.2; extra == "kafka"
Requires-Dist: PyYAML; extra == "kafka"
Requires-Dist: requests_file; extra == "kafka"
Requires-Dist: tabulate; extra == "kafka"
Requires-Dist: importlib_metadata>=4.0.0; python_version < "3.10" and extra == "kafka"
Requires-Dist: confluent_kafka[schemaregistry]>=1.9.0; extra == "kafka"
Requires-Dist: humanfriendly; extra == "kafka"
Requires-Dist: ruamel.yaml; extra == "kafka"
Provides-Extra: kafka-connect
Requires-Dist: requests; extra == "kafka-connect"
Requires-Dist: toml>=0.10.0; extra == "kafka-connect"
Requires-Dist: pydantic<2; extra == "kafka-connect"
Requires-Dist: sqlalchemy<2,>=1.4.39; extra == "kafka-connect"
Requires-Dist: cached_property; extra == "kafka-connect"
Requires-Dist: click>=7.1.2; extra == "kafka-connect"
Requires-Dist: scipy>=1.7.2; extra == "kafka-connect"
Requires-Dist: schwifty<2024.08.0; extra == "kafka-connect"
Requires-Dist: docker; extra == "kafka-connect"
Requires-Dist: progressbar2; extra == "kafka-connect"
Requires-Dist: patchy==2.8.0; extra == "kafka-connect"
Requires-Dist: expandvars>=0.6.5; extra == "kafka-connect"
Requires-Dist: traitlets!=5.2.2; extra == "kafka-connect"
Requires-Dist: psutil>=5.8.0; extra == "kafka-connect"
Requires-Dist: avro-gen3==0.7.16; extra == "kafka-connect"
Requires-Dist: cachetools; extra == "kafka-connect"
Requires-Dist: PyYAML; extra == "kafka-connect"
Requires-Dist: requests_file; extra == "kafka-connect"
Requires-Dist: importlib_metadata>=4.0.0; python_version < "3.10" and extra == "kafka-connect"
Requires-Dist: click-default-group; extra == "kafka-connect"
Requires-Dist: Deprecated; extra == "kafka-connect"
Requires-Dist: IPython!=8.22.0; extra == "kafka-connect"
Requires-Dist: pip; extra == "kafka-connect"
Requires-Dist: avro<1.12,>=1.11.3; extra == "kafka-connect"
Requires-Dist: acryl-datahub-classify==0.0.11; extra == "kafka-connect"
Requires-Dist: python-dateutil>=2.8.0; extra == "kafka-connect"
Requires-Dist: aiohttp<4; extra == "kafka-connect"
Requires-Dist: jsonref; extra == "kafka-connect"
Requires-Dist: sqlglot[rs]==25.32.1; extra == "kafka-connect"
Requires-Dist: packaging; extra == "kafka-connect"
Requires-Dist: ijson; extra == "kafka-connect"
Requires-Dist: JPype1; extra == "kafka-connect"
Requires-Dist: jsonschema; extra == "kafka-connect"
Requires-Dist: greenlet; extra == "kafka-connect"
Requires-Dist: click-spinner; extra == "kafka-connect"
Requires-Dist: numpy<2; extra == "kafka-connect"
Requires-Dist: great-expectations<=0.15.50,>=0.15.12; extra == "kafka-connect"
Requires-Dist: tabulate; extra == "kafka-connect"
Requires-Dist: humanfriendly; extra == "kafka-connect"
Requires-Dist: sqlparse; extra == "kafka-connect"
Requires-Dist: ruamel.yaml; extra == "kafka-connect"
Provides-Extra: ldap
Requires-Dist: click-default-group; extra == "ldap"
Requires-Dist: Deprecated; extra == "ldap"
Requires-Dist: toml>=0.10.0; extra == "ldap"
Requires-Dist: pydantic<2; extra == "ldap"
Requires-Dist: avro<1.12,>=1.11.3; extra == "ldap"
Requires-Dist: cached_property; extra == "ldap"
Requires-Dist: click>=7.1.2; extra == "ldap"
Requires-Dist: python-dateutil>=2.8.0; extra == "ldap"
Requires-Dist: aiohttp<4; extra == "ldap"
Requires-Dist: jsonref; extra == "ldap"
Requires-Dist: docker; extra == "ldap"
Requires-Dist: packaging; extra == "ldap"
Requires-Dist: progressbar2; extra == "ldap"
Requires-Dist: ijson; extra == "ldap"
Requires-Dist: python-ldap>=2.4; extra == "ldap"
Requires-Dist: expandvars>=0.6.5; extra == "ldap"
Requires-Dist: psutil>=5.8.0; extra == "ldap"
Requires-Dist: jsonschema; extra == "ldap"
Requires-Dist: avro-gen3==0.7.16; extra == "ldap"
Requires-Dist: click-spinner; extra == "ldap"
Requires-Dist: PyYAML; extra == "ldap"
Requires-Dist: requests_file; extra == "ldap"
Requires-Dist: tabulate; extra == "ldap"
Requires-Dist: importlib_metadata>=4.0.0; python_version < "3.10" and extra == "ldap"
Requires-Dist: humanfriendly; extra == "ldap"
Requires-Dist: ruamel.yaml; extra == "ldap"
Provides-Extra: looker
Requires-Dist: click-default-group; extra == "looker"
Requires-Dist: Deprecated; extra == "looker"
Requires-Dist: toml>=0.10.0; extra == "looker"
Requires-Dist: pydantic<2; extra == "looker"
Requires-Dist: avro<1.12,>=1.11.3; extra == "looker"
Requires-Dist: cached_property; extra == "looker"
Requires-Dist: click>=7.1.2; extra == "looker"
Requires-Dist: python-dateutil>=2.8.0; extra == "looker"
Requires-Dist: looker-sdk>=23.0.0; extra == "looker"
Requires-Dist: aiohttp<4; extra == "looker"
Requires-Dist: jsonref; extra == "looker"
Requires-Dist: deepmerge>=1.1.1; extra == "looker"
Requires-Dist: lkml>=1.3.4; extra == "looker"
Requires-Dist: docker; extra == "looker"
Requires-Dist: sqlglot[rs]==25.32.1; extra == "looker"
Requires-Dist: packaging; extra == "looker"
Requires-Dist: GitPython>2; extra == "looker"
Requires-Dist: progressbar2; extra == "looker"
Requires-Dist: ijson; extra == "looker"
Requires-Dist: patchy==2.8.0; extra == "looker"
Requires-Dist: expandvars>=0.6.5; extra == "looker"
Requires-Dist: python-liquid; extra == "looker"
Requires-Dist: psutil>=5.8.0; extra == "looker"
Requires-Dist: jsonschema; extra == "looker"
Requires-Dist: avro-gen3==0.7.16; extra == "looker"
Requires-Dist: click-spinner; extra == "looker"
Requires-Dist: PyYAML; extra == "looker"
Requires-Dist: requests_file; extra == "looker"
Requires-Dist: tabulate; extra == "looker"
Requires-Dist: importlib_metadata>=4.0.0; python_version < "3.10" and extra == "looker"
Requires-Dist: humanfriendly; extra == "looker"
Requires-Dist: ruamel.yaml; extra == "looker"
Provides-Extra: lookml
Requires-Dist: click-default-group; extra == "lookml"
Requires-Dist: Deprecated; extra == "lookml"
Requires-Dist: toml>=0.10.0; extra == "lookml"
Requires-Dist: pydantic<2; extra == "lookml"
Requires-Dist: avro<1.12,>=1.11.3; extra == "lookml"
Requires-Dist: cached_property; extra == "lookml"
Requires-Dist: click>=7.1.2; extra == "lookml"
Requires-Dist: python-dateutil>=2.8.0; extra == "lookml"
Requires-Dist: looker-sdk>=23.0.0; extra == "lookml"
Requires-Dist: aiohttp<4; extra == "lookml"
Requires-Dist: jsonref; extra == "lookml"
Requires-Dist: deepmerge>=1.1.1; extra == "lookml"
Requires-Dist: lkml>=1.3.4; extra == "lookml"
Requires-Dist: docker; extra == "lookml"
Requires-Dist: sqlglot[rs]==25.32.1; extra == "lookml"
Requires-Dist: packaging; extra == "lookml"
Requires-Dist: GitPython>2; extra == "lookml"
Requires-Dist: progressbar2; extra == "lookml"
Requires-Dist: ijson; extra == "lookml"
Requires-Dist: patchy==2.8.0; extra == "lookml"
Requires-Dist: expandvars>=0.6.5; extra == "lookml"
Requires-Dist: python-liquid; extra == "lookml"
Requires-Dist: psutil>=5.8.0; extra == "lookml"
Requires-Dist: jsonschema; extra == "lookml"
Requires-Dist: avro-gen3==0.7.16; extra == "lookml"
Requires-Dist: click-spinner; extra == "lookml"
Requires-Dist: PyYAML; extra == "lookml"
Requires-Dist: requests_file; extra == "lookml"
Requires-Dist: tabulate; extra == "lookml"
Requires-Dist: importlib_metadata>=4.0.0; python_version < "3.10" and extra == "lookml"
Requires-Dist: humanfriendly; extra == "lookml"
Requires-Dist: ruamel.yaml; extra == "lookml"
Provides-Extra: metabase
Requires-Dist: requests; extra == "metabase"
Requires-Dist: click-default-group; extra == "metabase"
Requires-Dist: Deprecated; extra == "metabase"
Requires-Dist: toml>=0.10.0; extra == "metabase"
Requires-Dist: pydantic<2; extra == "metabase"
Requires-Dist: avro<1.12,>=1.11.3; extra == "metabase"
Requires-Dist: cached_property; extra == "metabase"
Requires-Dist: click>=7.1.2; extra == "metabase"
Requires-Dist: python-dateutil>=2.8.0; extra == "metabase"
Requires-Dist: aiohttp<4; extra == "metabase"
Requires-Dist: jsonref; extra == "metabase"
Requires-Dist: docker; extra == "metabase"
Requires-Dist: sqlglot[rs]==25.32.1; extra == "metabase"
Requires-Dist: packaging; extra == "metabase"
Requires-Dist: progressbar2; extra == "metabase"
Requires-Dist: ijson; extra == "metabase"
Requires-Dist: patchy==2.8.0; extra == "metabase"
Requires-Dist: expandvars>=0.6.5; extra == "metabase"
Requires-Dist: psutil>=5.8.0; extra == "metabase"
Requires-Dist: jsonschema; extra == "metabase"
Requires-Dist: avro-gen3==0.7.16; extra == "metabase"
Requires-Dist: click-spinner; extra == "metabase"
Requires-Dist: PyYAML; extra == "metabase"
Requires-Dist: requests_file; extra == "metabase"
Requires-Dist: tabulate; extra == "metabase"
Requires-Dist: importlib_metadata>=4.0.0; python_version < "3.10" and extra == "metabase"
Requires-Dist: humanfriendly; extra == "metabase"
Requires-Dist: ruamel.yaml; extra == "metabase"
Provides-Extra: mlflow
Requires-Dist: click-default-group; extra == "mlflow"
Requires-Dist: Deprecated; extra == "mlflow"
Requires-Dist: toml>=0.10.0; extra == "mlflow"
Requires-Dist: pydantic<2; extra == "mlflow"
Requires-Dist: avro<1.12,>=1.11.3; extra == "mlflow"
Requires-Dist: cached_property; extra == "mlflow"
Requires-Dist: click>=7.1.2; extra == "mlflow"
Requires-Dist: python-dateutil>=2.8.0; extra == "mlflow"
Requires-Dist: aiohttp<4; extra == "mlflow"
Requires-Dist: jsonref; extra == "mlflow"
Requires-Dist: docker; extra == "mlflow"
Requires-Dist: mlflow-skinny>=2.3.0; extra == "mlflow"
Requires-Dist: packaging; extra == "mlflow"
Requires-Dist: progressbar2; extra == "mlflow"
Requires-Dist: ijson; extra == "mlflow"
Requires-Dist: expandvars>=0.6.5; extra == "mlflow"
Requires-Dist: psutil>=5.8.0; extra == "mlflow"
Requires-Dist: setuptools; extra == "mlflow"
Requires-Dist: jsonschema; extra == "mlflow"
Requires-Dist: avro-gen3==0.7.16; extra == "mlflow"
Requires-Dist: click-spinner; extra == "mlflow"
Requires-Dist: PyYAML; extra == "mlflow"
Requires-Dist: requests_file; extra == "mlflow"
Requires-Dist: tabulate; extra == "mlflow"
Requires-Dist: importlib_metadata>=4.0.0; python_version < "3.10" and extra == "mlflow"
Requires-Dist: humanfriendly; extra == "mlflow"
Requires-Dist: ruamel.yaml; extra == "mlflow"
Provides-Extra: mode
Requires-Dist: requests; extra == "mode"
Requires-Dist: click-default-group; extra == "mode"
Requires-Dist: Deprecated; extra == "mode"
Requires-Dist: toml>=0.10.0; extra == "mode"
Requires-Dist: pydantic<2; extra == "mode"
Requires-Dist: avro<1.12,>=1.11.3; extra == "mode"
Requires-Dist: cached_property; extra == "mode"
Requires-Dist: click>=7.1.2; extra == "mode"
Requires-Dist: python-dateutil>=2.8.0; extra == "mode"
Requires-Dist: aiohttp<4; extra == "mode"
Requires-Dist: jsonref; extra == "mode"
Requires-Dist: docker; extra == "mode"
Requires-Dist: sqlglot[rs]==25.32.1; extra == "mode"
Requires-Dist: packaging; extra == "mode"
Requires-Dist: tenacity>=8.0.1; extra == "mode"
Requires-Dist: progressbar2; extra == "mode"
Requires-Dist: ijson; extra == "mode"
Requires-Dist: patchy==2.8.0; extra == "mode"
Requires-Dist: expandvars>=0.6.5; extra == "mode"
Requires-Dist: python-liquid; extra == "mode"
Requires-Dist: psutil>=5.8.0; extra == "mode"
Requires-Dist: jsonschema; extra == "mode"
Requires-Dist: avro-gen3==0.7.16; extra == "mode"
Requires-Dist: click-spinner; extra == "mode"
Requires-Dist: PyYAML; extra == "mode"
Requires-Dist: requests_file; extra == "mode"
Requires-Dist: tabulate; extra == "mode"
Requires-Dist: importlib_metadata>=4.0.0; python_version < "3.10" and extra == "mode"
Requires-Dist: humanfriendly; extra == "mode"
Requires-Dist: ruamel.yaml; extra == "mode"
Provides-Extra: mongodb
Requires-Dist: click-default-group; extra == "mongodb"
Requires-Dist: Deprecated; extra == "mongodb"
Requires-Dist: pymongo[srv]>=3.11; extra == "mongodb"
Requires-Dist: toml>=0.10.0; extra == "mongodb"
Requires-Dist: pydantic<2; extra == "mongodb"
Requires-Dist: avro<1.12,>=1.11.3; extra == "mongodb"
Requires-Dist: cached_property; extra == "mongodb"
Requires-Dist: click>=7.1.2; extra == "mongodb"
Requires-Dist: python-dateutil>=2.8.0; extra == "mongodb"
Requires-Dist: aiohttp<4; extra == "mongodb"
Requires-Dist: jsonref; extra == "mongodb"
Requires-Dist: docker; extra == "mongodb"
Requires-Dist: packaging; extra == "mongodb"
Requires-Dist: progressbar2; extra == "mongodb"
Requires-Dist: ijson; extra == "mongodb"
Requires-Dist: expandvars>=0.6.5; extra == "mongodb"
Requires-Dist: psutil>=5.8.0; extra == "mongodb"
Requires-Dist: jsonschema; extra == "mongodb"
Requires-Dist: avro-gen3==0.7.16; extra == "mongodb"
Requires-Dist: click-spinner; extra == "mongodb"
Requires-Dist: PyYAML; extra == "mongodb"
Requires-Dist: requests_file; extra == "mongodb"
Requires-Dist: tabulate; extra == "mongodb"
Requires-Dist: importlib_metadata>=4.0.0; python_version < "3.10" and extra == "mongodb"
Requires-Dist: humanfriendly; extra == "mongodb"
Requires-Dist: ruamel.yaml; extra == "mongodb"
Provides-Extra: mssql
Requires-Dist: toml>=0.10.0; extra == "mssql"
Requires-Dist: pydantic<2; extra == "mssql"
Requires-Dist: sqlalchemy<2,>=1.4.39; extra == "mssql"
Requires-Dist: cached_property; extra == "mssql"
Requires-Dist: click>=7.1.2; extra == "mssql"
Requires-Dist: scipy>=1.7.2; extra == "mssql"
Requires-Dist: schwifty<2024.08.0; extra == "mssql"
Requires-Dist: docker; extra == "mssql"
Requires-Dist: sqlalchemy-pytds>=0.3; extra == "mssql"
Requires-Dist: progressbar2; extra == "mssql"
Requires-Dist: patchy==2.8.0; extra == "mssql"
Requires-Dist: expandvars>=0.6.5; extra == "mssql"
Requires-Dist: traitlets!=5.2.2; extra == "mssql"
Requires-Dist: psutil>=5.8.0; extra == "mssql"
Requires-Dist: avro-gen3==0.7.16; extra == "mssql"
Requires-Dist: cachetools; extra == "mssql"
Requires-Dist: PyYAML; extra == "mssql"
Requires-Dist: requests_file; extra == "mssql"
Requires-Dist: importlib_metadata>=4.0.0; python_version < "3.10" and extra == "mssql"
Requires-Dist: click-default-group; extra == "mssql"
Requires-Dist: Deprecated; extra == "mssql"
Requires-Dist: IPython!=8.22.0; extra == "mssql"
Requires-Dist: pip; extra == "mssql"
Requires-Dist: avro<1.12,>=1.11.3; extra == "mssql"
Requires-Dist: acryl-datahub-classify==0.0.11; extra == "mssql"
Requires-Dist: python-dateutil>=2.8.0; extra == "mssql"
Requires-Dist: aiohttp<4; extra == "mssql"
Requires-Dist: jsonref; extra == "mssql"
Requires-Dist: sqlglot[rs]==25.32.1; extra == "mssql"
Requires-Dist: packaging; extra == "mssql"
Requires-Dist: ijson; extra == "mssql"
Requires-Dist: jsonschema; extra == "mssql"
Requires-Dist: greenlet; extra == "mssql"
Requires-Dist: click-spinner; extra == "mssql"
Requires-Dist: numpy<2; extra == "mssql"
Requires-Dist: great-expectations<=0.15.50,>=0.15.12; extra == "mssql"
Requires-Dist: tabulate; extra == "mssql"
Requires-Dist: pyOpenSSL; extra == "mssql"
Requires-Dist: humanfriendly; extra == "mssql"
Requires-Dist: sqlparse; extra == "mssql"
Requires-Dist: ruamel.yaml; extra == "mssql"
Provides-Extra: mssql-odbc
Requires-Dist: toml>=0.10.0; extra == "mssql-odbc"
Requires-Dist: pydantic<2; extra == "mssql-odbc"
Requires-Dist: sqlalchemy<2,>=1.4.39; extra == "mssql-odbc"
Requires-Dist: cached_property; extra == "mssql-odbc"
Requires-Dist: click>=7.1.2; extra == "mssql-odbc"
Requires-Dist: scipy>=1.7.2; extra == "mssql-odbc"
Requires-Dist: schwifty<2024.08.0; extra == "mssql-odbc"
Requires-Dist: docker; extra == "mssql-odbc"
Requires-Dist: sqlalchemy-pytds>=0.3; extra == "mssql-odbc"
Requires-Dist: progressbar2; extra == "mssql-odbc"
Requires-Dist: patchy==2.8.0; extra == "mssql-odbc"
Requires-Dist: expandvars>=0.6.5; extra == "mssql-odbc"
Requires-Dist: traitlets!=5.2.2; extra == "mssql-odbc"
Requires-Dist: psutil>=5.8.0; extra == "mssql-odbc"
Requires-Dist: avro-gen3==0.7.16; extra == "mssql-odbc"
Requires-Dist: cachetools; extra == "mssql-odbc"
Requires-Dist: PyYAML; extra == "mssql-odbc"
Requires-Dist: requests_file; extra == "mssql-odbc"
Requires-Dist: importlib_metadata>=4.0.0; python_version < "3.10" and extra == "mssql-odbc"
Requires-Dist: click-default-group; extra == "mssql-odbc"
Requires-Dist: Deprecated; extra == "mssql-odbc"
Requires-Dist: IPython!=8.22.0; extra == "mssql-odbc"
Requires-Dist: pip; extra == "mssql-odbc"
Requires-Dist: avro<1.12,>=1.11.3; extra == "mssql-odbc"
Requires-Dist: acryl-datahub-classify==0.0.11; extra == "mssql-odbc"
Requires-Dist: python-dateutil>=2.8.0; extra == "mssql-odbc"
Requires-Dist: aiohttp<4; extra == "mssql-odbc"
Requires-Dist: jsonref; extra == "mssql-odbc"
Requires-Dist: sqlglot[rs]==25.32.1; extra == "mssql-odbc"
Requires-Dist: packaging; extra == "mssql-odbc"
Requires-Dist: ijson; extra == "mssql-odbc"
Requires-Dist: jsonschema; extra == "mssql-odbc"
Requires-Dist: greenlet; extra == "mssql-odbc"
Requires-Dist: pyodbc; extra == "mssql-odbc"
Requires-Dist: click-spinner; extra == "mssql-odbc"
Requires-Dist: numpy<2; extra == "mssql-odbc"
Requires-Dist: great-expectations<=0.15.50,>=0.15.12; extra == "mssql-odbc"
Requires-Dist: tabulate; extra == "mssql-odbc"
Requires-Dist: pyOpenSSL; extra == "mssql-odbc"
Requires-Dist: humanfriendly; extra == "mssql-odbc"
Requires-Dist: sqlparse; extra == "mssql-odbc"
Requires-Dist: ruamel.yaml; extra == "mssql-odbc"
Provides-Extra: mysql
Requires-Dist: toml>=0.10.0; extra == "mysql"
Requires-Dist: pydantic<2; extra == "mysql"
Requires-Dist: sqlalchemy<2,>=1.4.39; extra == "mysql"
Requires-Dist: cached_property; extra == "mysql"
Requires-Dist: click>=7.1.2; extra == "mysql"
Requires-Dist: scipy>=1.7.2; extra == "mysql"
Requires-Dist: schwifty<2024.08.0; extra == "mysql"
Requires-Dist: docker; extra == "mysql"
Requires-Dist: progressbar2; extra == "mysql"
Requires-Dist: patchy==2.8.0; extra == "mysql"
Requires-Dist: expandvars>=0.6.5; extra == "mysql"
Requires-Dist: traitlets!=5.2.2; extra == "mysql"
Requires-Dist: psutil>=5.8.0; extra == "mysql"
Requires-Dist: avro-gen3==0.7.16; extra == "mysql"
Requires-Dist: cachetools; extra == "mysql"
Requires-Dist: PyYAML; extra == "mysql"
Requires-Dist: requests_file; extra == "mysql"
Requires-Dist: importlib_metadata>=4.0.0; python_version < "3.10" and extra == "mysql"
Requires-Dist: click-default-group; extra == "mysql"
Requires-Dist: Deprecated; extra == "mysql"
Requires-Dist: IPython!=8.22.0; extra == "mysql"
Requires-Dist: pip; extra == "mysql"
Requires-Dist: avro<1.12,>=1.11.3; extra == "mysql"
Requires-Dist: acryl-datahub-classify==0.0.11; extra == "mysql"
Requires-Dist: python-dateutil>=2.8.0; extra == "mysql"
Requires-Dist: aiohttp<4; extra == "mysql"
Requires-Dist: jsonref; extra == "mysql"
Requires-Dist: sqlglot[rs]==25.32.1; extra == "mysql"
Requires-Dist: packaging; extra == "mysql"
Requires-Dist: ijson; extra == "mysql"
Requires-Dist: jsonschema; extra == "mysql"
Requires-Dist: greenlet; extra == "mysql"
Requires-Dist: click-spinner; extra == "mysql"
Requires-Dist: numpy<2; extra == "mysql"
Requires-Dist: pymysql>=1.0.2; extra == "mysql"
Requires-Dist: great-expectations<=0.15.50,>=0.15.12; extra == "mysql"
Requires-Dist: tabulate; extra == "mysql"
Requires-Dist: humanfriendly; extra == "mysql"
Requires-Dist: sqlparse; extra == "mysql"
Requires-Dist: ruamel.yaml; extra == "mysql"
Provides-Extra: mariadb
Requires-Dist: toml>=0.10.0; extra == "mariadb"
Requires-Dist: pydantic<2; extra == "mariadb"
Requires-Dist: sqlalchemy<2,>=1.4.39; extra == "mariadb"
Requires-Dist: cached_property; extra == "mariadb"
Requires-Dist: click>=7.1.2; extra == "mariadb"
Requires-Dist: scipy>=1.7.2; extra == "mariadb"
Requires-Dist: schwifty<2024.08.0; extra == "mariadb"
Requires-Dist: docker; extra == "mariadb"
Requires-Dist: progressbar2; extra == "mariadb"
Requires-Dist: patchy==2.8.0; extra == "mariadb"
Requires-Dist: expandvars>=0.6.5; extra == "mariadb"
Requires-Dist: traitlets!=5.2.2; extra == "mariadb"
Requires-Dist: psutil>=5.8.0; extra == "mariadb"
Requires-Dist: avro-gen3==0.7.16; extra == "mariadb"
Requires-Dist: cachetools; extra == "mariadb"
Requires-Dist: PyYAML; extra == "mariadb"
Requires-Dist: requests_file; extra == "mariadb"
Requires-Dist: importlib_metadata>=4.0.0; python_version < "3.10" and extra == "mariadb"
Requires-Dist: click-default-group; extra == "mariadb"
Requires-Dist: Deprecated; extra == "mariadb"
Requires-Dist: IPython!=8.22.0; extra == "mariadb"
Requires-Dist: pip; extra == "mariadb"
Requires-Dist: avro<1.12,>=1.11.3; extra == "mariadb"
Requires-Dist: acryl-datahub-classify==0.0.11; extra == "mariadb"
Requires-Dist: python-dateutil>=2.8.0; extra == "mariadb"
Requires-Dist: aiohttp<4; extra == "mariadb"
Requires-Dist: jsonref; extra == "mariadb"
Requires-Dist: sqlglot[rs]==25.32.1; extra == "mariadb"
Requires-Dist: packaging; extra == "mariadb"
Requires-Dist: ijson; extra == "mariadb"
Requires-Dist: jsonschema; extra == "mariadb"
Requires-Dist: greenlet; extra == "mariadb"
Requires-Dist: click-spinner; extra == "mariadb"
Requires-Dist: numpy<2; extra == "mariadb"
Requires-Dist: pymysql>=1.0.2; extra == "mariadb"
Requires-Dist: great-expectations<=0.15.50,>=0.15.12; extra == "mariadb"
Requires-Dist: tabulate; extra == "mariadb"
Requires-Dist: humanfriendly; extra == "mariadb"
Requires-Dist: sqlparse; extra == "mariadb"
Requires-Dist: ruamel.yaml; extra == "mariadb"
Provides-Extra: okta
Requires-Dist: click-default-group; extra == "okta"
Requires-Dist: Deprecated; extra == "okta"
Requires-Dist: toml>=0.10.0; extra == "okta"
Requires-Dist: pydantic<2; extra == "okta"
Requires-Dist: avro<1.12,>=1.11.3; extra == "okta"
Requires-Dist: cached_property; extra == "okta"
Requires-Dist: click>=7.1.2; extra == "okta"
Requires-Dist: python-dateutil>=2.8.0; extra == "okta"
Requires-Dist: aiohttp<4; extra == "okta"
Requires-Dist: jsonref; extra == "okta"
Requires-Dist: docker; extra == "okta"
Requires-Dist: packaging; extra == "okta"
Requires-Dist: progressbar2; extra == "okta"
Requires-Dist: ijson; extra == "okta"
Requires-Dist: expandvars>=0.6.5; extra == "okta"
Requires-Dist: okta~=1.7.0; extra == "okta"
Requires-Dist: psutil>=5.8.0; extra == "okta"
Requires-Dist: jsonschema; extra == "okta"
Requires-Dist: avro-gen3==0.7.16; extra == "okta"
Requires-Dist: click-spinner; extra == "okta"
Requires-Dist: PyYAML; extra == "okta"
Requires-Dist: requests_file; extra == "okta"
Requires-Dist: tabulate; extra == "okta"
Requires-Dist: importlib_metadata>=4.0.0; python_version < "3.10" and extra == "okta"
Requires-Dist: humanfriendly; extra == "okta"
Requires-Dist: nest-asyncio; extra == "okta"
Requires-Dist: ruamel.yaml; extra == "okta"
Provides-Extra: oracle
Requires-Dist: toml>=0.10.0; extra == "oracle"
Requires-Dist: pydantic<2; extra == "oracle"
Requires-Dist: sqlalchemy<2,>=1.4.39; extra == "oracle"
Requires-Dist: cached_property; extra == "oracle"
Requires-Dist: click>=7.1.2; extra == "oracle"
Requires-Dist: scipy>=1.7.2; extra == "oracle"
Requires-Dist: schwifty<2024.08.0; extra == "oracle"
Requires-Dist: docker; extra == "oracle"
Requires-Dist: progressbar2; extra == "oracle"
Requires-Dist: patchy==2.8.0; extra == "oracle"
Requires-Dist: expandvars>=0.6.5; extra == "oracle"
Requires-Dist: traitlets!=5.2.2; extra == "oracle"
Requires-Dist: psutil>=5.8.0; extra == "oracle"
Requires-Dist: avro-gen3==0.7.16; extra == "oracle"
Requires-Dist: cachetools; extra == "oracle"
Requires-Dist: PyYAML; extra == "oracle"
Requires-Dist: requests_file; extra == "oracle"
Requires-Dist: importlib_metadata>=4.0.0; python_version < "3.10" and extra == "oracle"
Requires-Dist: click-default-group; extra == "oracle"
Requires-Dist: Deprecated; extra == "oracle"
Requires-Dist: IPython!=8.22.0; extra == "oracle"
Requires-Dist: pip; extra == "oracle"
Requires-Dist: avro<1.12,>=1.11.3; extra == "oracle"
Requires-Dist: acryl-datahub-classify==0.0.11; extra == "oracle"
Requires-Dist: python-dateutil>=2.8.0; extra == "oracle"
Requires-Dist: aiohttp<4; extra == "oracle"
Requires-Dist: jsonref; extra == "oracle"
Requires-Dist: sqlglot[rs]==25.32.1; extra == "oracle"
Requires-Dist: packaging; extra == "oracle"
Requires-Dist: oracledb; extra == "oracle"
Requires-Dist: ijson; extra == "oracle"
Requires-Dist: jsonschema; extra == "oracle"
Requires-Dist: greenlet; extra == "oracle"
Requires-Dist: click-spinner; extra == "oracle"
Requires-Dist: numpy<2; extra == "oracle"
Requires-Dist: great-expectations<=0.15.50,>=0.15.12; extra == "oracle"
Requires-Dist: tabulate; extra == "oracle"
Requires-Dist: humanfriendly; extra == "oracle"
Requires-Dist: sqlparse; extra == "oracle"
Requires-Dist: ruamel.yaml; extra == "oracle"
Provides-Extra: postgres
Requires-Dist: toml>=0.10.0; extra == "postgres"
Requires-Dist: pydantic<2; extra == "postgres"
Requires-Dist: sqlalchemy<2,>=1.4.39; extra == "postgres"
Requires-Dist: cached_property; extra == "postgres"
Requires-Dist: click>=7.1.2; extra == "postgres"
Requires-Dist: scipy>=1.7.2; extra == "postgres"
Requires-Dist: schwifty<2024.08.0; extra == "postgres"
Requires-Dist: docker; extra == "postgres"
Requires-Dist: progressbar2; extra == "postgres"
Requires-Dist: patchy==2.8.0; extra == "postgres"
Requires-Dist: expandvars>=0.6.5; extra == "postgres"
Requires-Dist: traitlets!=5.2.2; extra == "postgres"
Requires-Dist: psutil>=5.8.0; extra == "postgres"
Requires-Dist: avro-gen3==0.7.16; extra == "postgres"
Requires-Dist: cachetools; extra == "postgres"
Requires-Dist: PyYAML; extra == "postgres"
Requires-Dist: requests_file; extra == "postgres"
Requires-Dist: importlib_metadata>=4.0.0; python_version < "3.10" and extra == "postgres"
Requires-Dist: GeoAlchemy2; extra == "postgres"
Requires-Dist: click-default-group; extra == "postgres"
Requires-Dist: Deprecated; extra == "postgres"
Requires-Dist: IPython!=8.22.0; extra == "postgres"
Requires-Dist: pip; extra == "postgres"
Requires-Dist: avro<1.12,>=1.11.3; extra == "postgres"
Requires-Dist: acryl-datahub-classify==0.0.11; extra == "postgres"
Requires-Dist: python-dateutil>=2.8.0; extra == "postgres"
Requires-Dist: aiohttp<4; extra == "postgres"
Requires-Dist: jsonref; extra == "postgres"
Requires-Dist: sqlglot[rs]==25.32.1; extra == "postgres"
Requires-Dist: packaging; extra == "postgres"
Requires-Dist: ijson; extra == "postgres"
Requires-Dist: psycopg2-binary; extra == "postgres"
Requires-Dist: jsonschema; extra == "postgres"
Requires-Dist: greenlet; extra == "postgres"
Requires-Dist: click-spinner; extra == "postgres"
Requires-Dist: numpy<2; extra == "postgres"
Requires-Dist: great-expectations<=0.15.50,>=0.15.12; extra == "postgres"
Requires-Dist: tabulate; extra == "postgres"
Requires-Dist: humanfriendly; extra == "postgres"
Requires-Dist: sqlparse; extra == "postgres"
Requires-Dist: ruamel.yaml; extra == "postgres"
Provides-Extra: presto
Requires-Dist: toml>=0.10.0; extra == "presto"
Requires-Dist: pydantic<2; extra == "presto"
Requires-Dist: sqlalchemy<2,>=1.4.39; extra == "presto"
Requires-Dist: cached_property; extra == "presto"
Requires-Dist: click>=7.1.2; extra == "presto"
Requires-Dist: scipy>=1.7.2; extra == "presto"
Requires-Dist: schwifty<2024.08.0; extra == "presto"
Requires-Dist: docker; extra == "presto"
Requires-Dist: progressbar2; extra == "presto"
Requires-Dist: patchy==2.8.0; extra == "presto"
Requires-Dist: expandvars>=0.6.5; extra == "presto"
Requires-Dist: traitlets!=5.2.2; extra == "presto"
Requires-Dist: trino[sqlalchemy]>=0.308; extra == "presto"
Requires-Dist: psutil>=5.8.0; extra == "presto"
Requires-Dist: avro-gen3==0.7.16; extra == "presto"
Requires-Dist: cachetools; extra == "presto"
Requires-Dist: PyYAML; extra == "presto"
Requires-Dist: requests_file; extra == "presto"
Requires-Dist: importlib_metadata>=4.0.0; python_version < "3.10" and extra == "presto"
Requires-Dist: click-default-group; extra == "presto"
Requires-Dist: Deprecated; extra == "presto"
Requires-Dist: IPython!=8.22.0; extra == "presto"
Requires-Dist: pip; extra == "presto"
Requires-Dist: avro<1.12,>=1.11.3; extra == "presto"
Requires-Dist: acryl-datahub-classify==0.0.11; extra == "presto"
Requires-Dist: python-dateutil>=2.8.0; extra == "presto"
Requires-Dist: aiohttp<4; extra == "presto"
Requires-Dist: jsonref; extra == "presto"
Requires-Dist: sqlglot[rs]==25.32.1; extra == "presto"
Requires-Dist: packaging; extra == "presto"
Requires-Dist: ijson; extra == "presto"
Requires-Dist: jsonschema; extra == "presto"
Requires-Dist: greenlet; extra == "presto"
Requires-Dist: click-spinner; extra == "presto"
Requires-Dist: numpy<2; extra == "presto"
Requires-Dist: acryl-pyhive[hive-pure-sasl]==0.6.16; extra == "presto"
Requires-Dist: great-expectations<=0.15.50,>=0.15.12; extra == "presto"
Requires-Dist: tabulate; extra == "presto"
Requires-Dist: humanfriendly; extra == "presto"
Requires-Dist: sqlparse; extra == "presto"
Requires-Dist: ruamel.yaml; extra == "presto"
Provides-Extra: presto-on-hive
Requires-Dist: toml>=0.10.0; extra == "presto-on-hive"
Requires-Dist: pydantic<2; extra == "presto-on-hive"
Requires-Dist: sqlalchemy<2,>=1.4.39; extra == "presto-on-hive"
Requires-Dist: cached_property; extra == "presto-on-hive"
Requires-Dist: click>=7.1.2; extra == "presto-on-hive"
Requires-Dist: scipy>=1.7.2; extra == "presto-on-hive"
Requires-Dist: schwifty<2024.08.0; extra == "presto-on-hive"
Requires-Dist: docker; extra == "presto-on-hive"
Requires-Dist: progressbar2; extra == "presto-on-hive"
Requires-Dist: patchy==2.8.0; extra == "presto-on-hive"
Requires-Dist: expandvars>=0.6.5; extra == "presto-on-hive"
Requires-Dist: traitlets!=5.2.2; extra == "presto-on-hive"
Requires-Dist: psutil>=5.8.0; extra == "presto-on-hive"
Requires-Dist: avro-gen3==0.7.16; extra == "presto-on-hive"
Requires-Dist: cachetools; extra == "presto-on-hive"
Requires-Dist: PyYAML; extra == "presto-on-hive"
Requires-Dist: requests_file; extra == "presto-on-hive"
Requires-Dist: importlib_metadata>=4.0.0; python_version < "3.10" and extra == "presto-on-hive"
Requires-Dist: click-default-group; extra == "presto-on-hive"
Requires-Dist: Deprecated; extra == "presto-on-hive"
Requires-Dist: IPython!=8.22.0; extra == "presto-on-hive"
Requires-Dist: pip; extra == "presto-on-hive"
Requires-Dist: avro<1.12,>=1.11.3; extra == "presto-on-hive"
Requires-Dist: acryl-datahub-classify==0.0.11; extra == "presto-on-hive"
Requires-Dist: python-dateutil>=2.8.0; extra == "presto-on-hive"
Requires-Dist: aiohttp<4; extra == "presto-on-hive"
Requires-Dist: jsonref; extra == "presto-on-hive"
Requires-Dist: sqlglot[rs]==25.32.1; extra == "presto-on-hive"
Requires-Dist: packaging; extra == "presto-on-hive"
Requires-Dist: ijson; extra == "presto-on-hive"
Requires-Dist: psycopg2-binary; extra == "presto-on-hive"
Requires-Dist: jsonschema; extra == "presto-on-hive"
Requires-Dist: greenlet; extra == "presto-on-hive"
Requires-Dist: click-spinner; extra == "presto-on-hive"
Requires-Dist: numpy<2; extra == "presto-on-hive"
Requires-Dist: acryl-pyhive[hive-pure-sasl]==0.6.16; extra == "presto-on-hive"
Requires-Dist: great-expectations<=0.15.50,>=0.15.12; extra == "presto-on-hive"
Requires-Dist: tabulate; extra == "presto-on-hive"
Requires-Dist: pymysql>=1.0.2; extra == "presto-on-hive"
Requires-Dist: humanfriendly; extra == "presto-on-hive"
Requires-Dist: sqlparse; extra == "presto-on-hive"
Requires-Dist: ruamel.yaml; extra == "presto-on-hive"
Provides-Extra: pulsar
Requires-Dist: requests; extra == "pulsar"
Requires-Dist: click-default-group; extra == "pulsar"
Requires-Dist: Deprecated; extra == "pulsar"
Requires-Dist: toml>=0.10.0; extra == "pulsar"
Requires-Dist: pydantic<2; extra == "pulsar"
Requires-Dist: avro<1.12,>=1.11.3; extra == "pulsar"
Requires-Dist: cached_property; extra == "pulsar"
Requires-Dist: click>=7.1.2; extra == "pulsar"
Requires-Dist: python-dateutil>=2.8.0; extra == "pulsar"
Requires-Dist: aiohttp<4; extra == "pulsar"
Requires-Dist: jsonref; extra == "pulsar"
Requires-Dist: docker; extra == "pulsar"
Requires-Dist: packaging; extra == "pulsar"
Requires-Dist: progressbar2; extra == "pulsar"
Requires-Dist: ijson; extra == "pulsar"
Requires-Dist: expandvars>=0.6.5; extra == "pulsar"
Requires-Dist: psutil>=5.8.0; extra == "pulsar"
Requires-Dist: jsonschema; extra == "pulsar"
Requires-Dist: avro-gen3==0.7.16; extra == "pulsar"
Requires-Dist: click-spinner; extra == "pulsar"
Requires-Dist: PyYAML; extra == "pulsar"
Requires-Dist: requests_file; extra == "pulsar"
Requires-Dist: tabulate; extra == "pulsar"
Requires-Dist: importlib_metadata>=4.0.0; python_version < "3.10" and extra == "pulsar"
Requires-Dist: humanfriendly; extra == "pulsar"
Requires-Dist: ruamel.yaml; extra == "pulsar"
Provides-Extra: redash
Requires-Dist: click-default-group; extra == "redash"
Requires-Dist: Deprecated; extra == "redash"
Requires-Dist: toml>=0.10.0; extra == "redash"
Requires-Dist: pydantic<2; extra == "redash"
Requires-Dist: redash-toolbelt; extra == "redash"
Requires-Dist: avro<1.12,>=1.11.3; extra == "redash"
Requires-Dist: cached_property; extra == "redash"
Requires-Dist: click>=7.1.2; extra == "redash"
Requires-Dist: python-dateutil>=2.8.0; extra == "redash"
Requires-Dist: aiohttp<4; extra == "redash"
Requires-Dist: jsonref; extra == "redash"
Requires-Dist: docker; extra == "redash"
Requires-Dist: sqlglot[rs]==25.32.1; extra == "redash"
Requires-Dist: packaging; extra == "redash"
Requires-Dist: progressbar2; extra == "redash"
Requires-Dist: ijson; extra == "redash"
Requires-Dist: patchy==2.8.0; extra == "redash"
Requires-Dist: expandvars>=0.6.5; extra == "redash"
Requires-Dist: psutil>=5.8.0; extra == "redash"
Requires-Dist: sql-metadata; extra == "redash"
Requires-Dist: jsonschema; extra == "redash"
Requires-Dist: avro-gen3==0.7.16; extra == "redash"
Requires-Dist: click-spinner; extra == "redash"
Requires-Dist: PyYAML; extra == "redash"
Requires-Dist: requests_file; extra == "redash"
Requires-Dist: tabulate; extra == "redash"
Requires-Dist: importlib_metadata>=4.0.0; python_version < "3.10" and extra == "redash"
Requires-Dist: humanfriendly; extra == "redash"
Requires-Dist: ruamel.yaml; extra == "redash"
Provides-Extra: redshift
Requires-Dist: toml>=0.10.0; extra == "redshift"
Requires-Dist: pydantic<2; extra == "redshift"
Requires-Dist: sqlalchemy<2,>=1.4.39; extra == "redshift"
Requires-Dist: cached_property; extra == "redshift"
Requires-Dist: click>=7.1.2; extra == "redshift"
Requires-Dist: parse>=1.19.0; extra == "redshift"
Requires-Dist: scipy>=1.7.2; extra == "redshift"
Requires-Dist: schwifty<2024.08.0; extra == "redshift"
Requires-Dist: docker; extra == "redshift"
Requires-Dist: progressbar2; extra == "redshift"
Requires-Dist: patchy==2.8.0; extra == "redshift"
Requires-Dist: redshift-connector>=2.1.5; extra == "redshift"
Requires-Dist: expandvars>=0.6.5; extra == "redshift"
Requires-Dist: traitlets!=5.2.2; extra == "redshift"
Requires-Dist: psutil>=5.8.0; extra == "redshift"
Requires-Dist: avro-gen3==0.7.16; extra == "redshift"
Requires-Dist: cachetools; extra == "redshift"
Requires-Dist: PyYAML; extra == "redshift"
Requires-Dist: requests_file; extra == "redshift"
Requires-Dist: importlib_metadata>=4.0.0; python_version < "3.10" and extra == "redshift"
Requires-Dist: wcmatch; extra == "redshift"
Requires-Dist: GeoAlchemy2; extra == "redshift"
Requires-Dist: click-default-group; extra == "redshift"
Requires-Dist: Deprecated; extra == "redshift"
Requires-Dist: IPython!=8.22.0; extra == "redshift"
Requires-Dist: pip; extra == "redshift"
Requires-Dist: avro<1.12,>=1.11.3; extra == "redshift"
Requires-Dist: acryl-datahub-classify==0.0.11; extra == "redshift"
Requires-Dist: python-dateutil>=2.8.0; extra == "redshift"
Requires-Dist: aiohttp<4; extra == "redshift"
Requires-Dist: jsonref; extra == "redshift"
Requires-Dist: sqlglot[rs]==25.32.1; extra == "redshift"
Requires-Dist: packaging; extra == "redshift"
Requires-Dist: ijson; extra == "redshift"
Requires-Dist: db-dtypes; extra == "redshift"
Requires-Dist: jsonschema; extra == "redshift"
Requires-Dist: greenlet; extra == "redshift"
Requires-Dist: click-spinner; extra == "redshift"
Requires-Dist: numpy<2; extra == "redshift"
Requires-Dist: great-expectations<=0.15.50,>=0.15.12; extra == "redshift"
Requires-Dist: tabulate; extra == "redshift"
Requires-Dist: humanfriendly; extra == "redshift"
Requires-Dist: sqlalchemy-redshift>=0.8.3; extra == "redshift"
Requires-Dist: sqlparse; extra == "redshift"
Requires-Dist: ruamel.yaml; extra == "redshift"
Provides-Extra: s3
Requires-Dist: click-default-group; extra == "s3"
Requires-Dist: Deprecated; extra == "s3"
Requires-Dist: pyarrow>=6.0.1; extra == "s3"
Requires-Dist: ujson>=5.2.0; extra == "s3"
Requires-Dist: toml>=0.10.0; extra == "s3"
Requires-Dist: tableschema>=1.20.2; extra == "s3"
Requires-Dist: pydantic<2; extra == "s3"
Requires-Dist: wcmatch; extra == "s3"
Requires-Dist: avro<1.12,>=1.11.3; extra == "s3"
Requires-Dist: cached_property; extra == "s3"
Requires-Dist: click>=7.1.2; extra == "s3"
Requires-Dist: python-dateutil>=2.8.0; extra == "s3"
Requires-Dist: botocore!=1.23.0; extra == "s3"
Requires-Dist: aiohttp<4; extra == "s3"
Requires-Dist: jsonref; extra == "s3"
Requires-Dist: parse>=1.19.0; extra == "s3"
Requires-Dist: smart-open[s3]>=5.2.1; extra == "s3"
Requires-Dist: boto3; extra == "s3"
Requires-Dist: docker; extra == "s3"
Requires-Dist: more-itertools>=8.12.0; extra == "s3"
Requires-Dist: moto[s3]<5.0.0; extra == "s3"
Requires-Dist: packaging; extra == "s3"
Requires-Dist: progressbar2; extra == "s3"
Requires-Dist: ijson; extra == "s3"
Requires-Dist: expandvars>=0.6.5; extra == "s3"
Requires-Dist: psutil>=5.8.0; extra == "s3"
Requires-Dist: jsonschema; extra == "s3"
Requires-Dist: avro-gen3==0.7.16; extra == "s3"
Requires-Dist: click-spinner; extra == "s3"
Requires-Dist: PyYAML; extra == "s3"
Requires-Dist: requests_file; extra == "s3"
Requires-Dist: tabulate; extra == "s3"
Requires-Dist: importlib_metadata>=4.0.0; python_version < "3.10" and extra == "s3"
Requires-Dist: pyspark~=3.5.0; extra == "s3"
Requires-Dist: humanfriendly; extra == "s3"
Requires-Dist: pydeequ>=1.1.0; extra == "s3"
Requires-Dist: ruamel.yaml; extra == "s3"
Provides-Extra: gcs
Requires-Dist: click-default-group; extra == "gcs"
Requires-Dist: Deprecated; extra == "gcs"
Requires-Dist: pyarrow>=6.0.1; extra == "gcs"
Requires-Dist: ujson>=5.2.0; extra == "gcs"
Requires-Dist: toml>=0.10.0; extra == "gcs"
Requires-Dist: tableschema>=1.20.2; extra == "gcs"
Requires-Dist: pydantic<2; extra == "gcs"
Requires-Dist: wcmatch; extra == "gcs"
Requires-Dist: avro<1.12,>=1.11.3; extra == "gcs"
Requires-Dist: cached_property; extra == "gcs"
Requires-Dist: click>=7.1.2; extra == "gcs"
Requires-Dist: python-dateutil>=2.8.0; extra == "gcs"
Requires-Dist: botocore!=1.23.0; extra == "gcs"
Requires-Dist: aiohttp<4; extra == "gcs"
Requires-Dist: jsonref; extra == "gcs"
Requires-Dist: parse>=1.19.0; extra == "gcs"
Requires-Dist: smart-open[s3]>=5.2.1; extra == "gcs"
Requires-Dist: boto3; extra == "gcs"
Requires-Dist: docker; extra == "gcs"
Requires-Dist: more-itertools>=8.12.0; extra == "gcs"
Requires-Dist: moto[s3]<5.0.0; extra == "gcs"
Requires-Dist: packaging; extra == "gcs"
Requires-Dist: progressbar2; extra == "gcs"
Requires-Dist: ijson; extra == "gcs"
Requires-Dist: expandvars>=0.6.5; extra == "gcs"
Requires-Dist: psutil>=5.8.0; extra == "gcs"
Requires-Dist: jsonschema; extra == "gcs"
Requires-Dist: avro-gen3==0.7.16; extra == "gcs"
Requires-Dist: click-spinner; extra == "gcs"
Requires-Dist: PyYAML; extra == "gcs"
Requires-Dist: requests_file; extra == "gcs"
Requires-Dist: tabulate; extra == "gcs"
Requires-Dist: importlib_metadata>=4.0.0; python_version < "3.10" and extra == "gcs"
Requires-Dist: pyspark~=3.5.0; extra == "gcs"
Requires-Dist: humanfriendly; extra == "gcs"
Requires-Dist: pydeequ>=1.1.0; extra == "gcs"
Requires-Dist: ruamel.yaml; extra == "gcs"
Provides-Extra: abs
Requires-Dist: pyarrow>=6.0.1; extra == "abs"
Requires-Dist: toml>=0.10.0; extra == "abs"
Requires-Dist: tableschema>=1.20.2; extra == "abs"
Requires-Dist: pydantic<2; extra == "abs"
Requires-Dist: cached_property; extra == "abs"
Requires-Dist: click>=7.1.2; extra == "abs"
Requires-Dist: parse>=1.19.0; extra == "abs"
Requires-Dist: azure-storage-file-datalake>=12.14.0; extra == "abs"
Requires-Dist: docker; extra == "abs"
Requires-Dist: progressbar2; extra == "abs"
Requires-Dist: expandvars>=0.6.5; extra == "abs"
Requires-Dist: psutil>=5.8.0; extra == "abs"
Requires-Dist: azure-core==1.29.4; extra == "abs"
Requires-Dist: avro-gen3==0.7.16; extra == "abs"
Requires-Dist: azure-identity>=1.17.1; extra == "abs"
Requires-Dist: PyYAML; extra == "abs"
Requires-Dist: requests_file; extra == "abs"
Requires-Dist: importlib_metadata>=4.0.0; python_version < "3.10" and extra == "abs"
Requires-Dist: pydeequ>=1.1.0; extra == "abs"
Requires-Dist: wcmatch; extra == "abs"
Requires-Dist: click-default-group; extra == "abs"
Requires-Dist: Deprecated; extra == "abs"
Requires-Dist: ujson>=5.2.0; extra == "abs"
Requires-Dist: avro<1.12,>=1.11.3; extra == "abs"
Requires-Dist: python-dateutil>=2.8.0; extra == "abs"
Requires-Dist: aiohttp<4; extra == "abs"
Requires-Dist: jsonref; extra == "abs"
Requires-Dist: more-itertools>=8.12.0; extra == "abs"
Requires-Dist: packaging; extra == "abs"
Requires-Dist: ijson; extra == "abs"
Requires-Dist: azure-storage-blob>=12.19.0; extra == "abs"
Requires-Dist: jsonschema; extra == "abs"
Requires-Dist: click-spinner; extra == "abs"
Requires-Dist: tabulate; extra == "abs"
Requires-Dist: pyspark~=3.5.0; extra == "abs"
Requires-Dist: humanfriendly; extra == "abs"
Requires-Dist: smart-open[azure]>=5.2.1; extra == "abs"
Requires-Dist: ruamel.yaml; extra == "abs"
Provides-Extra: sagemaker
Requires-Dist: click-default-group; extra == "sagemaker"
Requires-Dist: Deprecated; extra == "sagemaker"
Requires-Dist: toml>=0.10.0; extra == "sagemaker"
Requires-Dist: pydantic<2; extra == "sagemaker"
Requires-Dist: avro<1.12,>=1.11.3; extra == "sagemaker"
Requires-Dist: cached_property; extra == "sagemaker"
Requires-Dist: click>=7.1.2; extra == "sagemaker"
Requires-Dist: python-dateutil>=2.8.0; extra == "sagemaker"
Requires-Dist: botocore!=1.23.0; extra == "sagemaker"
Requires-Dist: aiohttp<4; extra == "sagemaker"
Requires-Dist: jsonref; extra == "sagemaker"
Requires-Dist: boto3; extra == "sagemaker"
Requires-Dist: docker; extra == "sagemaker"
Requires-Dist: packaging; extra == "sagemaker"
Requires-Dist: progressbar2; extra == "sagemaker"
Requires-Dist: ijson; extra == "sagemaker"
Requires-Dist: expandvars>=0.6.5; extra == "sagemaker"
Requires-Dist: psutil>=5.8.0; extra == "sagemaker"
Requires-Dist: jsonschema; extra == "sagemaker"
Requires-Dist: avro-gen3==0.7.16; extra == "sagemaker"
Requires-Dist: click-spinner; extra == "sagemaker"
Requires-Dist: PyYAML; extra == "sagemaker"
Requires-Dist: requests_file; extra == "sagemaker"
Requires-Dist: tabulate; extra == "sagemaker"
Requires-Dist: importlib_metadata>=4.0.0; python_version < "3.10" and extra == "sagemaker"
Requires-Dist: humanfriendly; extra == "sagemaker"
Requires-Dist: ruamel.yaml; extra == "sagemaker"
Provides-Extra: salesforce
Requires-Dist: click-default-group; extra == "salesforce"
Requires-Dist: Deprecated; extra == "salesforce"
Requires-Dist: toml>=0.10.0; extra == "salesforce"
Requires-Dist: pydantic<2; extra == "salesforce"
Requires-Dist: avro<1.12,>=1.11.3; extra == "salesforce"
Requires-Dist: cached_property; extra == "salesforce"
Requires-Dist: click>=7.1.2; extra == "salesforce"
Requires-Dist: python-dateutil>=2.8.0; extra == "salesforce"
Requires-Dist: aiohttp<4; extra == "salesforce"
Requires-Dist: jsonref; extra == "salesforce"
Requires-Dist: docker; extra == "salesforce"
Requires-Dist: packaging; extra == "salesforce"
Requires-Dist: progressbar2; extra == "salesforce"
Requires-Dist: ijson; extra == "salesforce"
Requires-Dist: expandvars>=0.6.5; extra == "salesforce"
Requires-Dist: psutil>=5.8.0; extra == "salesforce"
Requires-Dist: jsonschema; extra == "salesforce"
Requires-Dist: avro-gen3==0.7.16; extra == "salesforce"
Requires-Dist: click-spinner; extra == "salesforce"
Requires-Dist: PyYAML; extra == "salesforce"
Requires-Dist: requests_file; extra == "salesforce"
Requires-Dist: tabulate; extra == "salesforce"
Requires-Dist: importlib_metadata>=4.0.0; python_version < "3.10" and extra == "salesforce"
Requires-Dist: humanfriendly; extra == "salesforce"
Requires-Dist: simple-salesforce; extra == "salesforce"
Requires-Dist: ruamel.yaml; extra == "salesforce"
Provides-Extra: snowflake
Requires-Dist: toml>=0.10.0; extra == "snowflake"
Requires-Dist: pydantic<2; extra == "snowflake"
Requires-Dist: sqlalchemy<2,>=1.4.39; extra == "snowflake"
Requires-Dist: cached_property; extra == "snowflake"
Requires-Dist: click>=7.1.2; extra == "snowflake"
Requires-Dist: snowflake-sqlalchemy>=1.4.3; extra == "snowflake"
Requires-Dist: snowflake-connector-python>=3.4.0; extra == "snowflake"
Requires-Dist: scipy>=1.7.2; extra == "snowflake"
Requires-Dist: schwifty<2024.08.0; extra == "snowflake"
Requires-Dist: docker; extra == "snowflake"
Requires-Dist: progressbar2; extra == "snowflake"
Requires-Dist: patchy==2.8.0; extra == "snowflake"
Requires-Dist: expandvars>=0.6.5; extra == "snowflake"
Requires-Dist: traitlets!=5.2.2; extra == "snowflake"
Requires-Dist: psutil>=5.8.0; extra == "snowflake"
Requires-Dist: avro-gen3==0.7.16; extra == "snowflake"
Requires-Dist: cachetools; extra == "snowflake"
Requires-Dist: PyYAML; extra == "snowflake"
Requires-Dist: requests_file; extra == "snowflake"
Requires-Dist: importlib_metadata>=4.0.0; python_version < "3.10" and extra == "snowflake"
Requires-Dist: msal; extra == "snowflake"
Requires-Dist: click-default-group; extra == "snowflake"
Requires-Dist: Deprecated; extra == "snowflake"
Requires-Dist: IPython!=8.22.0; extra == "snowflake"
Requires-Dist: pip; extra == "snowflake"
Requires-Dist: avro<1.12,>=1.11.3; extra == "snowflake"
Requires-Dist: acryl-datahub-classify==0.0.11; extra == "snowflake"
Requires-Dist: python-dateutil>=2.8.0; extra == "snowflake"
Requires-Dist: aiohttp<4; extra == "snowflake"
Requires-Dist: jsonref; extra == "snowflake"
Requires-Dist: sqlglot[rs]==25.32.1; extra == "snowflake"
Requires-Dist: packaging; extra == "snowflake"
Requires-Dist: pandas; extra == "snowflake"
Requires-Dist: ijson; extra == "snowflake"
Requires-Dist: jsonschema; extra == "snowflake"
Requires-Dist: greenlet; extra == "snowflake"
Requires-Dist: cryptography; extra == "snowflake"
Requires-Dist: click-spinner; extra == "snowflake"
Requires-Dist: numpy<2; extra == "snowflake"
Requires-Dist: great-expectations<=0.15.50,>=0.15.12; extra == "snowflake"
Requires-Dist: tabulate; extra == "snowflake"
Requires-Dist: humanfriendly; extra == "snowflake"
Requires-Dist: sqlparse; extra == "snowflake"
Requires-Dist: ruamel.yaml; extra == "snowflake"
Provides-Extra: snowflake-summary
Requires-Dist: toml>=0.10.0; extra == "snowflake-summary"
Requires-Dist: pydantic<2; extra == "snowflake-summary"
Requires-Dist: sqlalchemy<2,>=1.4.39; extra == "snowflake-summary"
Requires-Dist: cached_property; extra == "snowflake-summary"
Requires-Dist: click>=7.1.2; extra == "snowflake-summary"
Requires-Dist: snowflake-sqlalchemy>=1.4.3; extra == "snowflake-summary"
Requires-Dist: snowflake-connector-python>=3.4.0; extra == "snowflake-summary"
Requires-Dist: scipy>=1.7.2; extra == "snowflake-summary"
Requires-Dist: schwifty<2024.08.0; extra == "snowflake-summary"
Requires-Dist: docker; extra == "snowflake-summary"
Requires-Dist: progressbar2; extra == "snowflake-summary"
Requires-Dist: patchy==2.8.0; extra == "snowflake-summary"
Requires-Dist: expandvars>=0.6.5; extra == "snowflake-summary"
Requires-Dist: traitlets!=5.2.2; extra == "snowflake-summary"
Requires-Dist: psutil>=5.8.0; extra == "snowflake-summary"
Requires-Dist: avro-gen3==0.7.16; extra == "snowflake-summary"
Requires-Dist: cachetools; extra == "snowflake-summary"
Requires-Dist: PyYAML; extra == "snowflake-summary"
Requires-Dist: requests_file; extra == "snowflake-summary"
Requires-Dist: importlib_metadata>=4.0.0; python_version < "3.10" and extra == "snowflake-summary"
Requires-Dist: msal; extra == "snowflake-summary"
Requires-Dist: click-default-group; extra == "snowflake-summary"
Requires-Dist: Deprecated; extra == "snowflake-summary"
Requires-Dist: IPython!=8.22.0; extra == "snowflake-summary"
Requires-Dist: pip; extra == "snowflake-summary"
Requires-Dist: avro<1.12,>=1.11.3; extra == "snowflake-summary"
Requires-Dist: acryl-datahub-classify==0.0.11; extra == "snowflake-summary"
Requires-Dist: python-dateutil>=2.8.0; extra == "snowflake-summary"
Requires-Dist: aiohttp<4; extra == "snowflake-summary"
Requires-Dist: jsonref; extra == "snowflake-summary"
Requires-Dist: sqlglot[rs]==25.32.1; extra == "snowflake-summary"
Requires-Dist: packaging; extra == "snowflake-summary"
Requires-Dist: pandas; extra == "snowflake-summary"
Requires-Dist: ijson; extra == "snowflake-summary"
Requires-Dist: jsonschema; extra == "snowflake-summary"
Requires-Dist: greenlet; extra == "snowflake-summary"
Requires-Dist: cryptography; extra == "snowflake-summary"
Requires-Dist: click-spinner; extra == "snowflake-summary"
Requires-Dist: numpy<2; extra == "snowflake-summary"
Requires-Dist: great-expectations<=0.15.50,>=0.15.12; extra == "snowflake-summary"
Requires-Dist: tabulate; extra == "snowflake-summary"
Requires-Dist: humanfriendly; extra == "snowflake-summary"
Requires-Dist: sqlparse; extra == "snowflake-summary"
Requires-Dist: ruamel.yaml; extra == "snowflake-summary"
Provides-Extra: snowflake-queries
Requires-Dist: toml>=0.10.0; extra == "snowflake-queries"
Requires-Dist: pydantic<2; extra == "snowflake-queries"
Requires-Dist: sqlalchemy<2,>=1.4.39; extra == "snowflake-queries"
Requires-Dist: cached_property; extra == "snowflake-queries"
Requires-Dist: click>=7.1.2; extra == "snowflake-queries"
Requires-Dist: snowflake-sqlalchemy>=1.4.3; extra == "snowflake-queries"
Requires-Dist: snowflake-connector-python>=3.4.0; extra == "snowflake-queries"
Requires-Dist: scipy>=1.7.2; extra == "snowflake-queries"
Requires-Dist: schwifty<2024.08.0; extra == "snowflake-queries"
Requires-Dist: docker; extra == "snowflake-queries"
Requires-Dist: progressbar2; extra == "snowflake-queries"
Requires-Dist: patchy==2.8.0; extra == "snowflake-queries"
Requires-Dist: expandvars>=0.6.5; extra == "snowflake-queries"
Requires-Dist: traitlets!=5.2.2; extra == "snowflake-queries"
Requires-Dist: psutil>=5.8.0; extra == "snowflake-queries"
Requires-Dist: avro-gen3==0.7.16; extra == "snowflake-queries"
Requires-Dist: cachetools; extra == "snowflake-queries"
Requires-Dist: PyYAML; extra == "snowflake-queries"
Requires-Dist: requests_file; extra == "snowflake-queries"
Requires-Dist: importlib_metadata>=4.0.0; python_version < "3.10" and extra == "snowflake-queries"
Requires-Dist: msal; extra == "snowflake-queries"
Requires-Dist: click-default-group; extra == "snowflake-queries"
Requires-Dist: Deprecated; extra == "snowflake-queries"
Requires-Dist: IPython!=8.22.0; extra == "snowflake-queries"
Requires-Dist: pip; extra == "snowflake-queries"
Requires-Dist: avro<1.12,>=1.11.3; extra == "snowflake-queries"
Requires-Dist: acryl-datahub-classify==0.0.11; extra == "snowflake-queries"
Requires-Dist: python-dateutil>=2.8.0; extra == "snowflake-queries"
Requires-Dist: aiohttp<4; extra == "snowflake-queries"
Requires-Dist: jsonref; extra == "snowflake-queries"
Requires-Dist: sqlglot[rs]==25.32.1; extra == "snowflake-queries"
Requires-Dist: packaging; extra == "snowflake-queries"
Requires-Dist: pandas; extra == "snowflake-queries"
Requires-Dist: ijson; extra == "snowflake-queries"
Requires-Dist: jsonschema; extra == "snowflake-queries"
Requires-Dist: greenlet; extra == "snowflake-queries"
Requires-Dist: cryptography; extra == "snowflake-queries"
Requires-Dist: click-spinner; extra == "snowflake-queries"
Requires-Dist: numpy<2; extra == "snowflake-queries"
Requires-Dist: great-expectations<=0.15.50,>=0.15.12; extra == "snowflake-queries"
Requires-Dist: tabulate; extra == "snowflake-queries"
Requires-Dist: humanfriendly; extra == "snowflake-queries"
Requires-Dist: sqlparse; extra == "snowflake-queries"
Requires-Dist: ruamel.yaml; extra == "snowflake-queries"
Provides-Extra: sqlalchemy
Requires-Dist: toml>=0.10.0; extra == "sqlalchemy"
Requires-Dist: pydantic<2; extra == "sqlalchemy"
Requires-Dist: sqlalchemy<2,>=1.4.39; extra == "sqlalchemy"
Requires-Dist: cached_property; extra == "sqlalchemy"
Requires-Dist: click>=7.1.2; extra == "sqlalchemy"
Requires-Dist: scipy>=1.7.2; extra == "sqlalchemy"
Requires-Dist: schwifty<2024.08.0; extra == "sqlalchemy"
Requires-Dist: docker; extra == "sqlalchemy"
Requires-Dist: progressbar2; extra == "sqlalchemy"
Requires-Dist: patchy==2.8.0; extra == "sqlalchemy"
Requires-Dist: expandvars>=0.6.5; extra == "sqlalchemy"
Requires-Dist: traitlets!=5.2.2; extra == "sqlalchemy"
Requires-Dist: psutil>=5.8.0; extra == "sqlalchemy"
Requires-Dist: avro-gen3==0.7.16; extra == "sqlalchemy"
Requires-Dist: cachetools; extra == "sqlalchemy"
Requires-Dist: PyYAML; extra == "sqlalchemy"
Requires-Dist: requests_file; extra == "sqlalchemy"
Requires-Dist: importlib_metadata>=4.0.0; python_version < "3.10" and extra == "sqlalchemy"
Requires-Dist: click-default-group; extra == "sqlalchemy"
Requires-Dist: Deprecated; extra == "sqlalchemy"
Requires-Dist: IPython!=8.22.0; extra == "sqlalchemy"
Requires-Dist: pip; extra == "sqlalchemy"
Requires-Dist: avro<1.12,>=1.11.3; extra == "sqlalchemy"
Requires-Dist: acryl-datahub-classify==0.0.11; extra == "sqlalchemy"
Requires-Dist: python-dateutil>=2.8.0; extra == "sqlalchemy"
Requires-Dist: aiohttp<4; extra == "sqlalchemy"
Requires-Dist: jsonref; extra == "sqlalchemy"
Requires-Dist: sqlglot[rs]==25.32.1; extra == "sqlalchemy"
Requires-Dist: packaging; extra == "sqlalchemy"
Requires-Dist: ijson; extra == "sqlalchemy"
Requires-Dist: jsonschema; extra == "sqlalchemy"
Requires-Dist: greenlet; extra == "sqlalchemy"
Requires-Dist: click-spinner; extra == "sqlalchemy"
Requires-Dist: numpy<2; extra == "sqlalchemy"
Requires-Dist: great-expectations<=0.15.50,>=0.15.12; extra == "sqlalchemy"
Requires-Dist: tabulate; extra == "sqlalchemy"
Requires-Dist: humanfriendly; extra == "sqlalchemy"
Requires-Dist: sqlparse; extra == "sqlalchemy"
Requires-Dist: ruamel.yaml; extra == "sqlalchemy"
Provides-Extra: sql-queries
Requires-Dist: click-default-group; extra == "sql-queries"
Requires-Dist: Deprecated; extra == "sql-queries"
Requires-Dist: toml>=0.10.0; extra == "sql-queries"
Requires-Dist: pydantic<2; extra == "sql-queries"
Requires-Dist: avro<1.12,>=1.11.3; extra == "sql-queries"
Requires-Dist: cached_property; extra == "sql-queries"
Requires-Dist: click>=7.1.2; extra == "sql-queries"
Requires-Dist: python-dateutil>=2.8.0; extra == "sql-queries"
Requires-Dist: aiohttp<4; extra == "sql-queries"
Requires-Dist: jsonref; extra == "sql-queries"
Requires-Dist: docker; extra == "sql-queries"
Requires-Dist: sqlglot[rs]==25.32.1; extra == "sql-queries"
Requires-Dist: packaging; extra == "sql-queries"
Requires-Dist: progressbar2; extra == "sql-queries"
Requires-Dist: ijson; extra == "sql-queries"
Requires-Dist: patchy==2.8.0; extra == "sql-queries"
Requires-Dist: expandvars>=0.6.5; extra == "sql-queries"
Requires-Dist: psutil>=5.8.0; extra == "sql-queries"
Requires-Dist: jsonschema; extra == "sql-queries"
Requires-Dist: avro-gen3==0.7.16; extra == "sql-queries"
Requires-Dist: click-spinner; extra == "sql-queries"
Requires-Dist: PyYAML; extra == "sql-queries"
Requires-Dist: requests_file; extra == "sql-queries"
Requires-Dist: tabulate; extra == "sql-queries"
Requires-Dist: importlib_metadata>=4.0.0; python_version < "3.10" and extra == "sql-queries"
Requires-Dist: humanfriendly; extra == "sql-queries"
Requires-Dist: sqlparse; extra == "sql-queries"
Requires-Dist: ruamel.yaml; extra == "sql-queries"
Provides-Extra: slack
Requires-Dist: click-default-group; extra == "slack"
Requires-Dist: slack-sdk==3.18.1; extra == "slack"
Requires-Dist: Deprecated; extra == "slack"
Requires-Dist: toml>=0.10.0; extra == "slack"
Requires-Dist: pydantic<2; extra == "slack"
Requires-Dist: avro<1.12,>=1.11.3; extra == "slack"
Requires-Dist: cached_property; extra == "slack"
Requires-Dist: click>=7.1.2; extra == "slack"
Requires-Dist: python-dateutil>=2.8.0; extra == "slack"
Requires-Dist: aiohttp<4; extra == "slack"
Requires-Dist: jsonref; extra == "slack"
Requires-Dist: docker; extra == "slack"
Requires-Dist: packaging; extra == "slack"
Requires-Dist: progressbar2; extra == "slack"
Requires-Dist: ijson; extra == "slack"
Requires-Dist: expandvars>=0.6.5; extra == "slack"
Requires-Dist: psutil>=5.8.0; extra == "slack"
Requires-Dist: jsonschema; extra == "slack"
Requires-Dist: avro-gen3==0.7.16; extra == "slack"
Requires-Dist: click-spinner; extra == "slack"
Requires-Dist: PyYAML; extra == "slack"
Requires-Dist: requests_file; extra == "slack"
Requires-Dist: tabulate; extra == "slack"
Requires-Dist: importlib_metadata>=4.0.0; python_version < "3.10" and extra == "slack"
Requires-Dist: humanfriendly; extra == "slack"
Requires-Dist: ruamel.yaml; extra == "slack"
Provides-Extra: superset
Requires-Dist: requests; extra == "superset"
Requires-Dist: click-default-group; extra == "superset"
Requires-Dist: Deprecated; extra == "superset"
Requires-Dist: toml>=0.10.0; extra == "superset"
Requires-Dist: pydantic<2; extra == "superset"
Requires-Dist: avro<1.12,>=1.11.3; extra == "superset"
Requires-Dist: cached_property; extra == "superset"
Requires-Dist: click>=7.1.2; extra == "superset"
Requires-Dist: python-dateutil>=2.8.0; extra == "superset"
Requires-Dist: sqlalchemy; extra == "superset"
Requires-Dist: aiohttp<4; extra == "superset"
Requires-Dist: jsonref; extra == "superset"
Requires-Dist: docker; extra == "superset"
Requires-Dist: packaging; extra == "superset"
Requires-Dist: progressbar2; extra == "superset"
Requires-Dist: ijson; extra == "superset"
Requires-Dist: expandvars>=0.6.5; extra == "superset"
Requires-Dist: psutil>=5.8.0; extra == "superset"
Requires-Dist: jsonschema; extra == "superset"
Requires-Dist: greenlet; extra == "superset"
Requires-Dist: avro-gen3==0.7.16; extra == "superset"
Requires-Dist: click-spinner; extra == "superset"
Requires-Dist: great_expectations; extra == "superset"
Requires-Dist: PyYAML; extra == "superset"
Requires-Dist: requests_file; extra == "superset"
Requires-Dist: tabulate; extra == "superset"
Requires-Dist: importlib_metadata>=4.0.0; python_version < "3.10" and extra == "superset"
Requires-Dist: humanfriendly; extra == "superset"
Requires-Dist: ruamel.yaml; extra == "superset"
Provides-Extra: preset
Requires-Dist: requests; extra == "preset"
Requires-Dist: click-default-group; extra == "preset"
Requires-Dist: Deprecated; extra == "preset"
Requires-Dist: toml>=0.10.0; extra == "preset"
Requires-Dist: pydantic<2; extra == "preset"
Requires-Dist: avro<1.12,>=1.11.3; extra == "preset"
Requires-Dist: cached_property; extra == "preset"
Requires-Dist: click>=7.1.2; extra == "preset"
Requires-Dist: python-dateutil>=2.8.0; extra == "preset"
Requires-Dist: sqlalchemy; extra == "preset"
Requires-Dist: aiohttp<4; extra == "preset"
Requires-Dist: jsonref; extra == "preset"
Requires-Dist: docker; extra == "preset"
Requires-Dist: packaging; extra == "preset"
Requires-Dist: progressbar2; extra == "preset"
Requires-Dist: ijson; extra == "preset"
Requires-Dist: expandvars>=0.6.5; extra == "preset"
Requires-Dist: psutil>=5.8.0; extra == "preset"
Requires-Dist: jsonschema; extra == "preset"
Requires-Dist: greenlet; extra == "preset"
Requires-Dist: avro-gen3==0.7.16; extra == "preset"
Requires-Dist: click-spinner; extra == "preset"
Requires-Dist: great_expectations; extra == "preset"
Requires-Dist: PyYAML; extra == "preset"
Requires-Dist: requests_file; extra == "preset"
Requires-Dist: tabulate; extra == "preset"
Requires-Dist: importlib_metadata>=4.0.0; python_version < "3.10" and extra == "preset"
Requires-Dist: humanfriendly; extra == "preset"
Requires-Dist: ruamel.yaml; extra == "preset"
Provides-Extra: tableau
Requires-Dist: click-default-group; extra == "tableau"
Requires-Dist: Deprecated; extra == "tableau"
Requires-Dist: toml>=0.10.0; extra == "tableau"
Requires-Dist: pydantic<2; extra == "tableau"
Requires-Dist: avro<1.12,>=1.11.3; extra == "tableau"
Requires-Dist: cached_property; extra == "tableau"
Requires-Dist: click>=7.1.2; extra == "tableau"
Requires-Dist: python-dateutil>=2.8.0; extra == "tableau"
Requires-Dist: aiohttp<4; extra == "tableau"
Requires-Dist: jsonref; extra == "tableau"
Requires-Dist: docker; extra == "tableau"
Requires-Dist: sqlglot[rs]==25.32.1; extra == "tableau"
Requires-Dist: packaging; extra == "tableau"
Requires-Dist: progressbar2; extra == "tableau"
Requires-Dist: ijson; extra == "tableau"
Requires-Dist: patchy==2.8.0; extra == "tableau"
Requires-Dist: expandvars>=0.6.5; extra == "tableau"
Requires-Dist: tableauserverclient>=0.24.0; extra == "tableau"
Requires-Dist: psutil>=5.8.0; extra == "tableau"
Requires-Dist: jsonschema; extra == "tableau"
Requires-Dist: avro-gen3==0.7.16; extra == "tableau"
Requires-Dist: click-spinner; extra == "tableau"
Requires-Dist: PyYAML; extra == "tableau"
Requires-Dist: requests_file; extra == "tableau"
Requires-Dist: tabulate; extra == "tableau"
Requires-Dist: importlib_metadata>=4.0.0; python_version < "3.10" and extra == "tableau"
Requires-Dist: humanfriendly; extra == "tableau"
Requires-Dist: ruamel.yaml; extra == "tableau"
Provides-Extra: teradata
Requires-Dist: toml>=0.10.0; extra == "teradata"
Requires-Dist: pydantic<2; extra == "teradata"
Requires-Dist: sqlalchemy<2,>=1.4.39; extra == "teradata"
Requires-Dist: cached_property; extra == "teradata"
Requires-Dist: click>=7.1.2; extra == "teradata"
Requires-Dist: scipy>=1.7.2; extra == "teradata"
Requires-Dist: schwifty<2024.08.0; extra == "teradata"
Requires-Dist: docker; extra == "teradata"
Requires-Dist: progressbar2; extra == "teradata"
Requires-Dist: patchy==2.8.0; extra == "teradata"
Requires-Dist: expandvars>=0.6.5; extra == "teradata"
Requires-Dist: traitlets!=5.2.2; extra == "teradata"
Requires-Dist: psutil>=5.8.0; extra == "teradata"
Requires-Dist: avro-gen3==0.7.16; extra == "teradata"
Requires-Dist: cachetools; extra == "teradata"
Requires-Dist: PyYAML; extra == "teradata"
Requires-Dist: requests_file; extra == "teradata"
Requires-Dist: importlib_metadata>=4.0.0; python_version < "3.10" and extra == "teradata"
Requires-Dist: teradatasqlalchemy<=20.0.0.2,>=17.20.0.0; extra == "teradata"
Requires-Dist: click-default-group; extra == "teradata"
Requires-Dist: Deprecated; extra == "teradata"
Requires-Dist: IPython!=8.22.0; extra == "teradata"
Requires-Dist: pip; extra == "teradata"
Requires-Dist: avro<1.12,>=1.11.3; extra == "teradata"
Requires-Dist: acryl-datahub-classify==0.0.11; extra == "teradata"
Requires-Dist: python-dateutil>=2.8.0; extra == "teradata"
Requires-Dist: aiohttp<4; extra == "teradata"
Requires-Dist: jsonref; extra == "teradata"
Requires-Dist: sqlglot[rs]==25.32.1; extra == "teradata"
Requires-Dist: packaging; extra == "teradata"
Requires-Dist: ijson; extra == "teradata"
Requires-Dist: jsonschema; extra == "teradata"
Requires-Dist: greenlet; extra == "teradata"
Requires-Dist: click-spinner; extra == "teradata"
Requires-Dist: numpy<2; extra == "teradata"
Requires-Dist: great-expectations<=0.15.50,>=0.15.12; extra == "teradata"
Requires-Dist: tabulate; extra == "teradata"
Requires-Dist: humanfriendly; extra == "teradata"
Requires-Dist: sqlparse; extra == "teradata"
Requires-Dist: ruamel.yaml; extra == "teradata"
Provides-Extra: trino
Requires-Dist: toml>=0.10.0; extra == "trino"
Requires-Dist: pydantic<2; extra == "trino"
Requires-Dist: sqlalchemy<2,>=1.4.39; extra == "trino"
Requires-Dist: cached_property; extra == "trino"
Requires-Dist: click>=7.1.2; extra == "trino"
Requires-Dist: scipy>=1.7.2; extra == "trino"
Requires-Dist: schwifty<2024.08.0; extra == "trino"
Requires-Dist: docker; extra == "trino"
Requires-Dist: progressbar2; extra == "trino"
Requires-Dist: patchy==2.8.0; extra == "trino"
Requires-Dist: expandvars>=0.6.5; extra == "trino"
Requires-Dist: traitlets!=5.2.2; extra == "trino"
Requires-Dist: trino[sqlalchemy]>=0.308; extra == "trino"
Requires-Dist: psutil>=5.8.0; extra == "trino"
Requires-Dist: avro-gen3==0.7.16; extra == "trino"
Requires-Dist: cachetools; extra == "trino"
Requires-Dist: PyYAML; extra == "trino"
Requires-Dist: requests_file; extra == "trino"
Requires-Dist: importlib_metadata>=4.0.0; python_version < "3.10" and extra == "trino"
Requires-Dist: click-default-group; extra == "trino"
Requires-Dist: Deprecated; extra == "trino"
Requires-Dist: IPython!=8.22.0; extra == "trino"
Requires-Dist: pip; extra == "trino"
Requires-Dist: avro<1.12,>=1.11.3; extra == "trino"
Requires-Dist: acryl-datahub-classify==0.0.11; extra == "trino"
Requires-Dist: python-dateutil>=2.8.0; extra == "trino"
Requires-Dist: aiohttp<4; extra == "trino"
Requires-Dist: jsonref; extra == "trino"
Requires-Dist: sqlglot[rs]==25.32.1; extra == "trino"
Requires-Dist: packaging; extra == "trino"
Requires-Dist: ijson; extra == "trino"
Requires-Dist: jsonschema; extra == "trino"
Requires-Dist: greenlet; extra == "trino"
Requires-Dist: click-spinner; extra == "trino"
Requires-Dist: numpy<2; extra == "trino"
Requires-Dist: great-expectations<=0.15.50,>=0.15.12; extra == "trino"
Requires-Dist: tabulate; extra == "trino"
Requires-Dist: humanfriendly; extra == "trino"
Requires-Dist: sqlparse; extra == "trino"
Requires-Dist: ruamel.yaml; extra == "trino"
Provides-Extra: starburst-trino-usage
Requires-Dist: toml>=0.10.0; extra == "starburst-trino-usage"
Requires-Dist: pydantic<2; extra == "starburst-trino-usage"
Requires-Dist: sqlalchemy<2,>=1.4.39; extra == "starburst-trino-usage"
Requires-Dist: cached_property; extra == "starburst-trino-usage"
Requires-Dist: click>=7.1.2; extra == "starburst-trino-usage"
Requires-Dist: scipy>=1.7.2; extra == "starburst-trino-usage"
Requires-Dist: schwifty<2024.08.0; extra == "starburst-trino-usage"
Requires-Dist: docker; extra == "starburst-trino-usage"
Requires-Dist: progressbar2; extra == "starburst-trino-usage"
Requires-Dist: patchy==2.8.0; extra == "starburst-trino-usage"
Requires-Dist: expandvars>=0.6.5; extra == "starburst-trino-usage"
Requires-Dist: traitlets!=5.2.2; extra == "starburst-trino-usage"
Requires-Dist: trino[sqlalchemy]>=0.308; extra == "starburst-trino-usage"
Requires-Dist: psutil>=5.8.0; extra == "starburst-trino-usage"
Requires-Dist: avro-gen3==0.7.16; extra == "starburst-trino-usage"
Requires-Dist: cachetools; extra == "starburst-trino-usage"
Requires-Dist: PyYAML; extra == "starburst-trino-usage"
Requires-Dist: requests_file; extra == "starburst-trino-usage"
Requires-Dist: importlib_metadata>=4.0.0; python_version < "3.10" and extra == "starburst-trino-usage"
Requires-Dist: click-default-group; extra == "starburst-trino-usage"
Requires-Dist: Deprecated; extra == "starburst-trino-usage"
Requires-Dist: IPython!=8.22.0; extra == "starburst-trino-usage"
Requires-Dist: pip; extra == "starburst-trino-usage"
Requires-Dist: avro<1.12,>=1.11.3; extra == "starburst-trino-usage"
Requires-Dist: acryl-datahub-classify==0.0.11; extra == "starburst-trino-usage"
Requires-Dist: python-dateutil>=2.8.0; extra == "starburst-trino-usage"
Requires-Dist: aiohttp<4; extra == "starburst-trino-usage"
Requires-Dist: jsonref; extra == "starburst-trino-usage"
Requires-Dist: sqlglot[rs]==25.32.1; extra == "starburst-trino-usage"
Requires-Dist: packaging; extra == "starburst-trino-usage"
Requires-Dist: ijson; extra == "starburst-trino-usage"
Requires-Dist: jsonschema; extra == "starburst-trino-usage"
Requires-Dist: greenlet; extra == "starburst-trino-usage"
Requires-Dist: click-spinner; extra == "starburst-trino-usage"
Requires-Dist: numpy<2; extra == "starburst-trino-usage"
Requires-Dist: great-expectations<=0.15.50,>=0.15.12; extra == "starburst-trino-usage"
Requires-Dist: tabulate; extra == "starburst-trino-usage"
Requires-Dist: humanfriendly; extra == "starburst-trino-usage"
Requires-Dist: sqlparse; extra == "starburst-trino-usage"
Requires-Dist: ruamel.yaml; extra == "starburst-trino-usage"
Provides-Extra: nifi
Requires-Dist: requests; extra == "nifi"
Requires-Dist: click-default-group; extra == "nifi"
Requires-Dist: Deprecated; extra == "nifi"
Requires-Dist: toml>=0.10.0; extra == "nifi"
Requires-Dist: pydantic<2; extra == "nifi"
Requires-Dist: avro<1.12,>=1.11.3; extra == "nifi"
Requires-Dist: cached_property; extra == "nifi"
Requires-Dist: click>=7.1.2; extra == "nifi"
Requires-Dist: python-dateutil>=2.8.0; extra == "nifi"
Requires-Dist: requests-gssapi; extra == "nifi"
Requires-Dist: aiohttp<4; extra == "nifi"
Requires-Dist: jsonref; extra == "nifi"
Requires-Dist: docker; extra == "nifi"
Requires-Dist: packaging; extra == "nifi"
Requires-Dist: progressbar2; extra == "nifi"
Requires-Dist: ijson; extra == "nifi"
Requires-Dist: expandvars>=0.6.5; extra == "nifi"
Requires-Dist: psutil>=5.8.0; extra == "nifi"
Requires-Dist: jsonschema; extra == "nifi"
Requires-Dist: avro-gen3==0.7.16; extra == "nifi"
Requires-Dist: click-spinner; extra == "nifi"
Requires-Dist: PyYAML; extra == "nifi"
Requires-Dist: requests_file; extra == "nifi"
Requires-Dist: tabulate; extra == "nifi"
Requires-Dist: importlib_metadata>=4.0.0; python_version < "3.10" and extra == "nifi"
Requires-Dist: humanfriendly; extra == "nifi"
Requires-Dist: ruamel.yaml; extra == "nifi"
Provides-Extra: powerbi
Requires-Dist: click-default-group; extra == "powerbi"
Requires-Dist: Deprecated; extra == "powerbi"
Requires-Dist: msal>=1.24.0; extra == "powerbi"
Requires-Dist: toml>=0.10.0; extra == "powerbi"
Requires-Dist: pydantic<2; extra == "powerbi"
Requires-Dist: avro<1.12,>=1.11.3; extra == "powerbi"
Requires-Dist: cached_property; extra == "powerbi"
Requires-Dist: click>=7.1.2; extra == "powerbi"
Requires-Dist: python-dateutil>=2.8.0; extra == "powerbi"
Requires-Dist: aiohttp<4; extra == "powerbi"
Requires-Dist: jsonref; extra == "powerbi"
Requires-Dist: docker; extra == "powerbi"
Requires-Dist: sqlglot[rs]==25.32.1; extra == "powerbi"
Requires-Dist: packaging; extra == "powerbi"
Requires-Dist: lark[regex]==1.1.4; extra == "powerbi"
Requires-Dist: progressbar2; extra == "powerbi"
Requires-Dist: ijson; extra == "powerbi"
Requires-Dist: patchy==2.8.0; extra == "powerbi"
Requires-Dist: expandvars>=0.6.5; extra == "powerbi"
Requires-Dist: psutil>=5.8.0; extra == "powerbi"
Requires-Dist: setuptools; extra == "powerbi"
Requires-Dist: jsonschema; extra == "powerbi"
Requires-Dist: avro-gen3==0.7.16; extra == "powerbi"
Requires-Dist: click-spinner; extra == "powerbi"
Requires-Dist: PyYAML; extra == "powerbi"
Requires-Dist: requests_file; extra == "powerbi"
Requires-Dist: tabulate; extra == "powerbi"
Requires-Dist: importlib_metadata>=4.0.0; python_version < "3.10" and extra == "powerbi"
Requires-Dist: humanfriendly; extra == "powerbi"
Requires-Dist: stopit==1.1.2; extra == "powerbi"
Requires-Dist: more-itertools; extra == "powerbi"
Requires-Dist: sqlparse; extra == "powerbi"
Requires-Dist: ruamel.yaml; extra == "powerbi"
Provides-Extra: powerbi-report-server
Requires-Dist: requests; extra == "powerbi-report-server"
Requires-Dist: click-default-group; extra == "powerbi-report-server"
Requires-Dist: Deprecated; extra == "powerbi-report-server"
Requires-Dist: toml>=0.10.0; extra == "powerbi-report-server"
Requires-Dist: pydantic<2; extra == "powerbi-report-server"
Requires-Dist: avro<1.12,>=1.11.3; extra == "powerbi-report-server"
Requires-Dist: cached_property; extra == "powerbi-report-server"
Requires-Dist: click>=7.1.2; extra == "powerbi-report-server"
Requires-Dist: python-dateutil>=2.8.0; extra == "powerbi-report-server"
Requires-Dist: aiohttp<4; extra == "powerbi-report-server"
Requires-Dist: jsonref; extra == "powerbi-report-server"
Requires-Dist: docker; extra == "powerbi-report-server"
Requires-Dist: packaging; extra == "powerbi-report-server"
Requires-Dist: progressbar2; extra == "powerbi-report-server"
Requires-Dist: ijson; extra == "powerbi-report-server"
Requires-Dist: requests_ntlm; extra == "powerbi-report-server"
Requires-Dist: expandvars>=0.6.5; extra == "powerbi-report-server"
Requires-Dist: psutil>=5.8.0; extra == "powerbi-report-server"
Requires-Dist: jsonschema; extra == "powerbi-report-server"
Requires-Dist: avro-gen3==0.7.16; extra == "powerbi-report-server"
Requires-Dist: click-spinner; extra == "powerbi-report-server"
Requires-Dist: PyYAML; extra == "powerbi-report-server"
Requires-Dist: requests_file; extra == "powerbi-report-server"
Requires-Dist: tabulate; extra == "powerbi-report-server"
Requires-Dist: importlib_metadata>=4.0.0; python_version < "3.10" and extra == "powerbi-report-server"
Requires-Dist: humanfriendly; extra == "powerbi-report-server"
Requires-Dist: ruamel.yaml; extra == "powerbi-report-server"
Provides-Extra: vertica
Requires-Dist: toml>=0.10.0; extra == "vertica"
Requires-Dist: pydantic<2; extra == "vertica"
Requires-Dist: sqlalchemy<2,>=1.4.39; extra == "vertica"
Requires-Dist: cached_property; extra == "vertica"
Requires-Dist: click>=7.1.2; extra == "vertica"
Requires-Dist: scipy>=1.7.2; extra == "vertica"
Requires-Dist: schwifty<2024.08.0; extra == "vertica"
Requires-Dist: docker; extra == "vertica"
Requires-Dist: progressbar2; extra == "vertica"
Requires-Dist: patchy==2.8.0; extra == "vertica"
Requires-Dist: expandvars>=0.6.5; extra == "vertica"
Requires-Dist: traitlets!=5.2.2; extra == "vertica"
Requires-Dist: psutil>=5.8.0; extra == "vertica"
Requires-Dist: avro-gen3==0.7.16; extra == "vertica"
Requires-Dist: cachetools; extra == "vertica"
Requires-Dist: PyYAML; extra == "vertica"
Requires-Dist: requests_file; extra == "vertica"
Requires-Dist: importlib_metadata>=4.0.0; python_version < "3.10" and extra == "vertica"
Requires-Dist: vertica-sqlalchemy-dialect[vertica-python]==0.0.8.2; extra == "vertica"
Requires-Dist: click-default-group; extra == "vertica"
Requires-Dist: Deprecated; extra == "vertica"
Requires-Dist: IPython!=8.22.0; extra == "vertica"
Requires-Dist: pip; extra == "vertica"
Requires-Dist: avro<1.12,>=1.11.3; extra == "vertica"
Requires-Dist: acryl-datahub-classify==0.0.11; extra == "vertica"
Requires-Dist: python-dateutil>=2.8.0; extra == "vertica"
Requires-Dist: aiohttp<4; extra == "vertica"
Requires-Dist: jsonref; extra == "vertica"
Requires-Dist: sqlglot[rs]==25.32.1; extra == "vertica"
Requires-Dist: packaging; extra == "vertica"
Requires-Dist: ijson; extra == "vertica"
Requires-Dist: jsonschema; extra == "vertica"
Requires-Dist: greenlet; extra == "vertica"
Requires-Dist: click-spinner; extra == "vertica"
Requires-Dist: numpy<2; extra == "vertica"
Requires-Dist: great-expectations<=0.15.50,>=0.15.12; extra == "vertica"
Requires-Dist: tabulate; extra == "vertica"
Requires-Dist: humanfriendly; extra == "vertica"
Requires-Dist: sqlparse; extra == "vertica"
Requires-Dist: ruamel.yaml; extra == "vertica"
Provides-Extra: unity-catalog
Requires-Dist: requests; extra == "unity-catalog"
Requires-Dist: toml>=0.10.0; extra == "unity-catalog"
Requires-Dist: pydantic<2; extra == "unity-catalog"
Requires-Dist: sqlalchemy<2,>=1.4.39; extra == "unity-catalog"
Requires-Dist: cached_property; extra == "unity-catalog"
Requires-Dist: click>=7.1.2; extra == "unity-catalog"
Requires-Dist: scipy>=1.7.2; extra == "unity-catalog"
Requires-Dist: schwifty<2024.08.0; extra == "unity-catalog"
Requires-Dist: docker; extra == "unity-catalog"
Requires-Dist: progressbar2; extra == "unity-catalog"
Requires-Dist: patchy==2.8.0; extra == "unity-catalog"
Requires-Dist: expandvars>=0.6.5; extra == "unity-catalog"
Requires-Dist: traitlets!=5.2.2; extra == "unity-catalog"
Requires-Dist: psutil>=5.8.0; extra == "unity-catalog"
Requires-Dist: avro-gen3==0.7.16; extra == "unity-catalog"
Requires-Dist: cachetools; extra == "unity-catalog"
Requires-Dist: PyYAML; extra == "unity-catalog"
Requires-Dist: requests_file; extra == "unity-catalog"
Requires-Dist: importlib_metadata>=4.0.0; python_version < "3.10" and extra == "unity-catalog"
Requires-Dist: databricks-sql-connector<3.0.0,>=2.8.0; extra == "unity-catalog"
Requires-Dist: click-default-group; extra == "unity-catalog"
Requires-Dist: databricks-sdk>=0.30.0; extra == "unity-catalog"
Requires-Dist: Deprecated; extra == "unity-catalog"
Requires-Dist: IPython!=8.22.0; extra == "unity-catalog"
Requires-Dist: pandas<2.2.0; extra == "unity-catalog"
Requires-Dist: pip; extra == "unity-catalog"
Requires-Dist: avro<1.12,>=1.11.3; extra == "unity-catalog"
Requires-Dist: acryl-datahub-classify==0.0.11; extra == "unity-catalog"
Requires-Dist: python-dateutil>=2.8.0; extra == "unity-catalog"
Requires-Dist: aiohttp<4; extra == "unity-catalog"
Requires-Dist: jsonref; extra == "unity-catalog"
Requires-Dist: sqlglot[rs]==25.32.1; extra == "unity-catalog"
Requires-Dist: packaging; extra == "unity-catalog"
Requires-Dist: ijson; extra == "unity-catalog"
Requires-Dist: jsonschema; extra == "unity-catalog"
Requires-Dist: greenlet; extra == "unity-catalog"
Requires-Dist: click-spinner; extra == "unity-catalog"
Requires-Dist: numpy<2; extra == "unity-catalog"
Requires-Dist: great-expectations<=0.15.50,>=0.15.12; extra == "unity-catalog"
Requires-Dist: tabulate; extra == "unity-catalog"
Requires-Dist: pyspark~=3.5.0; extra == "unity-catalog"
Requires-Dist: humanfriendly; extra == "unity-catalog"
Requires-Dist: sqlparse; extra == "unity-catalog"
Requires-Dist: ruamel.yaml; extra == "unity-catalog"
Provides-Extra: databricks
Requires-Dist: requests; extra == "databricks"
Requires-Dist: toml>=0.10.0; extra == "databricks"
Requires-Dist: pydantic<2; extra == "databricks"
Requires-Dist: sqlalchemy<2,>=1.4.39; extra == "databricks"
Requires-Dist: cached_property; extra == "databricks"
Requires-Dist: click>=7.1.2; extra == "databricks"
Requires-Dist: scipy>=1.7.2; extra == "databricks"
Requires-Dist: schwifty<2024.08.0; extra == "databricks"
Requires-Dist: docker; extra == "databricks"
Requires-Dist: progressbar2; extra == "databricks"
Requires-Dist: patchy==2.8.0; extra == "databricks"
Requires-Dist: expandvars>=0.6.5; extra == "databricks"
Requires-Dist: traitlets!=5.2.2; extra == "databricks"
Requires-Dist: psutil>=5.8.0; extra == "databricks"
Requires-Dist: avro-gen3==0.7.16; extra == "databricks"
Requires-Dist: cachetools; extra == "databricks"
Requires-Dist: PyYAML; extra == "databricks"
Requires-Dist: requests_file; extra == "databricks"
Requires-Dist: importlib_metadata>=4.0.0; python_version < "3.10" and extra == "databricks"
Requires-Dist: databricks-sql-connector<3.0.0,>=2.8.0; extra == "databricks"
Requires-Dist: click-default-group; extra == "databricks"
Requires-Dist: databricks-sdk>=0.30.0; extra == "databricks"
Requires-Dist: Deprecated; extra == "databricks"
Requires-Dist: IPython!=8.22.0; extra == "databricks"
Requires-Dist: pandas<2.2.0; extra == "databricks"
Requires-Dist: pip; extra == "databricks"
Requires-Dist: avro<1.12,>=1.11.3; extra == "databricks"
Requires-Dist: acryl-datahub-classify==0.0.11; extra == "databricks"
Requires-Dist: python-dateutil>=2.8.0; extra == "databricks"
Requires-Dist: aiohttp<4; extra == "databricks"
Requires-Dist: jsonref; extra == "databricks"
Requires-Dist: sqlglot[rs]==25.32.1; extra == "databricks"
Requires-Dist: packaging; extra == "databricks"
Requires-Dist: ijson; extra == "databricks"
Requires-Dist: jsonschema; extra == "databricks"
Requires-Dist: greenlet; extra == "databricks"
Requires-Dist: click-spinner; extra == "databricks"
Requires-Dist: numpy<2; extra == "databricks"
Requires-Dist: great-expectations<=0.15.50,>=0.15.12; extra == "databricks"
Requires-Dist: tabulate; extra == "databricks"
Requires-Dist: pyspark~=3.5.0; extra == "databricks"
Requires-Dist: humanfriendly; extra == "databricks"
Requires-Dist: sqlparse; extra == "databricks"
Requires-Dist: ruamel.yaml; extra == "databricks"
Provides-Extra: fivetran
Requires-Dist: toml>=0.10.0; extra == "fivetran"
Requires-Dist: pydantic<2; extra == "fivetran"
Requires-Dist: sqlalchemy<2,>=1.4.39; extra == "fivetran"
Requires-Dist: cached_property; extra == "fivetran"
Requires-Dist: click>=7.1.2; extra == "fivetran"
Requires-Dist: snowflake-sqlalchemy>=1.4.3; extra == "fivetran"
Requires-Dist: snowflake-connector-python>=3.4.0; extra == "fivetran"
Requires-Dist: parse>=1.19.0; extra == "fivetran"
Requires-Dist: scipy>=1.7.2; extra == "fivetran"
Requires-Dist: schwifty<2024.08.0; extra == "fivetran"
Requires-Dist: docker; extra == "fivetran"
Requires-Dist: google-cloud-resource-manager; extra == "fivetran"
Requires-Dist: progressbar2; extra == "fivetran"
Requires-Dist: patchy==2.8.0; extra == "fivetran"
Requires-Dist: google-cloud-logging<=3.5.0; extra == "fivetran"
Requires-Dist: expandvars>=0.6.5; extra == "fivetran"
Requires-Dist: traitlets!=5.2.2; extra == "fivetran"
Requires-Dist: psutil>=5.8.0; extra == "fivetran"
Requires-Dist: google-cloud-datacatalog>=1.5.0; extra == "fivetran"
Requires-Dist: avro-gen3==0.7.16; extra == "fivetran"
Requires-Dist: cachetools; extra == "fivetran"
Requires-Dist: PyYAML; extra == "fivetran"
Requires-Dist: requests_file; extra == "fivetran"
Requires-Dist: importlib_metadata>=4.0.0; python_version < "3.10" and extra == "fivetran"
Requires-Dist: google-cloud-bigquery; extra == "fivetran"
Requires-Dist: msal; extra == "fivetran"
Requires-Dist: wcmatch; extra == "fivetran"
Requires-Dist: click-default-group; extra == "fivetran"
Requires-Dist: Deprecated; extra == "fivetran"
Requires-Dist: IPython!=8.22.0; extra == "fivetran"
Requires-Dist: pip; extra == "fivetran"
Requires-Dist: avro<1.12,>=1.11.3; extra == "fivetran"
Requires-Dist: acryl-datahub-classify==0.0.11; extra == "fivetran"
Requires-Dist: python-dateutil>=2.8.0; extra == "fivetran"
Requires-Dist: aiohttp<4; extra == "fivetran"
Requires-Dist: jsonref; extra == "fivetran"
Requires-Dist: more-itertools>=8.12.0; extra == "fivetran"
Requires-Dist: sqlglot[rs]==25.32.1; extra == "fivetran"
Requires-Dist: packaging; extra == "fivetran"
Requires-Dist: pandas; extra == "fivetran"
Requires-Dist: ijson; extra == "fivetran"
Requires-Dist: sqlalchemy-bigquery>=1.4.1; extra == "fivetran"
Requires-Dist: jsonschema; extra == "fivetran"
Requires-Dist: greenlet; extra == "fivetran"
Requires-Dist: cryptography; extra == "fivetran"
Requires-Dist: click-spinner; extra == "fivetran"
Requires-Dist: numpy<2; extra == "fivetran"
Requires-Dist: great-expectations<=0.15.50,>=0.15.12; extra == "fivetran"
Requires-Dist: tabulate; extra == "fivetran"
Requires-Dist: humanfriendly; extra == "fivetran"
Requires-Dist: sqlparse; extra == "fivetran"
Requires-Dist: ruamel.yaml; extra == "fivetran"
Provides-Extra: qlik-sense
Requires-Dist: requests; extra == "qlik-sense"
Requires-Dist: click-default-group; extra == "qlik-sense"
Requires-Dist: Deprecated; extra == "qlik-sense"
Requires-Dist: toml>=0.10.0; extra == "qlik-sense"
Requires-Dist: pydantic<2; extra == "qlik-sense"
Requires-Dist: avro<1.12,>=1.11.3; extra == "qlik-sense"
Requires-Dist: cached_property; extra == "qlik-sense"
Requires-Dist: click>=7.1.2; extra == "qlik-sense"
Requires-Dist: python-dateutil>=2.8.0; extra == "qlik-sense"
Requires-Dist: aiohttp<4; extra == "qlik-sense"
Requires-Dist: jsonref; extra == "qlik-sense"
Requires-Dist: websocket-client; extra == "qlik-sense"
Requires-Dist: docker; extra == "qlik-sense"
Requires-Dist: sqlglot[rs]==25.32.1; extra == "qlik-sense"
Requires-Dist: packaging; extra == "qlik-sense"
Requires-Dist: progressbar2; extra == "qlik-sense"
Requires-Dist: ijson; extra == "qlik-sense"
Requires-Dist: patchy==2.8.0; extra == "qlik-sense"
Requires-Dist: expandvars>=0.6.5; extra == "qlik-sense"
Requires-Dist: psutil>=5.8.0; extra == "qlik-sense"
Requires-Dist: jsonschema; extra == "qlik-sense"
Requires-Dist: avro-gen3==0.7.16; extra == "qlik-sense"
Requires-Dist: click-spinner; extra == "qlik-sense"
Requires-Dist: PyYAML; extra == "qlik-sense"
Requires-Dist: requests_file; extra == "qlik-sense"
Requires-Dist: tabulate; extra == "qlik-sense"
Requires-Dist: importlib_metadata>=4.0.0; python_version < "3.10" and extra == "qlik-sense"
Requires-Dist: humanfriendly; extra == "qlik-sense"
Requires-Dist: ruamel.yaml; extra == "qlik-sense"
Provides-Extra: sigma
Requires-Dist: requests; extra == "sigma"
Requires-Dist: click-default-group; extra == "sigma"
Requires-Dist: Deprecated; extra == "sigma"
Requires-Dist: toml>=0.10.0; extra == "sigma"
Requires-Dist: pydantic<2; extra == "sigma"
Requires-Dist: avro<1.12,>=1.11.3; extra == "sigma"
Requires-Dist: cached_property; extra == "sigma"
Requires-Dist: click>=7.1.2; extra == "sigma"
Requires-Dist: python-dateutil>=2.8.0; extra == "sigma"
Requires-Dist: aiohttp<4; extra == "sigma"
Requires-Dist: jsonref; extra == "sigma"
Requires-Dist: docker; extra == "sigma"
Requires-Dist: sqlglot[rs]==25.32.1; extra == "sigma"
Requires-Dist: packaging; extra == "sigma"
Requires-Dist: progressbar2; extra == "sigma"
Requires-Dist: ijson; extra == "sigma"
Requires-Dist: patchy==2.8.0; extra == "sigma"
Requires-Dist: expandvars>=0.6.5; extra == "sigma"
Requires-Dist: psutil>=5.8.0; extra == "sigma"
Requires-Dist: jsonschema; extra == "sigma"
Requires-Dist: avro-gen3==0.7.16; extra == "sigma"
Requires-Dist: click-spinner; extra == "sigma"
Requires-Dist: PyYAML; extra == "sigma"
Requires-Dist: requests_file; extra == "sigma"
Requires-Dist: tabulate; extra == "sigma"
Requires-Dist: importlib_metadata>=4.0.0; python_version < "3.10" and extra == "sigma"
Requires-Dist: humanfriendly; extra == "sigma"
Requires-Dist: ruamel.yaml; extra == "sigma"
Provides-Extra: sac
Requires-Dist: requests; extra == "sac"
Requires-Dist: click-default-group; extra == "sac"
Requires-Dist: Deprecated; extra == "sac"
Requires-Dist: toml>=0.10.0; extra == "sac"
Requires-Dist: pydantic<2; extra == "sac"
Requires-Dist: avro<1.12,>=1.11.3; extra == "sac"
Requires-Dist: cached_property; extra == "sac"
Requires-Dist: click>=7.1.2; extra == "sac"
Requires-Dist: python-dateutil>=2.8.0; extra == "sac"
Requires-Dist: aiohttp<4; extra == "sac"
Requires-Dist: jsonref; extra == "sac"
Requires-Dist: Authlib; extra == "sac"
Requires-Dist: docker; extra == "sac"
Requires-Dist: packaging; extra == "sac"
Requires-Dist: progressbar2; extra == "sac"
Requires-Dist: ijson; extra == "sac"
Requires-Dist: expandvars>=0.6.5; extra == "sac"
Requires-Dist: psutil>=5.8.0; extra == "sac"
Requires-Dist: jsonschema; extra == "sac"
Requires-Dist: avro-gen3==0.7.16; extra == "sac"
Requires-Dist: click-spinner; extra == "sac"
Requires-Dist: PyYAML; extra == "sac"
Requires-Dist: requests_file; extra == "sac"
Requires-Dist: tabulate; extra == "sac"
Requires-Dist: importlib_metadata>=4.0.0; python_version < "3.10" and extra == "sac"
Requires-Dist: pyodata>=1.11.1; extra == "sac"
Requires-Dist: humanfriendly; extra == "sac"
Requires-Dist: ruamel.yaml; extra == "sac"
Provides-Extra: neo4j
Requires-Dist: click-default-group; extra == "neo4j"
Requires-Dist: Deprecated; extra == "neo4j"
Requires-Dist: toml>=0.10.0; extra == "neo4j"
Requires-Dist: pydantic<2; extra == "neo4j"
Requires-Dist: avro<1.12,>=1.11.3; extra == "neo4j"
Requires-Dist: cached_property; extra == "neo4j"
Requires-Dist: click>=7.1.2; extra == "neo4j"
Requires-Dist: python-dateutil>=2.8.0; extra == "neo4j"
Requires-Dist: aiohttp<4; extra == "neo4j"
Requires-Dist: jsonref; extra == "neo4j"
Requires-Dist: docker; extra == "neo4j"
Requires-Dist: neo4j; extra == "neo4j"
Requires-Dist: packaging; extra == "neo4j"
Requires-Dist: pandas; extra == "neo4j"
Requires-Dist: progressbar2; extra == "neo4j"
Requires-Dist: ijson; extra == "neo4j"
Requires-Dist: expandvars>=0.6.5; extra == "neo4j"
Requires-Dist: psutil>=5.8.0; extra == "neo4j"
Requires-Dist: jsonschema; extra == "neo4j"
Requires-Dist: avro-gen3==0.7.16; extra == "neo4j"
Requires-Dist: click-spinner; extra == "neo4j"
Requires-Dist: PyYAML; extra == "neo4j"
Requires-Dist: requests_file; extra == "neo4j"
Requires-Dist: tabulate; extra == "neo4j"
Requires-Dist: importlib_metadata>=4.0.0; python_version < "3.10" and extra == "neo4j"
Requires-Dist: humanfriendly; extra == "neo4j"
Requires-Dist: ruamel.yaml; extra == "neo4j"
Provides-Extra: all
Requires-Dist: toml>=0.10.0; extra == "all"
Requires-Dist: sqlalchemy<2,>=1.4.39; extra == "all"
Requires-Dist: cached_property; extra == "all"
Requires-Dist: parse>=1.19.0; extra == "all"
Requires-Dist: botocore!=1.23.0; extra == "all"
Requires-Dist: azure-storage-file-datalake>=12.14.0; extra == "all"
Requires-Dist: pyiceberg>=0.4.0; extra == "all"
Requires-Dist: google-cloud-resource-manager; extra == "all"
Requires-Dist: progressbar2; extra == "all"
Requires-Dist: patchy==2.8.0; extra == "all"
Requires-Dist: traitlets!=5.2.2; extra == "all"
Requires-Dist: sqlalchemy-hana>=0.5.0; (platform_machine != "aarch64" and platform_machine != "arm64") and extra == "all"
Requires-Dist: google-cloud-datacatalog>=1.5.0; extra == "all"
Requires-Dist: PyYAML; extra == "all"
Requires-Dist: gql[requests]>=3.3.0; extra == "all"
Requires-Dist: tenacity!=8.4.0; extra == "all"
Requires-Dist: gql>=3.3.0; extra == "all"
Requires-Dist: wcmatch; extra == "all"
Requires-Dist: pandas<2.2.0; extra == "all"
Requires-Dist: acryl-datahub-classify==0.0.11; extra == "all"
Requires-Dist: aiohttp<4; extra == "all"
Requires-Dist: simple-salesforce; extra == "all"
Requires-Dist: neo4j; extra == "all"
Requires-Dist: GitPython>2; extra == "all"
Requires-Dist: grpcio<2,>=1.44.0; extra == "all"
Requires-Dist: python-ldap>=2.4; extra == "all"
Requires-Dist: db-dtypes; extra == "all"
Requires-Dist: psycopg2-binary; extra == "all"
Requires-Dist: greenlet; extra == "all"
Requires-Dist: PyAthena[SQLAlchemy]<3.0.0,>=2.6.0; extra == "all"
Requires-Dist: tabulate; extra == "all"
Requires-Dist: sqlalchemy-redshift>=0.8.3; extra == "all"
Requires-Dist: smart-open[azure]>=5.2.1; extra == "all"
Requires-Dist: scipy>=1.7.2; extra == "all"
Requires-Dist: ruamel.yaml; extra == "all"
Requires-Dist: networkx>=2.6.2; extra == "all"
Requires-Dist: great_expectations; extra == "all"
Requires-Dist: msal>=1.24.0; extra == "all"
Requires-Dist: pydantic<2; extra == "all"
Requires-Dist: snowflake-sqlalchemy>=1.4.3; extra == "all"
Requires-Dist: smart-open[s3]>=5.2.1; extra == "all"
Requires-Dist: snowflake-connector-python>=3.4.0; extra == "all"
Requires-Dist: docker; extra == "all"
Requires-Dist: clickhouse-sqlalchemy<0.2.5,>=0.2.0; extra == "all"
Requires-Dist: redshift-connector>=2.1.5; extra == "all"
Requires-Dist: okta~=1.7.0; extra == "all"
Requires-Dist: trino[sqlalchemy]>=0.308; extra == "all"
Requires-Dist: psutil>=5.8.0; extra == "all"
Requires-Dist: cachetools; extra == "all"
Requires-Dist: requests_file; extra == "all"
Requires-Dist: great-expectations!=0.15.23,!=0.15.24,!=0.15.25,!=0.15.26; extra == "all"
Requires-Dist: databricks-sdk>=0.30.0; extra == "all"
Requires-Dist: Deprecated; extra == "all"
Requires-Dist: more_itertools; extra == "all"
Requires-Dist: deepmerge>=1.1.1; extra == "all"
Requires-Dist: jsonref; extra == "all"
Requires-Dist: websocket-client; extra == "all"
Requires-Dist: grpcio-tools<2,>=1.44.0; extra == "all"
Requires-Dist: lkml>=1.3.4; extra == "all"
Requires-Dist: mlflow-skinny>=2.3.0; extra == "all"
Requires-Dist: sqlglot[rs]==25.32.1; extra == "all"
Requires-Dist: ijson; extra == "all"
Requires-Dist: tableauserverclient>=0.24.0; extra == "all"
Requires-Dist: sqlalchemy-cockroachdb<2.0.0; extra == "all"
Requires-Dist: jsonschema; extra == "all"
Requires-Dist: click-spinner; extra == "all"
Requires-Dist: acryl-pyhive[hive-pure-sasl]==0.6.16; extra == "all"
Requires-Dist: great-expectations<=0.15.50,>=0.15.12; extra == "all"
Requires-Dist: pyOpenSSL; extra == "all"
Requires-Dist: requests; extra == "all"
Requires-Dist: slack-sdk==3.18.1; extra == "all"
Requires-Dist: pymongo[srv]>=3.11; extra == "all"
Requires-Dist: deltalake!=0.6.4,<0.18.0,>=0.6.3; (platform_system == "Darwin" and platform_machine == "arm64") and extra == "all"
Requires-Dist: deltalake!=0.6.4,>=0.6.3; (platform_system != "Darwin" or platform_machine != "arm64") and extra == "all"
Requires-Dist: google-cloud-datacatalog-lineage==0.2.2; extra == "all"
Requires-Dist: sqlalchemy; extra == "all"
Requires-Dist: requests-gssapi; extra == "all"
Requires-Dist: elasticsearch==7.13.4; extra == "all"
Requires-Dist: schwifty<2024.08.0; extra == "all"
Requires-Dist: moto[s3]<5.0.0; extra == "all"
Requires-Dist: sqlalchemy-pytds>=0.3; extra == "all"
Requires-Dist: tenacity>=8.0.1; extra == "all"
Requires-Dist: requests_ntlm; extra == "all"
Requires-Dist: azure-core==1.29.4; extra == "all"
Requires-Dist: confluent_kafka[schemaregistry]>=1.9.0; extra == "all"
Requires-Dist: importlib_metadata>=4.0.0; python_version < "3.10" and extra == "all"
Requires-Dist: pydeequ>=1.1.0; extra == "all"
Requires-Dist: teradatasqlalchemy<=20.0.0.2,>=17.20.0.0; extra == "all"
Requires-Dist: databricks-sql-connector<3.0.0,>=2.8.0; extra == "all"
Requires-Dist: google-cloud-bigquery; extra == "all"
Requires-Dist: msal; extra == "all"
Requires-Dist: vertica-sqlalchemy-dialect[vertica-python]==0.0.8.2; extra == "all"
Requires-Dist: GeoAlchemy2; extra == "all"
Requires-Dist: filelock; extra == "all"
Requires-Dist: ujson>=5.2.0; extra == "all"
Requires-Dist: databricks-dbapi; extra == "all"
Requires-Dist: avro<1.12,>=1.11.3; extra == "all"
Requires-Dist: looker-sdk>=23.0.0; extra == "all"
Requires-Dist: python-dateutil>=2.8.0; extra == "all"
Requires-Dist: packaging; extra == "all"
Requires-Dist: oracledb; extra == "all"
Requires-Dist: sqlalchemy-bigquery>=1.4.1; extra == "all"
Requires-Dist: setuptools; extra == "all"
Requires-Dist: fastavro>=1.2.0; extra == "all"
Requires-Dist: pymysql>=1.0.2; extra == "all"
Requires-Dist: pyodata>=1.11.1; extra == "all"
Requires-Dist: cassandra-driver>=3.28.0; extra == "all"
Requires-Dist: pyarrow>=6.0.1; extra == "all"
Requires-Dist: hdbcli>=2.11.20; (platform_machine != "aarch64" and platform_machine != "arm64") and extra == "all"
Requires-Dist: tableschema>=1.20.2; extra == "all"
Requires-Dist: click>=7.1.2; extra == "all"
Requires-Dist: boto3; extra == "all"
Requires-Dist: lark[regex]==1.1.4; extra == "all"
Requires-Dist: google-cloud-logging<=3.5.0; extra == "all"
Requires-Dist: expandvars>=0.6.5; extra == "all"
Requires-Dist: python-liquid; extra == "all"
Requires-Dist: sql-metadata; extra == "all"
Requires-Dist: avro-gen3==0.7.16; extra == "all"
Requires-Dist: azure-identity>=1.17.1; extra == "all"
Requires-Dist: click-default-group; extra == "all"
Requires-Dist: IPython!=8.22.0; extra == "all"
Requires-Dist: pip; extra == "all"
Requires-Dist: redash-toolbelt; extra == "all"
Requires-Dist: pydruid>=0.6.2; extra == "all"
Requires-Dist: Authlib; extra == "all"
Requires-Dist: more-itertools>=8.12.0; extra == "all"
Requires-Dist: pandas; extra == "all"
Requires-Dist: azure-storage-blob>=12.19.0; extra == "all"
Requires-Dist: JPype1; extra == "all"
Requires-Dist: cryptography; extra == "all"
Requires-Dist: numpy<2; extra == "all"
Requires-Dist: pyspark~=3.5.0; extra == "all"
Requires-Dist: humanfriendly; extra == "all"
Requires-Dist: stopit==1.1.2; extra == "all"
Requires-Dist: more-itertools; extra == "all"
Requires-Dist: sqlparse; extra == "all"
Requires-Dist: nest-asyncio; extra == "all"
Provides-Extra: cloud
Requires-Dist: acryl-datahub-cloud; extra == "cloud"
Provides-Extra: dev
Requires-Dist: toml>=0.10.0; extra == "dev"
Requires-Dist: duckdb; extra == "dev"
Requires-Dist: botocore!=1.23.0; extra == "dev"
Requires-Dist: cached_property; extra == "dev"
Requires-Dist: types-cachetools; extra == "dev"
Requires-Dist: parse>=1.19.0; extra == "dev"
Requires-Dist: azure-storage-file-datalake>=12.14.0; extra == "dev"
Requires-Dist: sqlalchemy<2,>=1.4.39; extra == "dev"
Requires-Dist: pyiceberg>=0.4.0; extra == "dev"
Requires-Dist: boto3-stubs[dynamodb,glue,s3,sagemaker,sts]==1.28.15; extra == "dev"
Requires-Dist: google-cloud-resource-manager; extra == "dev"
Requires-Dist: progressbar2; extra == "dev"
Requires-Dist: patchy==2.8.0; extra == "dev"
Requires-Dist: ruff==0.9.2; extra == "dev"
Requires-Dist: types-click==0.1.12; extra == "dev"
Requires-Dist: traitlets!=5.2.2; extra == "dev"
Requires-Dist: google-cloud-datacatalog>=1.5.0; extra == "dev"
Requires-Dist: pytest-asyncio>=0.16.0; extra == "dev"
Requires-Dist: PyYAML; extra == "dev"
Requires-Dist: mypy==1.10.1; extra == "dev"
Requires-Dist: pytest-docker>=1.1.0; extra == "dev"
Requires-Dist: tenacity!=8.4.0; extra == "dev"
Requires-Dist: typing-inspect; extra == "dev"
Requires-Dist: wcmatch; extra == "dev"
Requires-Dist: faker>=18.4.0; extra == "dev"
Requires-Dist: pandas<2.2.0; extra == "dev"
Requires-Dist: acryl-datahub-classify==0.0.11; extra == "dev"
Requires-Dist: flask-openid>=1.3.0; extra == "dev"
Requires-Dist: aiohttp<4; extra == "dev"
Requires-Dist: simple-salesforce; extra == "dev"
Requires-Dist: neo4j; extra == "dev"
Requires-Dist: GitPython>2; extra == "dev"
Requires-Dist: grpcio<2,>=1.44.0; extra == "dev"
Requires-Dist: python-ldap>=2.4; extra == "dev"
Requires-Dist: db-dtypes; extra == "dev"
Requires-Dist: sqlalchemy2-stubs; extra == "dev"
Requires-Dist: greenlet; extra == "dev"
Requires-Dist: psycopg2-binary; extra == "dev"
Requires-Dist: PyAthena[SQLAlchemy]<3.0.0,>=2.6.0; extra == "dev"
Requires-Dist: tabulate; extra == "dev"
Requires-Dist: types-dataclasses; extra == "dev"
Requires-Dist: sqlalchemy-redshift>=0.8.3; extra == "dev"
Requires-Dist: fastapi; extra == "dev"
Requires-Dist: smart-open[azure]>=5.2.1; extra == "dev"
Requires-Dist: ruamel.yaml; extra == "dev"
Requires-Dist: scipy>=1.7.2; extra == "dev"
Requires-Dist: sentry-sdk; extra == "dev"
Requires-Dist: networkx>=2.6.2; extra == "dev"
Requires-Dist: msal>=1.24.0; extra == "dev"
Requires-Dist: types-PyMySQL; extra == "dev"
Requires-Dist: pydantic<2; extra == "dev"
Requires-Dist: snowflake-sqlalchemy>=1.4.3; extra == "dev"
Requires-Dist: smart-open[s3]>=5.2.1; extra == "dev"
Requires-Dist: snowflake-connector-python>=3.4.0; extra == "dev"
Requires-Dist: docker; extra == "dev"
Requires-Dist: clickhouse-sqlalchemy<0.2.5,>=0.2.0; extra == "dev"
Requires-Dist: redshift-connector>=2.1.5; extra == "dev"
Requires-Dist: okta~=1.7.0; extra == "dev"
Requires-Dist: trino[sqlalchemy]>=0.308; extra == "dev"
Requires-Dist: psutil>=5.8.0; extra == "dev"
Requires-Dist: cachetools; extra == "dev"
Requires-Dist: requests_file; extra == "dev"
Requires-Dist: requests-mock; extra == "dev"
Requires-Dist: great-expectations!=0.15.23,!=0.15.24,!=0.15.25,!=0.15.26; extra == "dev"
Requires-Dist: uvicorn; extra == "dev"
Requires-Dist: types-ujson>=5.2.0; extra == "dev"
Requires-Dist: build; extra == "dev"
Requires-Dist: databricks-sdk>=0.30.0; extra == "dev"
Requires-Dist: Deprecated; extra == "dev"
Requires-Dist: types-setuptools; extra == "dev"
Requires-Dist: deepmerge>=1.1.1; extra == "dev"
Requires-Dist: jsonref; extra == "dev"
Requires-Dist: websocket-client; extra == "dev"
Requires-Dist: jsonpickle; extra == "dev"
Requires-Dist: mlflow-skinny>=2.3.0; extra == "dev"
Requires-Dist: lkml>=1.3.4; extra == "dev"
Requires-Dist: sqlglot[rs]==25.32.1; extra == "dev"
Requires-Dist: grpcio-tools<2,>=1.44.0; extra == "dev"
Requires-Dist: ijson; extra == "dev"
Requires-Dist: deepdiff!=8.0.0; extra == "dev"
Requires-Dist: sqlalchemy-cockroachdb<2.0.0; extra == "dev"
Requires-Dist: tableauserverclient>=0.24.0; extra == "dev"
Requires-Dist: jsonschema; extra == "dev"
Requires-Dist: pytest-cov>=2.8.1; extra == "dev"
Requires-Dist: click-spinner; extra == "dev"
Requires-Dist: acryl-pyhive[hive-pure-sasl]==0.6.16; extra == "dev"
Requires-Dist: great-expectations<=0.15.50,>=0.15.12; extra == "dev"
Requires-Dist: requests; extra == "dev"
Requires-Dist: slack-sdk==3.18.1; extra == "dev"
Requires-Dist: pydantic!=1.10.3,>=1.10.0; extra == "dev"
Requires-Dist: types-python-dateutil; extra == "dev"
Requires-Dist: deltalake!=0.6.4,<0.18.0,>=0.6.3; (platform_system == "Darwin" and platform_machine == "arm64") and extra == "dev"
Requires-Dist: deltalake!=0.6.4,>=0.6.3; (platform_system != "Darwin" or platform_machine != "arm64") and extra == "dev"
Requires-Dist: google-cloud-datacatalog-lineage==0.2.2; extra == "dev"
Requires-Dist: requests-gssapi; extra == "dev"
Requires-Dist: elasticsearch==7.13.4; extra == "dev"
Requires-Dist: moto[s3]<5.0.0; extra == "dev"
Requires-Dist: schwifty<2024.08.0; extra == "dev"
Requires-Dist: tenacity>=8.0.1; extra == "dev"
Requires-Dist: requests_ntlm; extra == "dev"
Requires-Dist: pytest-timeout; extra == "dev"
Requires-Dist: azure-core==1.29.4; extra == "dev"
Requires-Dist: types-pytz; extra == "dev"
Requires-Dist: confluent_kafka[schemaregistry]>=1.9.0; extra == "dev"
Requires-Dist: importlib_metadata>=4.0.0; python_version < "3.10" and extra == "dev"
Requires-Dist: types-toml; extra == "dev"
Requires-Dist: types-Deprecated; extra == "dev"
Requires-Dist: pydeequ>=1.1.0; extra == "dev"
Requires-Dist: teradatasqlalchemy<=20.0.0.2,>=17.20.0.0; extra == "dev"
Requires-Dist: databricks-sql-connector<3.0.0,>=2.8.0; extra == "dev"
Requires-Dist: google-cloud-bigquery; extra == "dev"
Requires-Dist: msal; extra == "dev"
Requires-Dist: vertica-sqlalchemy-dialect[vertica-python]==0.0.8.2; extra == "dev"
Requires-Dist: GeoAlchemy2; extra == "dev"
Requires-Dist: types-requests<=2.31.0.3,>=2.28.11.6; extra == "dev"
Requires-Dist: types-protobuf>=4.21.0.1; extra == "dev"
Requires-Dist: ujson>=5.2.0; extra == "dev"
Requires-Dist: databricks-dbapi; extra == "dev"
Requires-Dist: types-PyYAML; extra == "dev"
Requires-Dist: avro<1.12,>=1.11.3; extra == "dev"
Requires-Dist: looker-sdk>=23.0.0; extra == "dev"
Requires-Dist: python-dateutil>=2.8.0; extra == "dev"
Requires-Dist: packaging; extra == "dev"
Requires-Dist: twine; extra == "dev"
Requires-Dist: oracledb; extra == "dev"
Requires-Dist: mypy-boto3-sagemaker==1.28.15; extra == "dev"
Requires-Dist: sqlalchemy-bigquery>=1.4.1; extra == "dev"
Requires-Dist: setuptools; extra == "dev"
Requires-Dist: coverage>=5.1; extra == "dev"
Requires-Dist: fastavro>=1.2.0; extra == "dev"
Requires-Dist: pytest>=6.2.2; extra == "dev"
Requires-Dist: pymysql>=1.0.2; extra == "dev"
Requires-Dist: pyodata>=1.11.1; extra == "dev"
Requires-Dist: cassandra-driver>=3.28.0; extra == "dev"
Requires-Dist: pyarrow>=6.0.1; extra == "dev"
Requires-Dist: dask[dataframe]<2024.7.0; extra == "dev"
Requires-Dist: mixpanel>=4.9.0; extra == "dev"
Requires-Dist: tableschema>=1.20.2; extra == "dev"
Requires-Dist: click>=7.1.2; extra == "dev"
Requires-Dist: boto3; extra == "dev"
Requires-Dist: lark[regex]==1.1.4; extra == "dev"
Requires-Dist: google-cloud-logging<=3.5.0; extra == "dev"
Requires-Dist: expandvars>=0.6.5; extra == "dev"
Requires-Dist: python-liquid; extra == "dev"
Requires-Dist: types-six; extra == "dev"
Requires-Dist: feast<1,>=0.34.0; extra == "dev"
Requires-Dist: sql-metadata; extra == "dev"
Requires-Dist: avro-gen3==0.7.16; extra == "dev"
Requires-Dist: azure-identity>=1.17.1; extra == "dev"
Requires-Dist: types-click-spinner>=0.1.13.1; extra == "dev"
Requires-Dist: types-pyOpenSSL; extra == "dev"
Requires-Dist: pytest-random-order~=1.1.0; extra == "dev"
Requires-Dist: click-default-group; extra == "dev"
Requires-Dist: IPython!=8.22.0; extra == "dev"
Requires-Dist: pip; extra == "dev"
Requires-Dist: redash-toolbelt; extra == "dev"
Requires-Dist: pydruid>=0.6.2; extra == "dev"
Requires-Dist: typing_extensions>=4.2.0; extra == "dev"
Requires-Dist: Authlib; extra == "dev"
Requires-Dist: more-itertools>=8.12.0; extra == "dev"
Requires-Dist: pandas; extra == "dev"
Requires-Dist: azure-storage-blob>=12.19.0; extra == "dev"
Requires-Dist: JPype1; extra == "dev"
Requires-Dist: types-tabulate; extra == "dev"
Requires-Dist: freezegun; extra == "dev"
Requires-Dist: cryptography; extra == "dev"
Requires-Dist: numpy<2; extra == "dev"
Requires-Dist: pyspark~=3.5.0; extra == "dev"
Requires-Dist: humanfriendly; extra == "dev"
Requires-Dist: stopit==1.1.2; extra == "dev"
Requires-Dist: more-itertools; extra == "dev"
Requires-Dist: sqlparse; extra == "dev"
Requires-Dist: nest-asyncio; extra == "dev"
Provides-Extra: lint
Requires-Dist: ruff==0.9.2; extra == "lint"
Requires-Dist: mypy==1.10.1; extra == "lint"
Provides-Extra: testing-utils
Requires-Dist: PyYAML; extra == "testing-utils"
Requires-Dist: deepdiff!=8.0.0; extra == "testing-utils"
Requires-Dist: pytest-docker>=1.1.0; extra == "testing-utils"
Requires-Dist: pytest-timeout; extra == "testing-utils"
Requires-Dist: pytest>=6.2.2; extra == "testing-utils"
Provides-Extra: integration-tests
Requires-Dist: requests; extra == "integration-tests"
Requires-Dist: slack-sdk==3.18.1; extra == "integration-tests"
Requires-Dist: pymongo[srv]>=3.11; extra == "integration-tests"
Requires-Dist: pyarrow>=6.0.1; extra == "integration-tests"
Requires-Dist: deltalake!=0.6.4,<0.18.0,>=0.6.3; (platform_system == "Darwin" and platform_machine == "arm64") and extra == "integration-tests"
Requires-Dist: deltalake!=0.6.4,>=0.6.3; (platform_system != "Darwin" or platform_machine != "arm64") and extra == "integration-tests"
Requires-Dist: dask[dataframe]<2024.7.0; extra == "integration-tests"
Requires-Dist: tableschema>=1.20.2; extra == "integration-tests"
Requires-Dist: hdbcli>=2.11.20; (platform_machine != "aarch64" and platform_machine != "arm64") and extra == "integration-tests"
Requires-Dist: pydantic<2; extra == "integration-tests"
Requires-Dist: sqlalchemy<2,>=1.4.39; extra == "integration-tests"
Requires-Dist: botocore!=1.23.0; extra == "integration-tests"
Requires-Dist: parse>=1.19.0; extra == "integration-tests"
Requires-Dist: smart-open[s3]>=5.2.1; extra == "integration-tests"
Requires-Dist: azure-storage-file-datalake>=12.14.0; extra == "integration-tests"
Requires-Dist: pyiceberg>=0.4.0; extra == "integration-tests"
Requires-Dist: boto3; extra == "integration-tests"
Requires-Dist: schwifty<2024.08.0; extra == "integration-tests"
Requires-Dist: clickhouse-sqlalchemy<0.2.5,>=0.2.0; extra == "integration-tests"
Requires-Dist: moto[s3]<5.0.0; extra == "integration-tests"
Requires-Dist: sqlalchemy-pytds>=0.3; extra == "integration-tests"
Requires-Dist: patchy==2.8.0; extra == "integration-tests"
Requires-Dist: traitlets!=5.2.2; extra == "integration-tests"
Requires-Dist: sqlalchemy-hana>=0.5.0; (platform_machine != "aarch64" and platform_machine != "arm64") and extra == "integration-tests"
Requires-Dist: feast<1,>=0.34.0; extra == "integration-tests"
Requires-Dist: sql-metadata; extra == "integration-tests"
Requires-Dist: azure-core==1.29.4; extra == "integration-tests"
Requires-Dist: cachetools; extra == "integration-tests"
Requires-Dist: azure-identity>=1.17.1; extra == "integration-tests"
Requires-Dist: great-expectations!=0.15.23,!=0.15.24,!=0.15.25,!=0.15.26; extra == "integration-tests"
Requires-Dist: gql[requests]>=3.3.0; extra == "integration-tests"
Requires-Dist: pydeequ>=1.1.0; extra == "integration-tests"
Requires-Dist: tenacity!=8.4.0; extra == "integration-tests"
Requires-Dist: gql>=3.3.0; extra == "integration-tests"
Requires-Dist: vertica-sqlalchemy-dialect[vertica-python]==0.0.8.2; extra == "integration-tests"
Requires-Dist: wcmatch; extra == "integration-tests"
Requires-Dist: IPython!=8.22.0; extra == "integration-tests"
Requires-Dist: ujson>=5.2.0; extra == "integration-tests"
Requires-Dist: pip; extra == "integration-tests"
Requires-Dist: databricks-dbapi; extra == "integration-tests"
Requires-Dist: redash-toolbelt; extra == "integration-tests"
Requires-Dist: pydruid>=0.6.2; extra == "integration-tests"
Requires-Dist: acryl-datahub-classify==0.0.11; extra == "integration-tests"
Requires-Dist: flask-openid>=1.3.0; extra == "integration-tests"
Requires-Dist: more-itertools>=8.12.0; extra == "integration-tests"
Requires-Dist: sqlglot[rs]==25.32.1; extra == "integration-tests"
Requires-Dist: packaging; extra == "integration-tests"
Requires-Dist: azure-storage-blob>=12.19.0; extra == "integration-tests"
Requires-Dist: python-ldap>=2.4; extra == "integration-tests"
Requires-Dist: JPype1; extra == "integration-tests"
Requires-Dist: sqlalchemy-bigquery>=1.4.1; extra == "integration-tests"
Requires-Dist: greenlet; extra == "integration-tests"
Requires-Dist: PyAthena[SQLAlchemy]<3.0.0,>=2.6.0; extra == "integration-tests"
Requires-Dist: acryl-pyhive[hive-pure-sasl]==0.6.16; extra == "integration-tests"
Requires-Dist: numpy<2; extra == "integration-tests"
Requires-Dist: pymysql>=1.0.2; extra == "integration-tests"
Requires-Dist: great-expectations<=0.15.50,>=0.15.12; extra == "integration-tests"
Requires-Dist: pyspark~=3.5.0; extra == "integration-tests"
Requires-Dist: pyOpenSSL; extra == "integration-tests"
Requires-Dist: sqlparse; extra == "integration-tests"
Requires-Dist: smart-open[azure]>=5.2.1; extra == "integration-tests"
Requires-Dist: scipy>=1.7.2; extra == "integration-tests"
Provides-Extra: debug
Requires-Dist: memray; extra == "debug"
Dynamic: classifier
Dynamic: description
Dynamic: description-content-type
Dynamic: home-page
Dynamic: license
Dynamic: project-url
Dynamic: provides-extra
Dynamic: requires-dist
Dynamic: requires-python
Dynamic: summary
